Workbook

Sheet Corpus Summary
B2: Finalized manipulation review corpus
B3: Author-confirmed corpus; three named sources checked and included on 2 October 2026
B5: Primary category | C5: All sources | D5: Screening recommendations | E5: Added included papers | F5: Background | G5: Needs verification | H5: Final included papers
B6: VLA | C6: =COUNTIFS('Literature Register'!$B$2:$B$215,B6) -> 92 | D6: =COUNTIFS('Literature Register'!$B$2:$B$215,B6,'Literature Register'!$H$2:$H$215,"Proposed include",'Literature Register'!$J$2:$J$215,"Paper") -> 69 | E6: =COUNTIFS('Literature Register'!$B$2:$B$215,B6,'Literature Register'!$I$2:$I$215,"Include",'Literature Register'!$J$2:$J$215,"Paper",'Literature Register'!$N$2:$N$215,"<>Current manuscript") -> 9 | F6: =COUNTIFS('Literature Register'!$B$2:$B$215,B6,'Literature Register'!$H$2:$H$215,"Background") -> 18 | G6: =COUNTIFS('Literature Register'!$B$2:$B$215,B6,'Literature Register'!$H$2:$H$215,"Needs verification") -> 0 | H6: =COUNTIFS('Literature Register'!$B$2:$B$215,B6,'Literature Register'!$I$2:$I$215,"Include",'Literature Register'!$J$2:$J$215,"Paper") -> 69
B7: World model | C7: =COUNTIFS('Literature Register'!$B$2:$B$215,B7) -> 55 | D7: =COUNTIFS('Literature Register'!$B$2:$B$215,B7,'Literature Register'!$H$2:$H$215,"Proposed include",'Literature Register'!$J$2:$J$215,"Paper") -> 42 | E7: =COUNTIFS('Literature Register'!$B$2:$B$215,B7,'Literature Register'!$I$2:$I$215,"Include",'Literature Register'!$J$2:$J$215,"Paper",'Literature Register'!$N$2:$N$215,"<>Current manuscript") -> 10 | F7: =COUNTIFS('Literature Register'!$B$2:$B$215,B7,'Literature Register'!$H$2:$H$215,"Background") -> 9 | G7: =COUNTIFS('Literature Register'!$B$2:$B$215,B7,'Literature Register'!$H$2:$H$215,"Needs verification") -> 0 | H7: =COUNTIFS('Literature Register'!$B$2:$B$215,B7,'Literature Register'!$I$2:$I$215,"Include",'Literature Register'!$J$2:$J$215,"Paper") -> 42
B8: Dataset / benchmark | C8: =COUNTIFS('Literature Register'!$B$2:$B$215,B8) -> 39 | D8: =COUNTIFS('Literature Register'!$B$2:$B$215,B8,'Literature Register'!$H$2:$H$215,"Proposed include",'Literature Register'!$J$2:$J$215,"Paper") -> 33 | E8: =COUNTIFS('Literature Register'!$B$2:$B$215,B8,'Literature Register'!$I$2:$I$215,"Include",'Literature Register'!$J$2:$J$215,"Paper",'Literature Register'!$N$2:$N$215,"<>Current manuscript") -> 7 | F8: =COUNTIFS('Literature Register'!$B$2:$B$215,B8,'Literature Register'!$H$2:$H$215,"Background") -> 5 | G8: =COUNTIFS('Literature Register'!$B$2:$B$215,B8,'Literature Register'!$H$2:$H$215,"Needs verification") -> 0 | H8: =COUNTIFS('Literature Register'!$B$2:$B$215,B8,'Literature Register'!$I$2:$I$215,"Include",'Literature Register'!$J$2:$J$215,"Paper") -> 33
B9: Background / other | C9: =COUNTIFS('Literature Register'!$B$2:$B$215,B9) -> 28 | D9: =COUNTIFS('Literature Register'!$B$2:$B$215,B9,'Literature Register'!$H$2:$H$215,"Proposed include",'Literature Register'!$J$2:$J$215,"Paper") -> 0 | E9: =COUNTIFS('Literature Register'!$B$2:$B$215,B9,'Literature Register'!$I$2:$I$215,"Include",'Literature Register'!$J$2:$J$215,"Paper",'Literature Register'!$N$2:$N$215,"<>Current manuscript") -> 0 | F9: =COUNTIFS('Literature Register'!$B$2:$B$215,B9,'Literature Register'!$H$2:$H$215,"Background") -> 28 | G9: =COUNTIFS('Literature Register'!$B$2:$B$215,B9,'Literature Register'!$H$2:$H$215,"Needs verification") -> 0 | H9: =COUNTIFS('Literature Register'!$B$2:$B$215,B9,'Literature Register'!$I$2:$I$215,"Include",'Literature Register'!$J$2:$J$215,"Paper") -> 0
B10: Total distinct sources | C10: =SUM(C6:C9) -> 214 | D10: =SUM(D6:D9) -> 144 | E10: =SUM(E6:E9) -> 26 | F10: =SUM(F6:F9) -> 60 | G10: =SUM(G6:G9) -> 0 | H10: =SUM(H6:H9) -> 144
B12: Other technical/software sources | C12: =COUNTIFS('Literature Register'!$J$2:$J$215,"Technical release / software") -> 10
B13: Primary-source checks recorded | C13: =COUNTIFS('Literature Register'!$P$2:$P$215,"Primary source checked this update") -> 86
B14: Author decisions pending | C14: =COUNTIFS('Literature Register'!$I$2:$I$215,"Pending") -> 0
B15: Current citation keys accounted | C15: 186
B16: Mapped table citation occurrences | C16: 96
B18: Author-confirmed on 2 October 2026: 144 reports comprising 69 VLA, 42 world-model and 33 dataset/benchmark reports.
B19: One source is counted once by arXiv/DOI or primary-report identifier. Hybrid roles remain in Secondary roles.
B20: VLA scope: visual and language-conditioned manipulation policies and directly relevant training/inference methods.
B21: World-model scope: predictive systems with demonstrated relevance to manipulation, learned simulation, or robot control.
B22: Dataset/benchmark scope includes manipulation corpora, data-generation resources, benchmarks, and evaluation studies.
B23: Game-only, general-video, historical, survey, and method-context sources are retained as Background where appropriate.
B24: October 2 checks added three included sources and four contextual Background papers; the corpus remains 144 reports.
B25: Screening recommendations are retained separately. Final included papers are calculated from the Author decision cells.
B26: Use the filters on Literature Register and Table Coverage. All original workbook sheets and quantitative data are preserved.
B27: Year is the first arXiv submission year where available, otherwise the source year. Publication-year differences are in Notes.
B28: Table Coverage adds Seer, VPP and UWM to the retained mapping; R211–R214 are contextual citations outside the corpus.

Sheet Literature Register
A1: Record ID | B1: Primary category | C1: Model / resource | D1: Preprint / source year | E1: Paper / report title | F1: Two-sentence summary | G1: Primary source link | H1: Screening recommendation | I1: Author decision | J1: Source type | K1: Subtype | L1: Secondary roles | M1: Domain scope | N1: Discovery origin | O1: Canonical identifier | P1: Source verification | Q1: Checked date | R1: Source locator | S1: Citation keys | T1: Manuscript locations | U1: Decision reason | V1: Notes
A2: R001 | B2: VLA | C2: 3D-CAVLA | D2: 2025 | E2: 3D CAVLA: Leveraging Depth and 3D Context to Generalize Vision-Language-Action Models for Unseen Tasks | F2: 3D-CAVLA combines depth information, task-relevant visual regions, and intermediate reasoning for VLA adaptation. These cues support manipulation in tasks beyond those seen during training. | G2: https://arxiv.org/abs/2505.05800 | H2: Proposed include | I2: Include | J2: Paper | K2: Language-conditioned spatial manipulation policy | M2: manipulation | N2: Current manuscript | O2: arXiv:2505.05800 | P2: Prior primary-source check retained | R2: Established companion catalogue primary-source trace; not freshly rechecked this update. | S2: cavla | T2: Companion model catalogue; SectionIV | U2: Primary report proposes a visually and linguistically conditioned manipulation policy or a directly evaluated VLA training/inference method.
A3: R002 | B3: VLA | C3: 3D-VLA | D3: 2024 | E3: 3D-VLA: A 3D Vision-Language-Action Generative World Model | F3: 3D-VLA combines three-dimensional vision-language representations with generation of future observations and robot actions. It connects spatial grounding with predictive policy learning for manipulation. | G3: https://arxiv.org/abs/2403.09631 | H3: Proposed include | I3: Include | J3: Paper | K3: Predictive VLA policy | L3: WM / predictive-policy overlap | M3: manipulation | N3: Current manuscript | O3: arXiv:2403.09631 | P3: Prior primary-source check retained | R3: Established companion catalogue primary-source trace; not freshly rechecked this update. | S3: threedvla | T3: Companion model catalogue; SectionIV; Table2/tab:vla-master; tab:vla-master | U3: Primary report proposes a visually and linguistically conditioned manipulation policy or a directly evaluated VLA training/inference method. | V3: One report only; predictive-policy secondary tag does not generate a second WM count.
A4: R003 | B4: VLA | C4: Act3D (language-conditioned 3D policy) | D4: 2023 | E4: Act3D: 3D Feature Field Transformers for Multi-Task Robotic Manipulation | F4: Act3D uses a hierarchical three-dimensional feature field with task-instruction conditioning to predict manipulation actions. Coarse-to-fine spatial sampling concentrates computation where precise action prediction is needed. | G4: https://arxiv.org/abs/2306.17817 | H4: Proposed include | I4: Include | J4: Paper | K4: Language-conditioned spatial manipulation policy | M4: manipulation | N4: Current manuscript | O4: arXiv:2306.17817 | P4: Prior primary-source check retained | R4: Established companion catalogue primary-source trace; not freshly rechecked this update. | S4: act3d | T4: Companion model catalogue; SectionIV | U4: Primary report proposes a visually and linguistically conditioned manipulation policy or a directly evaluated VLA training/inference method.
A5: R004 | B5: VLA | C5: BitVLA | D5: 2025 | E5: BitVLA: 1-Bit Vision-Language-Action Models for Robotics Manipulation | F5: BitVLA combines low-bit model weights with visual-encoder compression to reduce the memory and inference demands of a VLA policy. It addresses resource-efficient manipulation deployment rather than explicit prediction of action consequences. | G5: https://arxiv.org/abs/2506.07530 | H5: Proposed include | I5: Include | J5: Paper | K5: VLA policy | M5: manipulation | N5: Current manuscript | O5: arXiv:2506.07530 | P5: Prior primary-source check retained | R5: Established companion catalogue primary-source trace; not freshly rechecked this update. | S5: bitvla | T5: Companion model catalogue; SectionIV; Table2/tab:vla-master; tab:vla-master | U5: Primary report proposes a visually and linguistically conditioned manipulation policy or a directly evaluated VLA training/inference method.
A6: R005 | B6: VLA | C6: BridgeVLA | D6: 2025 | E6: BridgeVLA: Input-Output Alignment for Efficient 3D Manipulation Learning | F6: BridgeVLA projects three-dimensional observations into multiple image views and predicts spatial action heatmaps. This design aligns visual inputs with the spatial representation of control outputs. | G6: https://arxiv.org/abs/2506.07961 | H6: Proposed include | I6: Include | J6: Paper | K6: Language-conditioned spatial manipulation policy | M6: manipulation | N6: Current manuscript | O6: arXiv:2506.07961 | P6: Prior primary-source check retained | R6: Established companion catalogue primary-source trace; not freshly rechecked this update. | S6: bridgevla | T6: Companion model catalogue; SectionIV | U6: Primary report proposes a visually and linguistically conditioned manipulation policy or a directly evaluated VLA training/inference method.
A7: R006 | B7: VLA | C7: CEED-VLA | D7: 2025 | E7: CEED-VLA: Consistency Vision-Language-Action Model with Early-Exit Decoding | F7: CEED-VLA uses consistency distillation and early-exit decoding to accelerate action-token generation. It studies efficient execution of VLA policies under constrained inference budgets. | G7: https://arxiv.org/abs/2506.13725 | H7: Proposed include | I7: Include | J7: Paper | K7: VLA training / inference method | L7: Efficiency | M7: manipulation | N7: Current manuscript | O7: arXiv:2506.13725 | P7: Prior primary-source check retained | R7: Established companion catalogue primary-source trace; not freshly rechecked this update. | S7: ceedvla | T7: Companion model catalogue; SectionIV | U7: Primary report proposes a visually and linguistically conditioned manipulation policy or a directly evaluated VLA training/inference method.
A8: R007 | B8: VLA | C8: CogACT | D8: 2024 | E8: CogACT: A Foundational Vision-Language-Action Model for Synergizing Cognition and Action in Robotic Manipulation | F8: CogACT couples a vision-language backbone to a specialized diffusion action transformer. This separation connects semantic interpretation with continuous manipulation commands. | G8: https://arxiv.org/abs/2411.19650 | H8: Proposed include | I8: Include | J8: Paper | K8: VLA policy | M8: manipulation | N8: Current manuscript | O8: arXiv:2411.19650 | P8: Prior primary-source check retained | R8: Established companion catalogue primary-source trace; not freshly rechecked this update. | S8: cogact | T8: Companion model catalogue; SectionIV | U8: Primary report proposes a visually and linguistically conditioned manipulation policy or a directly evaluated VLA training/inference method.
A9: R008 | B9: VLA | C9: ConRFT | D9: 2025 | E9: ConRFT: A Reinforced Fine-Tuning Method for VLA Models via Consistency Policy | F9: ConRFT fine-tunes VLA policies through offline and online reinforcement learning with a consistency-based objective. Human intervention during online learning supports adaptation to physical manipulation tasks. | G9: https://arxiv.org/abs/2502.05450 | H9: Proposed include | I9: Include | J9: Paper | K9: VLA reinforcement-learning / preference method | L9: Post-training | M9: manipulation | N9: Current manuscript | O9: arXiv:2502.05450 | P9: Prior primary-source check retained | R9: Established companion catalogue primary-source trace; not freshly rechecked this update. | S9: conrft | T9: Companion model catalogue; SectionIV | U9: Primary report proposes a visually and linguistically conditioned manipulation policy or a directly evaluated VLA training/inference method.
A10: R009 | B10: VLA | C10: CoT-VLA | D10: 2025 | E10: CoT-VLA: Visual Chain-of-Thought Reasoning for Vision-Language-Action Models | F10: CoT-VLA predicts future images as intermediate visual goals before generating action sequences. This visual chain of thought links prediction to policy execution without itself establishing candidate-action search. | G10: https://arxiv.org/abs/2503.22020 | H10: Proposed include | I10: Include | J10: Paper | K10: Predictive VLA policy | L10: WM / predictive-policy overlap | M10: manipulation | N10: Current manuscript | O10: arXiv:2503.22020 | P10: Prior primary-source check retained | R10: Established companion catalogue primary-source trace; not freshly rechecked this update. | S10: cotvla | T10: Companion model catalogue; SectionIV; Table2/tab:vla-master; tab:vla-master | U10: Primary report proposes a visually and linguistically conditioned manipulation policy or a directly evaluated VLA training/inference method. | V10: One report only; predictive-policy secondary tag does not generate a second WM count.
A11: R010 | B11: VLA | C11: DeeR-VLA | D11: 2024 | E11: DeeR-VLA: Dynamic Inference of Multimodal Large Language Models for Efficient Robot Execution | F11: DeeR-VLA equips a multimodal policy backbone with multiple exits so that inference depth can vary with the current input. It links robot execution efficiency to adaptive computation rather than a fixed processing depth. | G11: https://arxiv.org/abs/2411.02359 | H11: Proposed include | I11: Include | J11: Paper | K11: VLA training / inference method | L11: Efficiency | M11: manipulation | N11: Current manuscript | O11: arXiv:2411.02359 | P11: Prior primary-source check retained | R11: Established companion catalogue primary-source trace; not freshly rechecked this update. | S11: deervla | T11: Companion model catalogue; SectionIV | U11: Primary report proposes a visually and linguistically conditioned manipulation policy or a directly evaluated VLA training/inference method.
A12: R011 | B12: VLA | C12: DexVLA | D12: 2025 | E12: DexVLA: Vision-Language Model with Plug-In Diffusion Expert for General Robot Control | F12: DexVLA connects a vision-language backbone to a pretrained diffusion action expert. Its staged training adapts the action-generation component across tasks and robot embodiments. | G12: https://arxiv.org/abs/2502.05855 | H12: Proposed include | I12: Include | J12: Paper | K12: VLA policy | M12: manipulation | N12: Current manuscript | O12: arXiv:2502.05855 | P12: Prior primary-source check retained | R12: Established companion catalogue primary-source trace; not freshly rechecked this update. | S12: dexvla | T12: Companion model catalogue; SectionIV | U12: Primary report proposes a visually and linguistically conditioned manipulation policy or a directly evaluated VLA training/inference method.
A13: R012 | B13: VLA | C13: DiffusionVLA / DiVLA | D13: 2024 | E13: Diffusion-VLA: Generalizable and Interpretable Robot Foundation Model via Self-Generated Reasoning | F13: Combines autoregressive language reasoning with a diffusion module that generates robot actions. A reasoning-injection module connects generated explanations to control, with evaluation across real-robot sorting, grasping and instruction-following tasks. | G13: https://arxiv.org/abs/2412.03293 | H13: Proposed include | I13: Include | J13: Paper | K13: Reasoning-conditioned diffusion VLA | M13: manipulation | N13: Additional search | O13: arXiv:2412.03293 | P13: Primary source checked this update | Q13: 2026-10-01 | R13: arXiv abstract, title and submission history; first-report year used. | S13: diffusionvla | U13: Fresh primary-source search identifies an additional manipulation VLA report absent from the current bibliography and companion catalogue. | V13: Supplementary targeted search, not an exhaustive systematic search.
A14: R013 | B14: VLA | C14: Discrete Diffusion VLA | D14: 2025 | E14: Discrete Diffusion VLA: Bringing Discrete Diffusion to Action Decoding in Vision-Language-Action Policies | F14: Discrete Diffusion VLA generates discretized action chunks through iterative diffusion-style refinement within a shared transformer. It explores parallel action decoding as an alternative to sequential autoregressive generation. | G14: https://arxiv.org/abs/2508.20072 | H14: Proposed include | I14: Include | J14: Paper | K14: VLA policy | M14: manipulation | N14: Current manuscript | O14: arXiv:2508.20072 | P14: Prior primary-source check retained | R14: Established companion catalogue primary-source trace; not freshly rechecked this update. | S14: ddvla | T14: Companion model catalogue; SectionIV | U14: Primary report proposes a visually and linguistically conditioned manipulation policy or a directly evaluated VLA training/inference method.
A15: R014 | B15: VLA | C15: ECoT | D15: 2024 | E15: Robotic Control via Embodied Chain-of-Thought Reasoning | F15: Embodied Chain-of-Thought trains a VLA to generate intermediate plans and visually grounded reasoning before robot actions. The method studies whether explicit reasoning supervision improves control and instruction execution. | G15: https://arxiv.org/abs/2407.08693 | H15: Proposed include | I15: Include | J15: Paper | K15: VLA policy | M15: manipulation | N15: Current manuscript | O15: arXiv:2407.08693 | P15: Prior primary-source check retained | R15: Established companion catalogue primary-source trace; not freshly rechecked this update. | S15: ecot | T15: Companion model catalogue; SectionIV; Table2/tab:vla-master; tab:vla-master | U15: Primary report proposes a visually and linguistically conditioned manipulation policy or a directly evaluated VLA training/inference method.
A16: R015 | B16: VLA | C16: EdgeVLA / EVLA | D16: 2025 | E16: EdgeVLA: Efficient Vision-Language-Action Models for Edge Deployment | F16: EdgeVLA combines a smaller language backbone with non-autoregressive action prediction. It targets reduced inference and memory costs on resource-constrained robot hardware. | G16: https://arxiv.org/abs/2507.14049 | H16: Proposed include | I16: Include | J16: Paper | K16: VLA policy | M16: manipulation | N16: Current manuscript | O16: arXiv:2507.14049 | P16: Prior primary-source check retained | R16: Established companion catalogue primary-source trace; not freshly rechecked this update. | S16: edgevla | T16: Companion model catalogue; SectionIV | U16: Primary report proposes a visually and linguistically conditioned manipulation policy or a directly evaluated VLA training/inference method.
A17: R016 | B17: VLA | C17: EfficientVLA | D17: 2025 | E17: EfficientVLA: Training-Free Acceleration and Compression for Vision-Language-Action Models | F17: EfficientVLA accelerates existing policies through language-layer pruning, visual-token selection, and reuse of diffusion-head features. Its contribution is a training-free reduction of policy inference cost. | G17: https://arxiv.org/abs/2506.10100 | H17: Proposed include | I17: Include | J17: Paper | K17: VLA training / inference method | L17: Efficiency | M17: manipulation | N17: Current manuscript | O17: arXiv:2506.10100 | P17: Prior primary-source check retained | R17: Established companion catalogue primary-source trace; not freshly rechecked this update. | S17: efficientvla | T17: Companion model catalogue; SectionIV | U17: Primary report proposes a visually and linguistically conditioned manipulation policy or a directly evaluated VLA training/inference method.
A18: R017 | B18: VLA | C18: FAST / π0-FAST | D18: 2025 | E18: FAST: Efficient Action Tokenization for Vision-Language-Action Models | F18: FAST compresses continuous action chunks into frequency-domain tokens for autoregressive prediction. The π0-FAST policy demonstrates how this representation can support action generation for dexterous control. | G18: https://arxiv.org/abs/2501.09747 | H18: Proposed include | I18: Include | J18: Paper | K18: Action tokenization method with VLA policy variant | M18: manipulation | N18: Current manuscript | O18: arXiv:2501.09747 | P18: Prior primary-source check retained | R18: Established companion catalogue primary-source trace; not freshly rechecked this update. | S18: fast | T18: Companion model catalogue; SectionIV; Table2/tab:vla-master; tab:vla-master | U18: Primary report proposes a visually and linguistically conditioned manipulation policy or a directly evaluated VLA training/inference method.
A19: R018 | B19: VLA | C19: FLaRe (RL fine-tuning) | D19: 2024 | E19: FLaRe: Achieving Masterful and Adaptive Robot Policies with Large-Scale Reinforcement Learning Fine-Tuning | F19: FLaRe uses large-scale reinforcement-learning fine-tuning to improve pretrained robot policies. It is distinct from FLARE, the separate method for aligning policy features with future latent representations. | G19: https://arxiv.org/abs/2409.16578 | H19: Proposed include | I19: Include | J19: Paper | K19: VLA reinforcement-learning / preference method | L19: Post-training | M19: general robotics | N19: Current manuscript | O19: arXiv:2409.16578 | P19: Primary source checked this update | Q19: 2026-10-01 | R19: Abstract and experiments: RL fine-tuning of embodied robot policies; mobile manipulation in simulation and on physical robots. | S19: flarerl | T19: Companion model catalogue; SectionIV; Table2/tab:vla-master; tab:vla-master | U19: Primary report proposes a visually and linguistically conditioned manipulation policy or a directly evaluated VLA training/inference method. | V19: Year uses first arXiv report (2024); existing reference uses publication year 2025. Simulated embodied tasks include navigation and manipulation; not exclusively physical robot manipulation. Year differs from the manuscript citation; register uses the documented source year.
A20: R019 | B20: VLA | C20: ForceVLA | D20: 2025 | E20: ForceVLA: Enhancing VLA Models with a Force-Aware MoE for Contact-Rich Manipulation | F20: ForceVLA integrates force-torque feedback with vision-language features through a force-aware mixture-of-experts module. It targets contact-rich manipulation where visual information alone may be insufficient. | G20: https://arxiv.org/abs/2505.22159 | H20: Proposed include | I20: Include | J20: Paper | K20: VLA policy | M20: manipulation | N20: Current manuscript | O20: arXiv:2505.22159 | P20: Prior primary-source check retained | R20: Established companion catalogue primary-source trace; not freshly rechecked this update. | S20: forcevla | T20: Companion model catalogue; Other manuscript section | U20: Primary report proposes a visually and linguistically conditioned manipulation policy or a directly evaluated VLA training/inference method.
A21: R020 | B21: VLA | C21: FP3 (language-conditioned 3D policy) | D21: 2025 | E21: FP3: A 3D Foundation Policy for Robotic Manipulation | F21: FP3 pretrains a diffusion-transformer manipulation policy using point clouds, proprioception, and CLIP-encoded instructions. It adapts this language-conditioned three-dimensional policy to downstream tasks. | G21: https://arxiv.org/abs/2503.08950 | H21: Proposed include | I21: Include | J21: Paper | K21: Language-conditioned spatial manipulation policy | M21: manipulation | N21: Current manuscript | O21: arXiv:2503.08950 | P21: Primary source checked this update | Q21: 2026-10-01 | R21: Figure2 and SectionIII-A: point clouds, CLIP language embeddings and proprioception condition denoised action chunks. | S21: fp3 | T21: Companion model catalogue; SectionIV; Table2/tab:vla-master; tab:vla-master | U21: Primary report proposes a visually and linguistically conditioned manipulation policy or a directly evaluated VLA training/inference method.
A22: R021 | B22: VLA | C22: Gemini Robotics | D22: 2025 | E22: Gemini Robotics: Bringing AI into the Physical World | F22: Gemini Robotics extends a Gemini vision-language model to generate robot actions from observations and instructions. The developer-reported study examines manipulation capabilities and transfer across embodiments. | G22: https://arxiv.org/abs/2503.20020 | H22: Proposed include | I22: Include | J22: Paper | K22: VLA policy | M22: general robotics | N22: Current manuscript | O22: arXiv:2503.20020 | P22: Prior primary-source check retained | R22: Established companion catalogue primary-source trace; not freshly rechecked this update. | S22: geminirobotics | T22: Companion model catalogue; SectionIV; Table2/tab:vla-master; tab:vla-master | U22: Primary report proposes a visually and linguistically conditioned manipulation policy or a directly evaluated VLA training/inference method. | V22: Research paper retained despite vendor-origin evaluation; vendor reporting alone is not a non-paper classification.
A23: R022 | B23: VLA | C23: Gemini Robotics 1.5 | D23: 2025 | E23: Gemini Robotics 1.5: Pushing the Frontier of Generalist Robots with Advanced Embodied Reasoning, Thinking, and Motion Transfer | F23: Gemini Robotics 1.5 integrates embodied reasoning with action generation in a multi-embodiment policy. The developer report also describes transferring motion knowledge across robot configurations. | G23: https://arxiv.org/abs/2510.03342 | H23: Proposed include | I23: Include | J23: Paper | K23: VLA policy | M23: general robotics | N23: Current manuscript | O23: arXiv:2510.03342 | P23: Prior primary-source check retained | R23: Established companion catalogue primary-source trace; not freshly rechecked this update. | S23: gemini15 | T23: Companion model catalogue; SectionIV; Table2/tab:vla-master; tab:vla-master | U23: Primary report proposes a visually and linguistically conditioned manipulation policy or a directly evaluated VLA training/inference method. | V23: Research paper retained despite vendor-origin evaluation; vendor reporting alone is not a non-paper classification.
A24: R023 | B24: VLA | C24: GeoVLA | D24: 2025 | E24: GeoVLA: Empowering 3D Representations in Vision-Language-Action Models | F24: GeoVLA fuses image-language representations with point-cloud geometry in an action expert. This spatial interface supplies three-dimensional context for language-conditioned manipulation. | G24: https://arxiv.org/abs/2508.09071 | H24: Proposed include | I24: Include | J24: Paper | K24: Language-conditioned spatial manipulation policy | M24: manipulation | N24: Current manuscript | O24: arXiv:2508.09071 | P24: Prior primary-source check retained | R24: Established companion catalogue primary-source trace; not freshly rechecked this update. | S24: geovla | T24: Companion model catalogue; SectionIV | U24: Primary report proposes a visually and linguistically conditioned manipulation policy or a directly evaluated VLA training/inference method.
A25: R024 | B25: VLA | C25: GR-2 | D25: 2024 | E25: GR-2: A Generative Video-Language-Action Model with Web-Scale Knowledge for Robot Manipulation | F25: GR-2 combines large-scale video pretraining with joint video and action learning for robotic manipulation. Its predictive-policy formulation connects visual knowledge from web video to robot trajectories. | G25: https://arxiv.org/abs/2410.06158 | H25: Proposed include | I25: Include | J25: Paper | K25: Predictive VLA policy | L25: WM / predictive-policy overlap | M25: manipulation | N25: Current manuscript | O25: arXiv:2410.06158 | P25: Prior primary-source check retained | R25: Established companion catalogue primary-source trace; not freshly rechecked this update. | S25: gr2 | T25: Companion model catalogue; SectionIV; Table2/tab:vla-master; tab:vla-master | U25: Primary report proposes a visually and linguistically conditioned manipulation policy or a directly evaluated VLA training/inference method. | V25: One report only; predictive-policy secondary tag does not generate a second WM count. Research paper retained despite vendor-origin evaluation; vendor reporting alone is not a non-paper classification.
A26: R025 | B26: VLA | C26: GR00T N1 | D26: 2025 | E26: GR00T N1: An Open Foundation Model for Generalist Humanoid Robots | F26: GR00T N1 combines vision-language interpretation with diffusion-based action generation for humanoid robots. Its dual-system design connects slower semantic processing with continuous control. | G26: https://arxiv.org/abs/2503.14734 | H26: Proposed include | I26: Include | J26: Paper | K26: VLA policy | M26: general robotics | N26: Current manuscript | O26: arXiv:2503.14734 | P26: Prior primary-source check retained | R26: Established companion catalogue primary-source trace; not freshly rechecked this update. | S26: groot | T26: Companion model catalogue; SectionIV; Table2/tab:vla-master; tab:vla-master | U26: Primary report proposes a visually and linguistically conditioned manipulation policy or a directly evaluated VLA training/inference method.
A27: R026 | B27: VLA | C27: GRAPE | D27: 2024 | E27: GRAPE: Generalizing Robot Policy via Preference Alignment | F27: GRAPE aligns robot policies using trajectory preferences derived from successful and unsuccessful behavior. Task-specific spatial and temporal constraints guide the preference-based training signal. | G27: https://arxiv.org/abs/2411.19309 | H27: Proposed include | I27: Include | J27: Paper | K27: VLA reinforcement-learning / preference method | L27: Post-training | M27: manipulation | N27: Current manuscript | O27: arXiv:2411.19309 | P27: Primary source checked this update | Q27: 2026-10-01 | R27: Abstract: trajectory preferences and constraints align VLA policies. | S27: grape | T27: Companion model catalogue; SectionIV | U27: Primary report proposes a visually and linguistically conditioned manipulation policy or a directly evaluated VLA training/inference method.
A28: R027 | B28: VLA | C28: GraspVLA | D28: 2025 | E28: GraspVLA: A Grasping Foundation Model Pre-Trained on Billion-Scale Synthetic Action Data | F28: GraspVLA combines autoregressive perception with flow-matching action generation for grasping. Its training integrates synthetic robot data with semantic pretraining to support generalizable grasp behavior. | G28: https://arxiv.org/abs/2505.03233 | H28: Proposed include | I28: Include | J28: Paper | K28: Language-conditioned spatial manipulation policy | M28: manipulation | N28: Current manuscript | O28: arXiv:2505.03233 | P28: Prior primary-source check retained | R28: Established companion catalogue primary-source trace; not freshly rechecked this update. | S28: graspvla | T28: Companion model catalogue; SectionIV; Table2/tab:vla-master; tab:vla-master | U28: Primary report proposes a visually and linguistically conditioned manipulation policy or a directly evaluated VLA training/inference method.
A29: R028 | B29: VLA | C29: Hi Robot | D29: 2025 | E29: Hi Robot: Open-Ended Instruction Following with Hierarchical Vision-Language-Action Models | F29: Hi Robot uses hierarchical vision-language-action policies to interpret complex instructions and user feedback. A lower-level controller executes the manipulation steps selected by the higher-level reasoning component. | G29: https://arxiv.org/abs/2502.19417 | H29: Proposed include | I29: Include | J29: Paper | K29: VLA policy | M29: manipulation | N29: Current manuscript | O29: arXiv:2502.19417 | P29: Prior primary-source check retained | R29: Established companion catalogue primary-source trace; not freshly rechecked this update. | S29: hirobot | T29: Companion model catalogue; SectionIV; Table2/tab:vla-master; tab:vla-master | U29: Primary report proposes a visually and linguistically conditioned manipulation policy or a directly evaluated VLA training/inference method.
A30: R029 | B30: VLA | C30: iRe-VLA | D30: 2025 | E30: Improving Vision-Language-Action Model with Online Reinforcement Learning | F30: iRe-VLA alternates reinforcement-learning improvement with supervised learning. This alternating procedure aims to stabilize interactive adaptation of pretrained VLA policies. | G30: https://arxiv.org/abs/2501.16664 | H30: Proposed include | I30: Include | J30: Paper | K30: VLA reinforcement-learning / preference method | L30: Post-training | M30: manipulation | N30: Current manuscript | O30: arXiv:2501.16664 | P30: Prior primary-source check retained | R30: Established companion catalogue primary-source trace; not freshly rechecked this update. | S30: irevla | T30: Companion model catalogue; SectionIV | U30: Primary report proposes a visually and linguistically conditioned manipulation policy or a directly evaluated VLA training/inference method.
A31: R030 | B31: VLA | C31: LAPA | D31: 2024 | E31: Latent Action Pretraining from Videos | F31: LAPA learns latent action representations from video without ground-truth action labels during pretraining. Robot data subsequently maps the pretrained policy into executable robot actions. | G31: https://arxiv.org/abs/2410.11758 | H31: Proposed include | I31: Include | J31: Paper | K31: VLA policy | M31: manipulation | N31: Current manuscript | O31: arXiv:2410.11758 | P31: Prior primary-source check retained | R31: Established companion catalogue primary-source trace; not freshly rechecked this update. | S31: lapa | T31: Companion model catalogue; SectionIV | U31: Primary report proposes a visually and linguistically conditioned manipulation policy or a directly evaluated VLA training/inference method. | V31: Year uses first arXiv report (2024); existing reference uses publication year 2025. Year differs from the manuscript citation; register uses the documented source year.
A32: R031 | B32: VLA | C32: LingBot-VLA | D32: 2026 | E32: A Pragmatic VLA Foundation Model | F32: Trains a generalist VLA on real-world demonstrations from multiple dual-arm robot configurations. The study evaluates cross-platform manipulation and introduces an efficient training implementation and GM-100 evaluation data. | G32: https://arxiv.org/abs/2601.18692 | H32: Proposed include | I32: Include | J32: Paper | K32: Cross-embodiment VLA foundation policy | L32: Dataset / benchmark contribution | M32: manipulation | N32: Additional search | O32: arXiv:2601.18692 | P32: Primary source checked this update | Q32: 2026-10-01 | R32: arXiv abstract, title and submission history; first-report year used. | S32: lingbotvla | U32: Fresh primary-source search identifies an additional manipulation VLA report absent from the current bibliography and companion catalogue. | V32: Supplementary targeted search, not an exhaustive systematic search. Distinct original LingBot-VLA report; not the already-cited LingBot-VLA 2.0 paper.
A33: R032 | B33: VLA | C33: LingBot-VLA 2.0 | D33: 2026 | E33: From Foundation to Application: Improving VLA Models in Practice | F33: LingBot-VLA 2.0 extends a generalist VLA with whole-body action spaces and training across multiple robot embodiments and human videos. Auxiliary future prediction uses video-representation and depth-estimation supervision to connect action learning with temporal and geometric information. | G33: https://arxiv.org/abs/2607.06403 | H33: Proposed include | I33: Include | J33: Paper | K33: Predictive VLA policy | L33: WM / predictive-policy overlap | M33: general robotics | N33: Current manuscript | O33: arXiv:2607.06403 | P33: Prior primary-source check retained | R33: Established companion catalogue primary-source trace; not freshly rechecked this update. | S33: lingbotvla2 | T33: Companion model catalogue; SectionIV; Table2/tab:vla-master; tab:vla-master | U33: Primary report proposes a visually and linguistically conditioned manipulation policy or a directly evaluated VLA training/inference method. | V33: One report only; predictive-policy secondary tag does not generate a second WM count.
A34: R033 | B34: VLA | C34: LLARVA | D34: 2024 | E34: LLARVA: Vision-Action Instruction Tuning Enhances Robot Learning | F34: LLARVA uses vision-action instruction tuning with intermediate two-dimensional visual traces. These traces help align multimodal representations with the robot behaviors learned during adaptation. | G34: https://arxiv.org/abs/2406.11815 | H34: Proposed include | I34: Include | J34: Paper | K34: VLA policy | M34: manipulation | N34: Current manuscript | O34: arXiv:2406.11815 | P34: Prior primary-source check retained | R34: Established companion catalogue primary-source trace; not freshly rechecked this update. | S34: llarva | T34: Companion model catalogue; SectionIV | U34: Primary report proposes a visually and linguistically conditioned manipulation policy or a directly evaluated VLA training/inference method.
A35: R034 | B35: VLA | C35: LoHoVLA | D35: 2025 | E35: LoHoVLA: A Unified Vision-Language-Action Model for Long-Horizon Embodied Tasks | F35: LoHoVLA jointly generates subtask language and robot-action tokens. Hierarchical feedback connects these outputs during multi-step embodied task execution. | G35: https://arxiv.org/abs/2506.00411 | H35: Proposed include | I35: Include | J35: Paper | K35: VLA policy | M35: manipulation | N35: Current manuscript | O35: arXiv:2506.00411 | P35: Prior primary-source check retained | R35: Established companion catalogue primary-source trace; not freshly rechecked this update. | S35: lohovla | T35: Companion model catalogue; SectionIV; Table2/tab:vla-master; tab:vla-master | U35: Primary report proposes a visually and linguistically conditioned manipulation policy or a directly evaluated VLA training/inference method.
A36: R035 | B36: VLA | C36: Long-VLA | D36: 2025 | E36: Long-VLA: Unleashing Long-Horizon Capability of Vision-Language-Action Models | F36: Long-VLA uses phase-aware masking of sensory inputs to support coordination across successive subtasks. It addresses error accumulation and execution over extended manipulation horizons. | G36: https://arxiv.org/abs/2508.19958 | H36: Proposed include | I36: Include | J36: Paper | K36: VLA policy | M36: manipulation | N36: Current manuscript | O36: arXiv:2508.19958 | P36: Prior primary-source check retained | R36: Established companion catalogue primary-source trace; not freshly rechecked this update. | S36: longvla | T36: Companion model catalogue; SectionIV | U36: Primary report proposes a visually and linguistically conditioned manipulation policy or a directly evaluated VLA training/inference method.
A37: R036 | B37: VLA | C37: MemoryVLA | D37: 2025 | E37: MemoryVLA: Perceptual-Cognitive Memory in Vision-Language-Action Models for Robotic Manipulation | F37: MemoryVLA combines perceptual and semantic memory retrieval with a memory-conditioned diffusion action expert. It supplies temporal context for manipulation decisions that cannot be resolved reliably from the current observation alone. | G37: https://arxiv.org/abs/2508.19236 | H37: Proposed include | I37: Include | J37: Paper | K37: VLA policy | M37: manipulation | N37: Current manuscript | O37: arXiv:2508.19236 | P37: Prior primary-source check retained | R37: Established companion catalogue primary-source trace; not freshly rechecked this update. | S37: memoryvla | T37: Companion model catalogue; Other manuscript section | U37: Primary report proposes a visually and linguistically conditioned manipulation policy or a directly evaluated VLA training/inference method.
A38: R037 | B38: VLA | C38: Octo | D38: 2024 | E38: Octo: An Open-Source Generalist Robot Policy | F38: Octo is an open generalist robot policy with a diffusion action head and language- or image-goal conditioning. Its adaptation interface accommodates new observation inputs and robot action spaces. | G38: https://arxiv.org/abs/2405.12213 | H38: Proposed include | I38: Include | J38: Paper | K38: VLA policy | M38: manipulation | N38: Current manuscript | O38: arXiv:2405.12213 | P38: Prior primary-source check retained | R38: Established companion catalogue primary-source trace; not freshly rechecked this update. | S38: octo | T38: Companion model catalogue; SectionIV; Table2/tab:vla-master; tab:vla-master | U38: Primary report proposes a visually and linguistically conditioned manipulation policy or a directly evaluated VLA training/inference method.
A39: R038 | B39: VLA | C39: OneTwoVLA | D39: 2025 | E39: OneTwoVLA: A Unified Vision-Language-Action Model with Adaptive Reasoning | F39: OneTwoVLA unifies explicit reasoning and robot-action generation within one model. It switches between reasoning and execution as task progress requires. | G39: https://arxiv.org/abs/2505.11917 | H39: Proposed include | I39: Include | J39: Paper | K39: VLA policy | M39: manipulation | N39: Current manuscript | O39: arXiv:2505.11917 | P39: Prior primary-source check retained | R39: Established companion catalogue primary-source trace; not freshly rechecked this update. | S39: onetwovla | T39: Companion model catalogue; SectionIV | U39: Primary report proposes a visually and linguistically conditioned manipulation policy or a directly evaluated VLA training/inference method.
A40: R039 | B40: VLA | C40: OpenVLA | D40: 2024 | E40: OpenVLA: An Open-Source Vision-Language-Action Model | F40: OpenVLA combines pretrained visual-language representations with autoregressive robot-action prediction in an open model. It provides a generalist manipulation policy that can be adapted to new tasks through fine-tuning. | G40: https://arxiv.org/abs/2406.09246 | H40: Proposed include | I40: Include | J40: Paper | K40: VLA policy | M40: manipulation | N40: Current manuscript | O40: arXiv:2406.09246 | P40: Prior primary-source check retained | R40: Established companion catalogue primary-source trace; not freshly rechecked this update. | S40: openvla | T40: Companion model catalogue; SectionIV; Table2/tab:vla-master; tab:vla-master | U40: Primary report proposes a visually and linguistically conditioned manipulation policy or a directly evaluated VLA training/inference method.
A41: R040 | B41: VLA | C41: OpenVLA-OFT | D41: 2025 | E41: Fine-Tuning Vision-Language-Action Models: Optimizing Speed and Success | F41: OpenVLA-OFT studies fine-tuning choices for faster and more successful VLA control. Its recipe uses action chunking and parallel continuous regression instead of sequential action-token decoding. | G41: https://arxiv.org/abs/2502.19645 | H41: Proposed include | I41: Include | J41: Paper | K41: VLA training / inference method | M41: manipulation | N41: Current manuscript | O41: arXiv:2502.19645 | P41: Prior primary-source check retained | R41: Established companion catalogue primary-source trace; not freshly rechecked this update. | S41: openvlaoft | T41: Companion model catalogue; SectionIV; Table2/tab:vla-master; tab:vla-master | U41: Primary report proposes a visually and linguistically conditioned manipulation policy or a directly evaluated VLA training/inference method.
A42: R041 | B42: VLA | C42: PD-VLA | D42: 2025 | E42: Accelerating Vision-Language-Action Model Integrated with Action Chunking via Parallel Decoding | F42: PD-VLA applies parallel fixed-point iterations to decode action chunks from an autoregressive VLA. It targets action-generation latency while retaining the policy formulation of robot control. | G42: https://arxiv.org/abs/2503.02310 | H42: Proposed include | I42: Include | J42: Paper | K42: VLA training / inference method | L42: Efficiency | M42: manipulation | N42: Current manuscript | O42: arXiv:2503.02310 | P42: Prior primary-source check retained | R42: Established companion catalogue primary-source trace; not freshly rechecked this update. | S42: pdvla | T42: Companion model catalogue; SectionIV | U42: Primary report proposes a visually and linguistically conditioned manipulation policy or a directly evaluated VLA training/inference method.
A43: R042 | B43: VLA | C43: PointVLA | D43: 2025 | E43: PointVLA: Injecting the 3D World into Vision-Language-Action Models | F43: PointVLA injects point-cloud information into pretrained VLA action modules through lightweight adaptation. It gives an existing policy access to three-dimensional geometry for manipulation. | G43: https://arxiv.org/abs/2503.07511 | H43: Proposed include | I43: Include | J43: Paper | K43: Language-conditioned spatial manipulation policy | M43: manipulation | N43: Current manuscript | O43: arXiv:2503.07511 | P43: Prior primary-source check retained | R43: Established companion catalogue primary-source trace; not freshly rechecked this update. | S43: pointvla | T43: Companion model catalogue; SectionIV | U43: Primary report proposes a visually and linguistically conditioned manipulation policy or a directly evaluated VLA training/inference method.
A44: R043 | B44: VLA | C44: QueST (language-conditioned skill policy) | D44: 2024 | E44: QueST: Self-Supervised Skill Abstractions for Learning Continuous Control | F44: Learns quantized temporal skill representations from action sequences and predicts skills from visual observations and task descriptions for multitask and few-shot control. It provides a lightweight policy baseline for RIPT-VLA. | G44: https://arxiv.org/abs/2407.15840 | H44: Proposed include | I44: Include | J44: Paper | K44: Language-conditioned skill policy | M44: manipulation | N44: Existing companion catalogue | O44: arXiv:2407.15840 | P44: Primary source checked this update | Q44: 2026-10-01 | R44: Section4 implementation: LIBERO tasks are language-annotated and frozen CLIP encodes task conditioning. | S44: quest | T44: Companion model catalogue | U44: Primary report proposes a visually and linguistically conditioned manipulation policy or a directly evaluated VLA training/inference method. | V44: Named in companion catalogue but not cited in current manuscript; candidate addition, not an existing included study. Named as a RIPT-VLA backbone in Table2 but its own paper is not currently cited. Language-conditioned skill-policy subtype; not a pretrained large-VLM architecture.
A45: R044 | B45: VLA | C45: RationalVLA | D45: 2025 | E45: RationalVLA: A Rational Vision-Language-Action Model with Dual System | F45: RationalVLA couples higher-level instruction reasoning with manipulation control in a dual-system design. It includes assessment and rejection of commands judged infeasible or defective. | G45: https://arxiv.org/abs/2506.10826 | H45: Proposed include | I45: Include | J45: Paper | K45: VLA policy | M45: manipulation | N45: Current manuscript | O45: arXiv:2506.10826 | P45: Prior primary-source check retained | R45: Established companion catalogue primary-source trace; not freshly rechecked this update. | S45: rationalvla | T45: Companion model catalogue; SectionIV | U45: Primary report proposes a visually and linguistically conditioned manipulation policy or a directly evaluated VLA training/inference method.
A46: R045 | B46: VLA | C46: RDT-1B | D46: 2024 | E46: RDT-1B: A Diffusion Foundation Model for Bimanual Manipulation | F46: RDT-1B uses a diffusion transformer to generate bimanual robot actions conditioned on multimodal inputs. A unified action representation supports learning from robots with different configurations. | G46: https://arxiv.org/abs/2410.07864 | H46: Proposed include | I46: Include | J46: Paper | K46: VLA policy | M46: manipulation | N46: Current manuscript | O46: arXiv:2410.07864 | P46: Prior primary-source check retained | R46: Established companion catalogue primary-source trace; not freshly rechecked this update. | S46: rdt1b | T46: Companion model catalogue; SectionIV; Table2/tab:vla-master; tab:vla-master | U46: Primary report proposes a visually and linguistically conditioned manipulation policy or a directly evaluated VLA training/inference method.
A47: R046 | B47: VLA | C47: RIPT-VLA | D47: 2025 | E47: Interactive Post-Training for Vision-Language-Action Models | F47: RIPT-VLA fine-tunes pretrained robot policies through reinforcement learning with sparse task-success rewards. It studies interactive post-training of both lightweight and larger policies under limited supervision. | G47: https://arxiv.org/abs/2505.17016 | H47: Proposed include | I47: Include | J47: Paper | K47: VLA reinforcement-learning / preference method | L47: Post-training | M47: manipulation | N47: Current manuscript | O47: arXiv:2505.17016 | P47: Prior primary-source check retained | R47: Established companion catalogue primary-source trace; not freshly rechecked this update. | S47: riptvla | T47: Companion model catalogue; SectionIV; Table2/tab:vla-master; tab:vla-master | U47: Primary report proposes a visually and linguistically conditioned manipulation policy or a directly evaluated VLA training/inference method.
A48: R047 | B48: VLA | C48: RLDG | D48: 2024 | E48: RLDG: Robotic Generalist Policy Distillation via Reinforcement Learning | F48: RLDG distills trajectories produced by task-specific reinforcement-learning policies into a generalist robot policy. It uses specialist behavior as an additional source of training data for generalist control. | G48: https://arxiv.org/abs/2412.09858 | H48: Proposed include | I48: Include | J48: Paper | K48: VLA reinforcement-learning / preference method | L48: Post-training | M48: manipulation | N48: Current manuscript | O48: arXiv:2412.09858 | P48: Primary source checked this update | Q48: 2026-10-01 | R48: Figure1 and Section3.3: specialist RL-generated trajectories fine-tune OpenVLA and Octo. | S48: rldg | T48: Companion model catalogue; SectionIV | U48: Primary report proposes a visually and linguistically conditioned manipulation policy or a directly evaluated VLA training/inference method.
A49: R048 | B49: VLA | C49: RoboFlamingo | D49: 2023 | E49: Vision-Language Foundation Models as Effective Robot Imitators | F49: RoboFlamingo adapts a pretrained OpenFlamingo vision-language model for robot imitation learning. An action-prediction interface connects multimodal understanding to language-conditioned manipulation. | G49: https://arxiv.org/abs/2311.01378 | H49: Proposed include | I49: Include | J49: Paper | K49: VLA policy | M49: manipulation | N49: Current manuscript | O49: arXiv:2311.01378 | P49: Prior primary-source check retained | R49: Established companion catalogue primary-source trace; not freshly rechecked this update. | S49: roboflamingo | T49: Companion model catalogue; SectionIV | U49: Primary report proposes a visually and linguistically conditioned manipulation policy or a directly evaluated VLA training/inference method. | V49: Year uses first arXiv report (2023); existing reference uses publication year 2024. Year differs from the manuscript citation; register uses the documented source year.
A50: R049 | B50: VLA | C50: RoboMamba | D50: 2024 | E50: RoboMamba: Multimodal State Space Model for Efficient Robot Reasoning and Manipulation | F50: RoboMamba uses a Mamba state-space backbone for multimodal reasoning and robot-action prediction. It explores efficient language-conditioned manipulation through this alternative sequence-model architecture. | G50: https://arxiv.org/abs/2406.04339 | H50: Proposed include | I50: Include | J50: Paper | K50: VLA policy | M50: manipulation | N50: Current manuscript | O50: arXiv:2406.04339 | P50: Prior primary-source check retained | R50: Established companion catalogue primary-source trace; not freshly rechecked this update. | S50: robomamba | T50: Companion model catalogue; SectionIV; Table2/tab:vla-master; tab:vla-master | U50: Primary report proposes a visually and linguistically conditioned manipulation policy or a directly evaluated VLA training/inference method.
A51: R050 | B51: VLA | C51: RoboVLMs | D51: 2024 | E51: What Matters in Building Vision-Language-Action Models for Generalist Robots | F51: Studies how VLM backbones, policy architectures and cross-embodiment data affect manipulation policies. The RoboVLMs framework implements and evaluates these combinations in simulation and on real robots. | G51: https://arxiv.org/abs/2412.14058 | H51: Proposed include | I51: Include | J51: Paper | K51: VLA design study and policy family | M51: manipulation | N51: Additional search | O51: arXiv:2412.14058 | P51: Primary source checked this update | Q51: 2026-10-01 | R51: arXiv abstract, title and submission history; first-report year used. | S51: robovlms | U51: Fresh primary-source search identifies an additional manipulation VLA report absent from the current bibliography and companion catalogue. | V51: Supplementary targeted search, not an exhaustive systematic search.
A52: R051 | B52: VLA | C52: RT-2 | D52: 2023 | E52: RT-2: Vision-Language-Action Models Transfer Web Knowledge to Robotic Control | F52: RT-2 represents robot actions as tokens and co-trains on robotic trajectories and vision-language tasks. It studies how knowledge learned from web data transfers into language-conditioned manipulation. | G52: https://arxiv.org/abs/2307.15818 | H52: Proposed include | I52: Include | J52: Paper | K52: VLA policy | M52: manipulation | N52: Current manuscript | O52: arXiv:2307.15818 | P52: Prior primary-source check retained | R52: Established companion catalogue primary-source trace; not freshly rechecked this update. | S52: rt2 | T52: Companion model catalogue; SectionIV; Table2/tab:vla-master; tab:vla-master | U52: Primary report proposes a visually and linguistically conditioned manipulation policy or a directly evaluated VLA training/inference method.
A53: R052 | B53: VLA | C53: RT-H | D53: 2024 | E53: RT-H: Action Hierarchies Using Language | F53: RT-H inserts a language-based action hierarchy between task instructions and low-level robot commands. Intermediate motion descriptions organize execution and provide a structured interface for control. | G53: https://arxiv.org/abs/2403.01823 | H53: Proposed include | I53: Include | J53: Paper | K53: VLA policy | M53: manipulation | N53: Current manuscript | O53: arXiv:2403.01823 | P53: Prior primary-source check retained | R53: Established companion catalogue primary-source trace; not freshly rechecked this update. | S53: rth | T53: Companion model catalogue; SectionIV | U53: Primary report proposes a visually and linguistically conditioned manipulation policy or a directly evaluated VLA training/inference method.
A54: R053 | B54: VLA | C54: RVT (language-conditioned 3D policy) | D54: 2023 | E54: RVT: Robotic View Transformer for 3D Object Manipulation | F54: RVT combines rendered views of a three-dimensional scene with language-goal embeddings in a transformer. The resulting representation supports spatially grounded manipulation from limited demonstrations. | G54: https://arxiv.org/abs/2306.14896 | H54: Proposed include | I54: Include | J54: Paper | K54: Language-conditioned spatial manipulation policy | M54: manipulation | N54: Current manuscript | O54: arXiv:2306.14896 | P54: Prior primary-source check retained | R54: Established companion catalogue primary-source trace; not freshly rechecked this update. | S54: rvt | T54: Companion model catalogue; SectionIV | U54: Primary report proposes a visually and linguistically conditioned manipulation policy or a directly evaluated VLA training/inference method.
A55: R054 | B55: VLA | C55: RVT-2 | D55: 2024 | E55: RVT-2: Learning Precise Manipulation from Few Demonstrations | F55: RVT-2 improves the architecture and execution of language-conditioned multi-view manipulation policies. It emphasizes precise control and efficient learning from few demonstrations. | G55: https://arxiv.org/abs/2406.08545 | H55: Proposed include | I55: Include | J55: Paper | K55: Language-conditioned spatial manipulation policy | M55: manipulation | N55: Current manuscript | O55: arXiv:2406.08545 | P55: Prior primary-source check retained | R55: Established companion catalogue primary-source trace; not freshly rechecked this update. | S55: rvt2 | T55: Companion model catalogue; SectionIV | U55: Primary report proposes a visually and linguistically conditioned manipulation policy or a directly evaluated VLA training/inference method.
A56: R055 | B56: VLA | C56: SimpleVLA-RL | D56: 2025 | E56: SimpleVLA-RL: Scaling VLA Training via Reinforcement Learning | F56: SimpleVLA-RL adapts VLA policies through online reinforcement learning with stochastic action-token decoding. It evaluates how interaction changes performance under different demonstration budgets. | G56: https://arxiv.org/abs/2509.09674 | H56: Proposed include | I56: Include | J56: Paper | K56: VLA reinforcement-learning / preference method | L56: Post-training | M56: manipulation | N56: Current manuscript | O56: arXiv:2509.09674 | P56: Prior primary-source check retained | R56: Established companion catalogue primary-source trace; not freshly rechecked this update. | S56: simplevlarl | T56: Companion model catalogue; SectionIV; Table2/tab:vla-master; tab:vla-master | U56: Primary report proposes a visually and linguistically conditioned manipulation policy or a directly evaluated VLA training/inference method. | V56: Year uses first arXiv report (2025); existing reference uses publication year 2026. Year differs from the manuscript citation; register uses the documented source year.
A57: R056 | B57: VLA | C57: SmolVLA | D57: 2025 | E57: SmolVLA: A Vision-Language-Action Model for Affordable and Efficient Robotics | F57: SmolVLA uses a compact vision-language backbone and a flow-matching action expert. Its asynchronous inference design supports robot deployment with modest computational resources. | G57: https://arxiv.org/abs/2506.01844 | H57: Proposed include | I57: Include | J57: Paper | K57: VLA policy | M57: manipulation | N57: Current manuscript | O57: arXiv:2506.01844 | P57: Prior primary-source check retained | R57: Established companion catalogue primary-source trace; not freshly rechecked this update. | S57: smolvla | T57: Companion model catalogue; SectionIV; Table2/tab:vla-master; tab:vla-master | U57: Primary report proposes a visually and linguistically conditioned manipulation policy or a directly evaluated VLA training/inference method.
A58: R057 | B58: VLA | C58: SpatialVLA | D58: 2025 | E58: SpatialVLA: Exploring Spatial Representations for Visual-Language-Action Models | F58: SpatialVLA uses geometric visual representations and spatially structured action tokens. These representations connect scene geometry with language-conditioned manipulation commands. | G58: https://arxiv.org/abs/2501.15830 | H58: Proposed include | I58: Include | J58: Paper | K58: Language-conditioned spatial manipulation policy | M58: manipulation | N58: Current manuscript | O58: arXiv:2501.15830 | P58: Prior primary-source check retained | R58: Established companion catalogue primary-source trace; not freshly rechecked this update. | S58: spatialvla | T58: Companion model catalogue; SectionIV; Table2/tab:vla-master; tab:vla-master | U58: Primary report proposes a visually and linguistically conditioned manipulation policy or a directly evaluated VLA training/inference method.
A59: R058 | B59: VLA | C59: Tactile-VLA | D59: 2025 | E59: Tactile-VLA: Unlocking Vision-Language-Action Model's Physical Knowledge for Tactile Generalization | F59: Tactile-VLA combines tactile feedback and multimodal reasoning with a hybrid position-force controller. It connects contact sensing to robot action selection for physical interaction. | G59: https://arxiv.org/abs/2507.09160 | H59: Proposed include | I59: Include | J59: Paper | K59: VLA policy | M59: manipulation | N59: Current manuscript | O59: arXiv:2507.09160 | P59: Prior primary-source check retained | R59: Established companion catalogue primary-source trace; not freshly rechecked this update. | S59: tactilevla | T59: Companion model catalogue; Other manuscript section | U59: Primary report proposes a visually and linguistically conditioned manipulation policy or a directly evaluated VLA training/inference method.
A60: R059 | B60: VLA | C60: TinyVLA | D60: 2024 | E60: TinyVLA: Towards Fast, Data-Efficient Vision-Language-Action Models for Robotic Manipulation | F60: TinyVLA combines a compact multimodal backbone with a diffusion action decoder. It targets manipulation learning with lower computation and fewer demonstrations. | G60: https://arxiv.org/abs/2409.12514 | H60: Proposed include | I60: Include | J60: Paper | K60: VLA policy | M60: manipulation | N60: Current manuscript | O60: arXiv:2409.12514 | P60: Prior primary-source check retained | R60: Established companion catalogue primary-source trace; not freshly rechecked this update. | S60: tinyvla | T60: Companion model catalogue; SectionIV; Table2/tab:vla-master; tab:vla-master | U60: Primary report proposes a visually and linguistically conditioned manipulation policy or a directly evaluated VLA training/inference method. | V60: Year uses first arXiv report (2024); existing reference uses publication year 2025. Year differs from the manuscript citation; register uses the documented source year.
A61: R060 | B61: VLA | C61: UniVLA | D61: 2025 | E61: UniVLA: Learning to Act Anywhere with Task-centric Latent Actions | F61: Learns task-centered latent actions from video using language and visual features to separate task-relevant motion. The learned representations are decoded into actions for different robots and evaluated on manipulation and navigation tasks. | G61: https://arxiv.org/abs/2505.06111 | H61: Proposed include | I61: Include | J61: Paper | K61: Latent-action VLA policy | M61: general robotics | N61: Additional search | O61: arXiv:2505.06111 | P61: Primary source checked this update | Q61: 2026-10-01 | R61: arXiv abstract, title and submission history; first-report year used. | S61: univla | U61: Fresh primary-source search identifies an additional manipulation VLA report absent from the current bibliography and companion catalogue. | V61: Supplementary targeted search, not an exhaustive systematic search.
A62: R061 | B62: VLA | C62: VLA-0 | D62: 2025 | E62: VLA-0: Building State-of-the-Art VLAs with Zero Modification | F62: Represents robot actions directly as text in an existing vision-language model without adding a separate action head or action vocabulary. It tests training and decoding design choices on LIBERO and real-robot manipulation. | G62: https://arxiv.org/abs/2510.13054 | H62: Proposed include | I62: Include | J62: Paper | K62: Action-as-text VLA policy | M62: manipulation | N62: Additional search | O62: arXiv:2510.13054 | P62: Primary source checked this update | Q62: 2026-10-01 | R62: arXiv abstract, title and submission history; first-report year used. | S62: vla0 | U62: Fresh primary-source search identifies an additional manipulation VLA report absent from the current bibliography and companion catalogue. | V62: Supplementary targeted search, not an exhaustive systematic search.
A63: R062 | B63: VLA | C63: VLA-Adapter | D63: 2025 | E63: VLA-Adapter: An Effective Paradigm for Tiny-Scale Vision-Language-Action Model | F63: Uses Bridge Attention to pass selected vision-language features into a lightweight action policy. It studies efficient VLA adaptation without large-scale robot pretraining and evaluates simulation and real-robot manipulation. | G63: https://arxiv.org/abs/2509.09372 | H63: Proposed include | I63: Include | J63: Paper | K63: VLA architecture / adaptation method | M63: manipulation | N63: Additional search | O63: arXiv:2509.09372 | P63: Primary source checked this update | Q63: 2026-10-01 | R63: arXiv abstract, title and submission history; first-report year used. | S63: vlaadapter | U63: Fresh primary-source search identifies an additional manipulation VLA report absent from the current bibliography and companion catalogue. | V63: Supplementary targeted search, not an exhaustive systematic search.
A64: R063 | B64: VLA | C64: VLA-Cache | D64: 2025 | E64: VLA-Cache: Towards Efficient Vision-Language-Action Model via Adaptive Token Caching | F64: VLA-Cache reuses visual tokens that change little between observations while recomputing task-relevant information. This reduces repeated inference work in an existing VLA control pipeline. | G64: https://arxiv.org/abs/2502.02175 | H64: Proposed include | I64: Include | J64: Paper | K64: VLA training / inference method | L64: Efficiency | M64: manipulation | N64: Current manuscript | O64: arXiv:2502.02175 | P64: Prior primary-source check retained | R64: Established companion catalogue primary-source trace; not freshly rechecked this update. | S64: vlacache | T64: Companion model catalogue; SectionIV | U64: Primary report proposes a visually and linguistically conditioned manipulation policy or a directly evaluated VLA training/inference method.
A65: R064 | B65: VLA | C65: VLA-RL | D65: 2025 | E65: VLA-RL: Towards Masterful and General Robotic Manipulation with Scalable Reinforcement Learning | F65: VLA-RL applies online reinforcement learning to autoregressive VLA policies. Its framework combines scalable training infrastructure with a learned progress-reward model. | G65: https://arxiv.org/abs/2505.18719 | H65: Proposed include | I65: Include | J65: Paper | K65: VLA reinforcement-learning / preference method | L65: Post-training | M65: manipulation | N65: Current manuscript | O65: arXiv:2505.18719 | P65: Prior primary-source check retained | R65: Established companion catalogue primary-source trace; not freshly rechecked this update. | S65: vlarl | T65: Companion model catalogue; SectionIV | U65: Primary report proposes a visually and linguistically conditioned manipulation policy or a directly evaluated VLA training/inference method.
A66: R065 | B66: VLA | C66: π0 | D66: 2024 | E66: π0: A Vision-Language-Action Flow Model for General Robot Control | F66: The π0 model couples a pretrained vision-language backbone to a flow-matching action expert. It generates continuous action chunks for manipulation across tasks and robot embodiments. | G66: https://arxiv.org/abs/2410.24164 | H66: Proposed include | I66: Include | J66: Paper | K66: VLA policy | M66: manipulation | N66: Current manuscript | O66: arXiv:2410.24164 | P66: Prior primary-source check retained | R66: Established companion catalogue primary-source trace; not freshly rechecked this update. | S66: pi0 | T66: Companion model catalogue; SectionIV; Table2/tab:vla-master; tab:vla-master | U66: Primary report proposes a visually and linguistically conditioned manipulation policy or a directly evaluated VLA training/inference method. | V66: Year uses first arXiv report (2024); existing reference uses publication year 2025. Year differs from the manuscript citation; register uses the documented source year.
A67: R066 | B67: VLA | C67: π0.5 | D67: 2025 | E67: π0.5: A Vision-Language-Action Model with Open-World Generalization | F67: The π0.5 model extends π0 through heterogeneous co-training and hierarchical task conditioning. It studies language-conditioned manipulation in settings beyond familiar training environments. | G67: https://arxiv.org/abs/2504.16054 | H67: Proposed include | I67: Include | J67: Paper | K67: VLA policy | M67: general robotics | N67: Current manuscript | O67: arXiv:2504.16054 | P67: Prior primary-source check retained | R67: Established companion catalogue primary-source trace; not freshly rechecked this update. | S67: pi05 | T67: Companion model catalogue; SectionIV; Table2/tab:vla-master; tab:vla-master | U67: Primary report proposes a visually and linguistically conditioned manipulation policy or a directly evaluated VLA training/inference method.
A68: R067 | B68: VLA | C68: π0.7 | D68: 2026 | E68: π0.7: A Steerable Generalist Robotic Foundation Model with Emergent Capabilities | F68: π0.7 conditions a generalist robot policy on language and additional context such as subgoal images and task-performance metadata. This conditioning supports steering the execution strategy while training on demonstrations, autonomous experience, and non-robot data. | G68: https://arxiv.org/abs/2604.15483 | H68: Proposed include | I68: Include | J68: Paper | K68: VLA policy | M68: manipulation | N68: Current manuscript | O68: arXiv:2604.15483 | P68: Prior primary-source check retained | R68: Established companion catalogue primary-source trace; not freshly rechecked this update. | S68: pi07 | T68: Companion model catalogue; SectionIV; Table2/tab:vla-master; tab:vla-master | U68: Primary report proposes a visually and linguistically conditioned manipulation policy or a directly evaluated VLA training/inference method.
A69: R068 | B69: VLA | C69: ACT / ALOHA (contextual) | D69: 2023 | E69: Learning Fine-Grained Bimanual Manipulation with Low-Cost Hardware | F69: This paper introduces the ALOHA teleoperation platform and Action Chunking with Transformers for bimanual imitation learning. Predicting sequences of actions provides a control precedent for later chunk-based VLA policies. | G69: https://arxiv.org/abs/2304.13705 | H69: Background | I69: Background | J69: Paper | K69: Context: Imitation-learning baseline / platform | M69: manipulation | N69: Current manuscript | O69: arXiv:2304.13705 | P69: Prior primary-source check retained | R69: Established companion catalogue primary-source trace; not freshly rechecked this update. | S69: act | T69: Companion model catalogue; SectionIV | U69: Non-language-conditioned imitation-learning baseline; retain as context, not a VLA report.
A70: R069 | B70: VLA | C70: Code as Policies (contextual planner) | D70: 2022 | E70: Code as Policies: Language Model Programs for Embodied Control | F70: Code as Policies generates robot-control programs from natural-language instructions. The generated programs connect perception outputs, control APIs, and feedback to executable behaviors. | G70: https://arxiv.org/abs/2209.07753 | H70: Background | I70: Background | J70: Paper | K70: Context: Contextual planner / control system | M70: manipulation | N70: Current manuscript | O70: arXiv:2209.07753 | P70: Prior primary-source check retained | R70: Established companion catalogue primary-source trace; not freshly rechecked this update. | S70: codeaspolicies | T70: Companion model catalogue; SectionIV | U70: Generated policy programs invoke perception/control APIs; separate contextual planning system, first reported before 2023. | V70: Historical precursor retained separately; not counted in the original VLA time window. Year uses first arXiv report (2022); existing reference uses publication year 2023. Year differs from the manuscript citation; register uses the documented source year.
A71: R070 | B71: VLA | C71: Diffusion Policy (contextual) | D71: 2023 | E71: Diffusion Policy: Visuomotor Policy Learning via Action Diffusion | F71: Diffusion Policy models visuomotor action sequences through conditional denoising diffusion. Receding-horizon execution makes it a control foundation for later diffusion-based robot policies. | G71: https://arxiv.org/abs/2303.04137 | H71: Background | I71: Background | J71: Paper | K71: Context: Imitation-learning baseline / platform | M71: manipulation | N71: Current manuscript | O71: arXiv:2303.04137 | P71: Prior primary-source check retained | R71: Established companion catalogue primary-source trace; not freshly rechecked this update. | S71: diffusionpolicy | T71: Companion model catalogue; SectionIV | U71: Original visuomotor diffusion-control method; language-conditioned VLA interface is not established for this report.
A72: R071 | B72: VLA | C72: Gemini Robotics On-Device | D72: 2025 | E72: Gemini Robotics On-Device: Bringing AI to Local Robotic Devices | F72: Gemini Robotics On-Device is a vendor-reported VLA designed to run locally on robot hardware. The release describes adaptation to manipulation tasks through fine-tuning and provides context for on-device deployment. | G72: https://deepmind.google/blog/gemini-robotics-on-device-brings-ai-to-local-robotic-devices/ | H72: Non-paper source | I72: Exclude | J72: Technical release / software | K72: Official technical release / model card | M72: manipulation | N72: Current manuscript | O72: https://deepmind.google/blog/gemini-robotics-on-device-brings-ai-to-local-robotic-devices | P72: Primary source checked this update | Q72: 2026-10-01 | R72: Official technical announcement of locally running VLA; links existing Gemini Robotics technical report, not a separate paper. | S72: geminiondevice | T72: SectionIV | U72: Official vendor source, not a separately identified research paper; excluded from paper counts.
A73: R072 | B73: VLA | C73: GR00T N1.5 | D73: 2025 | E73: GR00T N1.5: An Improved Open Foundation Model for Generalist Humanoid Robots | F73: GR00T N1.5 extends the GR00T humanoid policy family with changes to its architecture and training data. The official release describes future-latent representation alignment as a component of policy learning. | G73: https://research.nvidia.com/labs/gear/gr00t-n1_5/ | H73: Non-paper source | I73: Exclude | J73: Technical release / software | K73: Official technical release / model card | M73: general robotics | N73: Current manuscript | O73: https://research.nvidia.com/labs/gear/gr00t-n1_5 | P73: Primary source checked this update | Q73: 2026-10-01 | R73: Official GR00T N1.5 release page; technical release retained outside distinct-paper total. | S73: grootn15 | T73: SectionIV | U73: Official vendor source, not a separately identified research paper; excluded from paper counts.
A74: R073 | B74: VLA | C74: GR00T N1.7 | D74: 2026 | E74: GR00T-N1.7-3B Model Card | F74: GR00T N1.7 is a cross-embodiment robot policy that conditions action chunks on visual observations, language, and proprioception. Its released model uses a flow-matching action transformer and supports post-training for particular robots and tasks. | G74: https://huggingface.co/nvidia/GR00T-N1.7-3B | H74: Non-paper source | I74: Exclude | J74: Technical release / software | K74: Official technical release / model card | M74: general robotics | N74: Current manuscript | O74: https://huggingface.co/nvidia/gr00t-n1.7-3b | P74: Prior primary-source check retained | R74: Established companion catalogue primary-source trace; not freshly rechecked this update. | S74: grootn17 | T74: Companion model catalogue; SectionIV; Table2/tab:vla-master; tab:vla-master | U74: Official vendor source, not a separately identified research paper; excluded from paper counts.
A75: R074 | B75: VLA | C75: Helix | D75: 2025 | E75: Helix: A Vision-Language-Action Model for Generalist Humanoid Control | F75: Helix combines a slower vision-language component with a faster continuous-action controller for humanoid upper-body manipulation. The cited vendor release describes this dual-system architecture and its demonstrated behaviors. | G75: https://www.figure.ai/news/helix | H75: Non-paper source | I75: Exclude | J75: Technical release / software | K75: Official technical release / model card | M75: general robotics | N75: Current manuscript | O75: https://www.figure.ai/news/helix | P75: Primary source checked this update | Q75: 2026-10-01 | R75: Official Figure AI technical release describing dual-system VLA for humanoid control. | S75: helix | T75: SectionIV; Table2/tab:vla-master; tab:vla-master | U75: Official vendor source, not a separately identified research paper; excluded from paper counts.
A76: R075 | B76: VLA | C76: Helix 02 | D76: 2026 | E76: Introducing Helix 02: Full-Body Autonomy | F76: Helix 02 combines language and scene reasoning, a full-body visuomotor policy, and a learned low-level whole-body controller. The vendor describes coordinated locomotion and manipulation using visual, tactile, and proprioceptive inputs. | G76: https://www.figure.ai/news/helix-02 | H76: Non-paper source | I76: Exclude | J76: Technical release / software | K76: Official technical release / model card | M76: general robotics | N76: Current manuscript | O76: https://www.figure.ai/news/helix-02 | P76: Prior primary-source check retained | R76: Established companion catalogue primary-source trace; not freshly rechecked this update. | S76: helix02 | T76: Companion model catalogue; SectionIV; Table2/tab:vla-master; tab:vla-master | U76: Official vendor source, not a separately identified research paper; excluded from paper counts.
A77: R076 | B77: VLA | C77: HULC (language-conditioned policy) | D77: 2022 | E77: What Matters in Language Conditioned Robotic Imitation Learning | F77: A hierarchical language-conditioned imitation policy using latent plans and aligned visual-language representations for multi-task manipulation. Its role in this register is context for the policy comparison. | G77: https://arxiv.org/abs/2204.06252 | H77: Background | I77: Background | J77: Paper | K77: Context: Language-conditioned comparator; related context | M77: manipulation | N77: Existing companion catalogue | O77: arXiv:2204.06252 | P77: Prior primary-source check retained | R77: Established companion catalogue primary-source trace; not freshly rechecked this update. | S77: hulc | T77: Companion model catalogue | U77: Language-conditioned imitation-policy precursor first reported in 2022, outside January 2023 onward VLA search window. | V77: Historical precursor retained separately; not counted in the original VLA time window. Named in companion catalogue but not cited in current manuscript; candidate addition, not an existing included study.
A78: R077 | B78: VLA | C78: Lift3D Foundation Policy | D78: 2024 | E78: Lift3D Foundation Policy: Lifting 2D Large-Scale Pretrained Models for Robust 3D Robotic Manipulation | F78: Lift3D adapts pretrained two-dimensional visual features into implicit and explicit three-dimensional manipulation representations. Its reported policy uses point clouds and robot state without language conditioning. | G78: https://arxiv.org/abs/2411.18623 | H78: Background | I78: Background | J78: Paper | K78: Context: Visuomotor policy without language conditioning | M78: manipulation | N78: Current manuscript | O78: arXiv:2411.18623 | P78: Primary source checked this update | Q78: 2026-10-01 | R78: Conclusion and AppendixB.1: model cannot comprehend language conditions and uses point clouds and robot states. | S78: lift3d | T78: Companion model catalogue; SectionIV | U78: Visual 3D manipulation policy; language conditioning is not part of its stated input interface.
A79: R078 | B79: VLA | C79: Mobile ALOHA (contextual) | D79: 2024 | E79: Mobile ALOHA: Learning Bimanual Mobile Manipulation with Low-Cost Whole-Body Teleoperation | F79: Mobile ALOHA combines whole-body teleoperation with imitation learning for mobile bimanual manipulation. It extends demonstration-based control to coordinated base and arm motions. | G79: https://arxiv.org/abs/2401.02117 | H79: Background | I79: Background | J79: Paper | K79: Context: Imitation-learning baseline / platform | M79: manipulation | N79: Current manuscript | O79: arXiv:2401.02117 | P79: Prior primary-source check retained | R79: Established companion catalogue primary-source trace; not freshly rechecked this update. | S79: mobilealoha | T79: Companion model catalogue; SectionIV | U79: Teleoperation and imitation-learning platform without a language-conditioned policy contribution.
A80: R079 | B80: VLA | C80: MOKA (VLM control framework) | D80: 2024 | E80: MOKA: Open-World Robotic Manipulation through Mark-Based Visual Prompting | F80: MOKA uses marked images and point-based affordances to interpret manipulation instructions. These geometric interfaces translate vision-language reasoning into executable control commands. | G80: https://arxiv.org/abs/2403.03174 | H80: Background | I80: Background | J80: Paper | K80: Context: Contextual planner / control system | M80: manipulation | N80: Current manuscript | O80: arXiv:2403.03174 | P80: Prior primary-source check retained | R80: Established companion catalogue primary-source trace; not freshly rechecked this update. | S80: moka | T80: Companion model catalogue; SectionIV | U80: Modular VLM affordance prompting and geometric control; separate from learned VLA policy reports.
A81: R080 | B81: VLA | C81: OK-Robot (modular control system) | D81: 2024 | E81: OK-Robot: What Really Matters in Integrating Open-Knowledge Models for Robotics | F81: OK-Robot integrates open perception, navigation, and grasping components for language-directed mobile manipulation. It studies how these components work together in unfamiliar environments. | G81: https://arxiv.org/abs/2401.12202 | H81: Background | I81: Background | J81: Paper | K81: Context: Contextual planner / control system | M81: manipulation | N81: Current manuscript | O81: arXiv:2401.12202 | P81: Prior primary-source check retained | R81: Established companion catalogue primary-source trace; not freshly rechecked this update. | S81: okrobot | T81: Companion model catalogue; SectionIV | U81: Integration of perception, navigation and grasping components; contextual modular system, not a learned VLA policy.
A82: R081 | B82: VLA | C82: Ontology-Driven Prompt Tuning for LLM-Based Task and Motion Planning | D82: 2024 | E82: Ontology-Driven Prompt Tuning for LLM-Based Task and Motion Planning | F82: This framework enriches language-model prompts with ontology-based task knowledge and descriptions of the environment. It uses this knowledge to improve semantic consistency and temporal ordering in task-and-motion plans. | G82: https://arxiv.org/abs/2412.07493v1 | H82: Background | I82: Background | J82: Paper | K82: Context: related manipulation method | M82: manipulation | N82: Current manuscript | O82: arXiv:2412.07493 | P82: Primary source checked this update | Q82: 2026-10-01 | R82: Original preprint title and abstract; ontology-based prompting for task-and-motion planning. | S82: ontollmtamp | T82: SectionIV | U82: Knowledge-guided task-and-motion planning system; neither a learned VLA policy nor a learned world model. | V82: Year uses first arXiv report (2024); existing reference uses publication year 2025. Year differs from the manuscript citation; register uses the documented source year.
A83: R082 | B83: VLA | C83: OWMM-Agent / OWMM-VLM | D83: 2025 | E83: OWMM-Agent: Open World Mobile Manipulation With Multi-modal Agentic Data Synthesis | F83: OWMM-Agent uses multimodal scene and robot-state context to coordinate mobile manipulation through function calls. Its associated instruction tuning supports an agentic integration of perception, navigation, and manipulation components. | G83: https://arxiv.org/abs/2506.04217 | H83: Background | I83: Background | J83: Paper | K83: Context: Contextual planner / control system | M83: manipulation | N83: Current manuscript | O83: arXiv:2506.04217 | P83: Prior primary-source check retained | R83: Established companion catalogue primary-source trace; not freshly rechecked this update. | S83: owmmagent | T83: Companion model catalogue; SectionIV | U83: Agentic VLM/function-call mobile-manipulation framework; retain as modular-system context rather than a learned VLA action-policy report.
A84: R083 | B84: VLA | C84: PaLM-E (contextual embodied VLM) | D84: 2023 | E84: PaLM-E: An Embodied Multimodal Language Model | F84: PaLM-E incorporates visual observations and continuous sensor information into an embodied language model. It supports multimodal reasoning and high-level robot planning. | G84: https://arxiv.org/abs/2303.03378 | H84: Background | I84: Background | J84: Paper | K84: Context: Contextual planner / control system | M84: manipulation | N84: Current manuscript | O84: arXiv:2303.03378 | P84: Prior primary-source check retained | R84: Established companion catalogue primary-source trace; not freshly rechecked this update. | S84: palme | T84: Companion model catalogue; SectionIV | U84: Embodied multimodal language model for reasoning and high-level planning; not an action-policy contribution under the selected boundary.
A85: R084 | B85: VLA | C85: PerAct (language-conditioned 3D policy) | D85: 2022 | E85: Perceiver-Actor: A Multi-Task Transformer for Robotic Manipulation | F85: PerAct encodes language goals and voxelized RGB-D observations with a Perceiver architecture. It learns discretized six-degree-of-freedom manipulation actions through behavior cloning. | G85: https://arxiv.org/abs/2209.05451 | H85: Background | I85: Background | J85: Paper | K85: Context: Language-conditioned policy / precursor | M85: manipulation | N85: Current manuscript | O85: arXiv:2209.05451 | P85: Prior primary-source check retained | R85: Established companion catalogue primary-source trace; not freshly rechecked this update. | S85: peract | T85: Companion model catalogue; SectionIV | U85: Language-conditioned 3D action-policy precursor first reported in 2022, outside January 2023 onward VLA search window. | V85: Historical precursor retained separately; not counted in the original VLA time window.
A86: R085 | B86: VLA | C86: ReKep (constraint-based planner) | D86: 2024 | E86: ReKep: Spatio-Temporal Reasoning of Relational Keypoint Constraints for Robotic Manipulation | F86: ReKep uses visual-language reasoning to formulate relational constraints between task-relevant keypoints. It then optimizes robot motions to satisfy those constraints over time. | G86: https://arxiv.org/abs/2409.01652 | H86: Background | I86: Background | J86: Paper | K86: Context: Contextual planner / control system | M86: manipulation | N86: Current manuscript | O86: arXiv:2409.01652 | P86: Prior primary-source check retained | R86: Established companion catalogue primary-source trace; not freshly rechecked this update. | S86: rekep | T86: Companion model catalogue; SectionIV | U86: Keypoint constraints and trajectory optimization; contextual manipulation planner rather than a VLA action policy.
A87: R086 | B87: VLA | C87: RT-1 (contextual precursor) | D87: 2022 | E87: RT-1: Robotics Transformer for Real-World Control at Scale | F87: RT-1 maps camera observations and language instructions to discretized robot commands using a transformer policy. It is an early language-conditioned control precursor to later VLA foundation models. | G87: https://arxiv.org/abs/2212.06817 | H87: Background | I87: Background | J87: Paper | K87: Context: Language-conditioned policy / precursor | M87: manipulation | N87: Current manuscript | O87: arXiv:2212.06817 | P87: Prior primary-source check retained | R87: Established companion catalogue primary-source trace; not freshly rechecked this update. | S87: rt1 | T87: Companion model catalogue; SectionIV; Table2/tab:vla-master; tab:vla-master | U87: Language-conditioned action-policy precursor first reported in 2022, outside January 2023 onward VLA search window. | V87: Historical precursor retained separately; not counted in the original VLA time window.
A88: R087 | B88: VLA | C88: SayCan (contextual planner) | D88: 2022 | E88: Do As I Can, Not As I Say: Grounding Language in Robotic Affordances | F88: SayCan combines language-model task suggestions with learned skill-value estimates. It uses these estimates to select behaviors that are both instruction-relevant and physically feasible. | G88: https://arxiv.org/abs/2204.01691 | H88: Background | I88: Background | J88: Paper | K88: Context: Contextual planner / control system | M88: manipulation | N88: Current manuscript | O88: arXiv:2204.01691 | P88: Prior primary-source check retained | R88: Established companion catalogue primary-source trace; not freshly rechecked this update. | S88: saycan | T88: Companion model catalogue; SectionIV | U88: Language planner selects existing skills; not a unified learned visual-language action policy, and first report predates 2023. | V88: Historical precursor retained separately; not counted in the original VLA time window.
A89: R088 | B89: VLA | C89: VIMA (contextual multimodal policy) | D89: 2022 | E89: VIMA: General Robot Manipulation with Multimodal Prompts | F89: VIMA specifies manipulation tasks using prompts that interleave text and images. A transformer policy converts these multimodal task descriptions and observations into robot actions. | G89: https://arxiv.org/abs/2210.03094 | H89: Background | I89: Background | J89: Paper | K89: Context: Language-conditioned policy / precursor | M89: manipulation | N89: Current manuscript | O89: arXiv:2210.03094 | P89: Prior primary-source check retained | R89: Established companion catalogue primary-source trace; not freshly rechecked this update. | S89: vima | T89: Companion model catalogue; SectionIV | U89: Multimodal-prompt manipulation policy first reported in 2022, outside January 2023 onward VLA search window. | V89: Historical precursor retained separately; not counted in the original VLA time window. Year uses first arXiv report (2022); existing reference uses publication year 2023. Year differs from the manuscript citation; register uses the documented source year.
A90: R089 | B90: VLA | C90: VoxPoser (contextual planner) | D90: 2023 | E90: VoxPoser: Composable 3D Value Maps for Robotic Manipulation with Language Models | F90: VoxPoser converts language and visual information into composable three-dimensional value maps. These maps guide motion planning for manipulation instead of directly predicting motor commands from a single policy head. | G90: https://arxiv.org/abs/2307.05973 | H90: Background | I90: Background | J90: Paper | K90: Context: Contextual planner / control system | M90: manipulation | N90: Current manuscript | O90: arXiv:2307.05973 | P90: Prior primary-source check retained | R90: Established companion catalogue primary-source trace; not freshly rechecked this update. | S90: voxposer | T90: Companion model catalogue; SectionIV | U90: VLM-generated value maps and motion planning are a modular control interface rather than the reviewed learned VLA policy class.
A91: R090 | B91: World model | C91: AR-WAM | D91: 2026 | E91: AR-WAM: A Visual-Conditioned Agent-Ready World Action Model for Robotic Manipulation | F91: AR-WAM conditions a predictive robot policy on a visual target and an operation token rather than a language encoder. It jointly predicts latent scene evolution and actions, with a separate agent interface handling longer task coordination. | G91: https://arxiv.org/abs/2609.23578 | H91: Proposed include | I91: Include | J91: Paper | K91: Visual-conditioned latent world-action model | L91: WAM; agent interface; expanded search window; no language encoder | M91: manipulation | N91: Additional search | O91: arXiv:2609.23578 | P91: Primary source checked this update | Q91: 2026-10-01 | R91: arXiv:2609.23578v1, abstract and submission history | S91: arwam | U91: Adds a manipulation WAM with simulation and physical robot evaluations; it is not a VLA under a language-conditioned policy-interface criterion. | V91: Supplemental primary-source search on 2026-10-01; not cited in the present manuscript. Identity and eligibility assessed from primary abstract/metadata, not an exhaustive numerical replication. First public report 2026-09-20 is after the manuscript's August 2026 search cutoff; include only in the expanded search window through 2026-10-01.
A92: R091 | B92: World model | C92: AVDC | D92: 2023 | E92: Learning to act from actionless videos through dense correspondences | F92: AVDC generates task-directed videos and uses dense correspondences between frames to infer control actions. This connects action-free video demonstrations to robot execution. | G92: https://arxiv.org/abs/2310.08576 | H92: Proposed include | I92: Include | J92: Paper | K92: Video generation with action recovery | L92: action-free demonstrations; video planning | M92: manipulation | N92: Current manuscript | O92: arXiv:2310.08576 | P92: Prior primary-source check retained | R92: Prior companion model catalogue and Current References primary-source link; not reopened this update | S92: avdc | T92: manuscript.tex:578 | U92: Task-conditioned visual prediction is converted to robot control and evaluated on manipulation. | V92: Existing primary-source identity and summary retained from the previously checked companion catalogue; this update does not claim a fresh full-text audit. Individual prior-check date was not recorded. Year column uses first arXiv submission (2023); supplied publication/reference year was 2024. Year differs from the manuscript citation; register uses the documented source year.
A93: R092 | B93: World model | C93: Cosmos | D93: 2025 | E93: Cosmos World Foundation Model Platform for Physical AI | F93: Cosmos provides video tokenizers, a curation pipeline and generative world foundation models. Its robotic post-training examples include instruction-conditioned video prediction and action-vector-conditioned next-frame prediction, distinct from an unadapted backbone. | G93: https://arxiv.org/abs/2501.03575 | H93: Proposed include | I93: Include | J93: Paper | K93: Video foundation model with robotic adaptation | L93: action-conditioned adaptation; data curation; video generation | M93: manipulation | N93: Current manuscript | O93: arXiv:2501.03575 | P93: Primary source checked this update | Q93: 2026-10-01 | R93: arXiv:2501.03575v3, Sec. 6.2 (robotic manipulation post-training); abstract and submission history | S93: cosmos | T93: Table tab:wm-master; manuscript.tex:1053; manuscript.tex:1124; manuscript.tex:487; manuscript.tex:580; manuscript.tex:769; tab:wm-master | U93: Section 6.2 evaluates robot video prediction, including post-training for action-vector-conditioned next-frame generation.
A94: R093 | B94: World model | C94: Cosmos Policy | D94: 2026 | E94: Cosmos Policy: Fine-tuning video models for visuomotor control and planning | F94: Cosmos Policy adapts a video model to jointly generate actions, future states, and values. It evaluates direct visuomotor execution alongside rollout refinement and candidate selection for planning. | G94: https://arxiv.org/abs/2601.16163 | H94: Proposed include | I94: Include | J94: Paper | K94: World-action model with policy and planning modes | L94: VLA overlap; WAM; planning | M94: manipulation | N94: Current manuscript | O94: arXiv:2601.16163 | P94: Prior primary-source check retained | R94: Prior companion model catalogue and Current References primary-source link; not reopened this update | S94: cosmospolicy | T94: Table tab:wm-master; manuscript.tex:1073; manuscript.tex:1122; manuscript.tex:468; manuscript.tex:501; manuscript.tex:643; manuscript.tex:722; manuscript.tex:732; manuscript.tex:787; manuscript.tex:844; manuscript.tex:950; manuscript.tex:97; manuscript.tex:986; tab:wm-master | U94: Manipulation policy jointly predicts actions, future state and value; direct control and rollout-based planning are separately evaluated. | V94: Existing primary-source identity and summary retained from the previously checked companion catalogue; this update does not claim a fresh full-text audit. Individual prior-check date was not recorded.
A95: R094 | B95: World model | C95: Ctrl-World | D95: 2025 | E95: Ctrl-World: A Controllable Generative World Model for Robot Manipulation | F95: Ctrl-World predicts multi-view video under robot actions and retrieves pose-conditioned memory to extend rollout consistency. It uses generated trajectories for policy evaluation and corrective training, with evidence limited to the reported protocols. | G95: https://arxiv.org/abs/2510.10125 | H95: Proposed include | I95: Include | J95: Paper | K95: Action-conditioned learned simulator | L95: multi-view; policy evaluation; synthetic data | M95: manipulation | N95: Existing companion catalogue | O95: arXiv:2510.10125 | P95: Primary source checked this update | Q95: 2026-10-01 | R95: arXiv:2510.10125v3, abstract and submission history | S95: ctrlworld | U95: Provides controllable multi-view robot rollouts for policy evaluation and policy-improvement data. | V95: Already present in the companion model catalogue but not cited in the current manuscript; retained here as a separately traceable source.
A96: R095 | B96: World model | C96: DINO-WM | D96: 2024 | E96: DINO-WM: World models on pre-trained visual features enable zero-shot planning | F96: DINO-WM learns action-conditioned transitions over pretrained DINO image features. It plans toward visual goals in feature space without reconstructing future images. | G96: https://arxiv.org/abs/2411.04983 | H96: Proposed include | I96: Include | J96: Paper | K96: Action-conditioned latent dynamics and planning | L96: goal-conditioned control; latent planning | M96: manipulation | N96: Current manuscript | O96: arXiv:2411.04983 | P96: Prior primary-source check retained | R96: Prior companion model catalogue and Current References primary-source link; not reopened this update | S96: dinowm | T96: manuscript.tex:603 | U96: Learns transitions over pretrained visual features and evaluates visual goal-directed control, including manipulation. | V96: Existing primary-source identity and summary retained from the previously checked companion catalogue; this update does not claim a fresh full-text audit. Individual prior-check date was not recorded.
A97: R096 | B97: World model | C97: DreamDojo | D97: 2026 | E97: DreamDojo: A generalist robot world model from large-scale human videos | F97: DreamDojo learns an action-conditioned video world model from human videos using continuous latent actions as proxy controls, then adapts it with robot data. Its generated rollouts support applications including policy evaluation and model-based planning. | G97: https://arxiv.org/abs/2602.06949 | H97: Proposed include | I97: Include | J97: Paper | K97: Action-conditioned video world model | L97: human video; learned simulation; planning | M97: manipulation | N97: Current manuscript | O97: arXiv:2602.06949 | P97: Prior primary-source check retained | R97: Prior companion model catalogue and Current References primary-source link; not reopened this update | S97: dreamdojo | T97: Table tab:wm-master; manuscript.tex:783; tab:wm-master | U97: Adapts human-video pretraining to robot-action simulation and evaluates downstream robot uses. | V97: Prior check verified the arXiv paper. Manuscript PMLR proceedings URL was inaccessible during that check; exact proceedings metadata remains unconfirmed. Existing primary-source identity and summary retained from the previously checked companion catalogue; this update does not claim a fresh full-text audit. Individual prior-check date was not recorded.
A98: R097 | B98: World model | C98: DreamerV3 | D98: 2023 | E98: Mastering diverse control tasks through world models | F98: DreamerV3 learns policies through trajectories imagined in a latent dynamics model with training procedures shared across domains. The published evaluation spans robot manipulation and locomotion as well as games, so manipulation relevance should not be inferred solely from its Minecraft demonstration. | G98: https://arxiv.org/abs/2301.04104 | H98: Proposed include | I98: Include | J98: Paper | K98: General latent imagination learning | L98: general-control foundation; model-based RL; simulated manipulation | M98: general robotics | N98: Current manuscript | O98: arXiv:2301.04104 | P98: Primary source checked this update | Q98: 2026-10-01 | R98: arXiv:2301.04104v2, abstract; Nature doi:10.1038/s41586-025-08744-2 search-indexed primary text, Fig. 2 discussion (robot manipulation domains) | S98: dreamerv3 | T98: Table tab:wm-master; manuscript.tex:569; manuscript.tex:763; tab:wm-master | U98: Primary published report explicitly includes robot manipulation domains alongside locomotion and games. | V98: Nature version and arXiv predecessor are one report identity for counting; published title differs from the early arXiv title. Year column uses first arXiv submission (2023); supplied publication/reference year was 2025. Year differs from the manuscript citation; register uses the documented source year.
A99: R098 | B99: World model | C99: DreamGen | D99: 2025 | E99: DreamGen: Unlocking generalization in robot learning through video world models | F99: DreamGen generates task-conditioned robot videos and obtains pseudo-action labels through inverse dynamics. The resulting synthetic trajectories augment policy training as an offline data-generation pipeline. | G99: https://arxiv.org/abs/2505.12705 | H99: Proposed include | I99: Include | J99: Paper | K99: Synthetic robot trajectory generation | L99: inverse dynamics; synthetic data | M99: manipulation | N99: Current manuscript | O99: arXiv:2505.12705 | P99: Prior primary-source check retained | R99: Prior companion model catalogue and Current References primary-source link; not reopened this update | S99: dreamgen | T99: Table tab:wm-master; manuscript.tex:1068; manuscript.tex:1271; manuscript.tex:619; manuscript.tex:726; manuscript.tex:778; manuscript.tex:97; tab:wm-master; tab:datasets | U99: Generates robot video and inferred action labels and evaluates downstream manipulation-policy training. | V99: Existing primary-source identity and summary retained from the previously checked companion catalogue; this update does not claim a fresh full-text audit. Individual prior-check date was not recorded.
A100: R099 | B100: World model | C100: DreamVLA | D100: 2025 | E100: DreamVLA: A vision-language-action model dreamed with comprehensive world knowledge | F100: DreamVLA forecasts compact dynamic, spatial, and semantic representations. A diffusion-based action generator conditions its manipulation commands on this predicted world information. | G100: https://arxiv.org/abs/2507.04447 | H100: Proposed include | I100: Include | J100: Paper | K100: Predictive VLA with future representations | L100: VLA overlap; WAM; auxiliary prediction | M100: manipulation | N100: Current manuscript | O100: arXiv:2507.04447 | P100: Prior primary-source check retained | R100: Prior companion model catalogue and Current References primary-source link; not reopened this update | S100: dreamvla | T100: Table tab:wm-master; manuscript.tex:641; manuscript.tex:786; tab:wm-master | U100: Uses predicted dynamic, spatial and semantic information for manipulation action generation. | V100: Predictive training or joint generation does not by itself establish a forward model for supplied candidate actions or online candidate search. Existing primary-source identity and summary retained from the previously checked companion catalogue; this update does not claim a fresh full-text audit. Individual prior-check date was not recorded.
...

Sheet Table Coverage
A1: Manuscript table | B1: Printed entry | C1: Cited key | D1: Matched record | E1: Primary category | F1: Proposed decision | G1: Matched source title | H1: Source link | I1: Correction / note
A2: VLA models | B2: RT-1 (precursor) | C2: rt1 | D2: R086 | E2: VLA | F2: Background | G2: RT-1: Robotics Transformer for Real-World Control at Scale | H2: https://arxiv.org/abs/2212.06817
A3: VLA models | B3: RT-2 | C3: rt2 | D3: R051 | E3: VLA | F3: Proposed include | G3: RT-2: Vision-Language-Action Models Transfer Web Knowledge to Robotic Control | H3: https://arxiv.org/abs/2307.15818
A4: VLA models | B4: RT-X | C4: oxe | D4: R161 | E4: Dataset / benchmark | F4: Proposed include | G4: Open X-Embodiment: Robotic learning datasets and RT-X models | H4: https://arxiv.org/abs/2310.08864
A5: VLA models | B5: OpenVLA | C5: openvla | D5: R039 | E5: VLA | F5: Proposed include | G5: OpenVLA: An Open-Source Vision-Language-Action Model | H5: https://arxiv.org/abs/2406.09246
A6: VLA models | B6: FAST / π_0-FAST | C6: fast | D6: R017 | E6: VLA | F6: Proposed include | G6: FAST: Efficient Action Tokenization for Vision-Language-Action Models | H6: https://arxiv.org/abs/2501.09747
A7: VLA models | B7: OpenVLA-OFT | C7: openvlaoft | D7: R040 | E7: VLA | F7: Proposed include | G7: Fine-Tuning Vision-Language-Action Models: Optimizing Speed and Success | H7: https://arxiv.org/abs/2502.19645
A8: VLA models | B8: Octo | C8: octo | D8: R037 | E8: VLA | F8: Proposed include | G8: Octo: An Open-Source Generalist Robot Policy | H8: https://arxiv.org/abs/2405.12213
A9: VLA models | B9: π_0 | C9: pi0 | D9: R065 | E9: VLA | F9: Proposed include | G9: π0: A Vision-Language-Action Flow Model for General Robot Control | H9: https://arxiv.org/abs/2410.24164
A10: VLA models | B10: RDT-1B | C10: rdt1b | D10: R045 | E10: VLA | F10: Proposed include | G10: RDT-1B: A Diffusion Foundation Model for Bimanual Manipulation | H10: https://arxiv.org/abs/2410.07864
A11: VLA models | B11: GR00T N1 | C11: groot | D11: R025 | E11: VLA | F11: Proposed include | G11: GR00T N1: An Open Foundation Model for Generalist Humanoid Robots | H11: https://arxiv.org/abs/2503.14734
A12: VLA models | B12: GR00T N1.7 | C12: grootn17 | D12: R073 | E12: VLA | F12: Non-paper source | G12: GR00T-N1.7-3B Model Card | H12: https://huggingface.co/nvidia/GR00T-N1.7-3B
A13: VLA models | B13: π_0.5 | C13: pi05 | D13: R066 | E13: VLA | F13: Proposed include | G13: π0.5: A Vision-Language-Action Model with Open-World Generalization | H13: https://arxiv.org/abs/2504.16054
... A82: Benchmarks | B82: VBench-2.0 | C82: vbench2 | D82: R180 | E82: Dataset / benchmark | F82: Background | G82: VBench-2.0: Advancing video generation benchmark suite for intrinsic faithfulness | H82: https://arxiv.org/abs/2503.21755
A83: Benchmarks | B83: EWMBench | C83: genieenvisioner | D83: R104 | E83: World model | F83: Proposed include | G83: Genie envisioner: A unified world foundation platform for robotic manipulation | H83: https://arxiv.org/abs/2508.05635 | I83: Citation mismatch: table cites Genie Envisioner. Standalone EWMBench paper: R151; https://arxiv.org/abs/2505.09694
A84: Benchmarks | B84: WorldArena | C84: worldarena | D84: R175 | E84: Dataset / benchmark | F84: Proposed include | G84: WorldArena: A unified benchmark for evaluating perception and functional utility of embodied world models | H84: https://arxiv.org/abs/2602.08971
A85: Benchmarks | B85: WorldArena 2.0 | C85: shang2026worldarena2 | D85: R176 | E85: Dataset / benchmark | F85: Proposed include | G85: WorldArena 2.0: Extending embodied world model benchmarking on modality, functionality and platform | H85: https://arxiv.org/abs/2605.17912
A86: Benchmarks | B86: ManipArena | C86: maniparena | D86: R157 | E86: Dataset / benchmark | F86: Proposed include | G86: ManipArena: Comprehensive real-world evaluation of reasoning-oriented generalist robot manipulation | H86: https://arxiv.org/abs/2603.28545
A87: Training datasets | B87: Open X-Embodiment | C87: oxe | D87: R161 | E87: Dataset / benchmark | F87: Proposed include | G87: Open X-Embodiment: Robotic learning datasets and RT-X models | H87: https://arxiv.org/abs/2310.08864
A88: Training datasets | B88: DROID | C88: droid | D88: R150 | E88: Dataset / benchmark | F88: Proposed include | G88: DROID: A large-scale in-the-wild robot manipulation dataset | H88: https://arxiv.org/abs/2403.12945
A89: Training datasets | B89: BridgeData V2 | C89: bridgedata | D89: R146 | E89: Dataset / benchmark | F89: Proposed include | G89: BridgeData V2: A dataset for robot learning at scale | H89: https://arxiv.org/abs/2308.12952
A90: Training datasets | B90: AgiBot World | C90: agibotworld | D90: R144 | E90: Dataset / benchmark | F90: Proposed include | G90: AgiBot World Colosseo: A large-scale manipulation platform for scalable and intelligent embodied systems | H90: https://arxiv.org/abs/2503.06669
A91: Training datasets | B91: LeRobot | C91: cadene2026lerobot | D91: R178 | E91: Dataset / benchmark | F91: Background | G91: LeRobot: An open-source library for end-to-end robot learning | H91: https://arxiv.org/abs/2602.22818
A92: Training datasets | B92: Ego4D | C92: ego4d | D92: R177 | E92: Dataset / benchmark | F92: Background | G92: Ego4D: Around the world in 3,000 hours of egocentric video | H92: https://arxiv.org/abs/2110.07058
A93: Training datasets | B93: VideoMix22M | C93: vjepa2 | D93: R124 | E93: World model | F93: Proposed include | G93: V-JEPA 2: Self-supervised video models enable understanding, prediction and planning | H93: https://arxiv.org/abs/2506.09985
A94: Training datasets | B94: DreamGen traj. | C94: dreamgen | D94: R098 | E94: World model | F94: Proposed include | G94: DreamGen: Unlocking generalization in robot learning through video world models | H94: https://arxiv.org/abs/2505.12705
A95: VLA master | B95: Seer | C95: seer | D95: R208 | E95: VLA | F95: Proposed include | G95: Predictive Inverse Dynamics Models are Scalable Learners for Robotic Manipulation | H95: https://arxiv.org/abs/2412.15109 | I95: Added to manuscript master table on 2 October 2026 after author approval.
A96: VLA master | B96: VPP | C96: vpp | D96: R209 | E96: VLA | F96: Proposed include | G96: Video Prediction Policy: A Generalist Robot Policy with Predictive Visual Representations | H96: https://arxiv.org/abs/2412.14803 | I96: Added to manuscript master table on 2 October 2026 after author approval.
A97: World model master | B97: Unified World Models | C97: uwm | D97: R210 | E97: World model | F97: Proposed include | G97: Unified World Models: Coupling Video and Action Diffusion for Pretraining on Large Robotic Datasets | H97: https://arxiv.org/abs/2504.02792 | I97: Added to manuscript master table on 2 October 2026 after author approval.

Sheet Search Notes
A1: Search date | B1: Research category | C1: Search query / source check | D1: Primary source links | E1: Scope / outcome
A2: 2026-10-01 | B2: VLA | C2: site.arxiv.org RoboVLMs generalist robot policies vision language action | D2: https://arxiv.org/abs/2412.14058; https://robovlms.github.io/ | E2: Targeted search for a missing generalist VLA design study; primary arXiv record opened and checked.
A3: 2026-10-01 | B3: VLA | C3: site.arxiv.org VLA adapter effective vision language action 2025 | D3: https://arxiv.org/abs/2509.09372; https://github.com/OpenHelix-Team/VLA-Adapter | E3: Identified official repository and verified the linked paper; combined with the subsequent exact-name search.
A4: 2026-10-01 | B4: VLA | C4: site.arxiv.org UniVLA learning to act anywhere task centric latent actions | D4: https://arxiv.org/abs/2505.06111; https://www.roboticsproceedings.org/rss21/p014.pdf | E4: Identified RSS report and checked arXiv identity, abstract and first-submission date.
A5: 2026-10-01 | B5: VLA | C5: site.arxiv.org "TinyVLA" "RoboVLMs" "STAR" vision language action | E5: Exploratory query; no new inclusion attributed solely to this query.
A6: 2026-10-01 | B6: VLA | C6: site.arxiv.org "VLA-Adapter" | D6: https://arxiv.org/abs/2509.09372; https://vla-adapter.github.io/ | E6: Exact-name supplementary lookup and primary-paper verification; secondary search hits were not treated as authoritative evidence.
A7: 2026-10-01 | B7: VLA | C7: site.arxiv.org "VLA-0" "Vision-Language" models | D7: https://arxiv.org/abs/2510.13054; https://vla0.github.io/ | E7: Identified VLA-0 and checked primary arXiv record; no performance ranking copied into the register.
A8: 2026-10-01 | B8: VLA | C8: site.arxiv.org "HeteroVLA" | E8: Exploratory query; no HeteroVLA record included because this search did not establish a primary source.
A9: 2026-10-01 | B9: VLA | C9: Direct primary-source lookup: DiffusionVLA | D9: https://arxiv.org/abs/2412.03293 | E9: Known candidate identity opened directly and verified against title, abstract and submission history; no invented web query.
A10: 2026-10-01 | B10: VLA | C10: Direct primary-source follow-up: original LingBot-VLA | D10: https://arxiv.org/abs/2601.18692 | E10: Candidate surfaced in the combined exploratory search output; primary record opened directly. Distinct from LingBot-VLA 2.0.
A11: 2026-10-01 | B11: VLA | C11: Direct source checks for ambiguous policy interfaces and source types | D11: https://arxiv.org/html/2503.08950v1; https://arxiv.org/html/2407.15840v3; https://arxiv.org/html/2411.18623v2; https://arxiv.org/html/2412.09858v1; https://arxiv.org/html/2409.16578v2; https://arxiv.org/abs/2411.19309; https://deepmind.google/blog/gemini-robotics-on-device-brings-ai-to-local-robotic-devices/; https://research.nvidia.com/labs/gear/gr00t-n1_5/; https://www.figure.ai/news/helix; https://arxiv.org/abs/2412.07493v1 | E11: Direct opens and in-document finds; not a database query. Resolved language-conditioning, manipulation scope, method subtype and non-paper technical-source classifications.
A12: 2026-10-01 | B12: World model | C12: site.arxiv.org robot manipulation world model action conditioned RoboDreamer WoVoGen RoboDream 2024 2025 | D12: https://arxiv.org/abs/2404.12377; https://arxiv.org/abs/2504.16464; https://arxiv.org/abs/2606.02577; https://arxiv.org/abs/2609.23578 | E12: Targeted supplementary discovery, not exhaustive database retrieval. Followed primary arXiv records for identity, date and abstract-level eligibility. AR-WAM is an expanded-window September 2026 addition.
A13: 2026-10-01 | B13: World model | C13: site.arxiv.org world model manipulation AVID RoboDreamer GRWM 2025 | D13: https://arxiv.org/abs/2505.10075; https://arxiv.org/abs/2505.11528; https://arxiv.org/abs/2509.22642; https://arxiv.org/abs/2406.14540 | E13: Discovered FlowDreamer, LaDi-WM, WoW and IRASim; primary records subsequently opened. Non-primary aggregator results were not used as final evidence. Other search hits were discovery leads only, not reviewed as an exhaustive candidate pool.
A14: 2026-10-01 | B14: World model | C14: site.arxiv.org/abs "HarmoWAM" | D14: https://arxiv.org/abs/2605.10942 | E14: Verified current manuscript system identity, adaptive predictive/reactive mechanism and real-robot manipulation relevance from primary abstract.
A15: 2026-10-01 | B15: World model | C15: site.arxiv.org/abs "LaWAM" | D15: https://arxiv.org/abs/2606.15768 | E15: Search followed by direct primary arXiv open; checked title, latent-subgoal mechanism and manipulation relevance.
A16: 2026-10-01 | B16: World model | C16: site.arxiv.org/abs "VLA-JEPA" | D16: https://arxiv.org/abs/2602.10098; https://ginwind.github.io/VLA-JEPA/ | E16: Checked primary abstract and official Method Overview; distinguished future supervision from future-frame inputs. Other search results were not incorporated into this finite supplemental set.
A17: 2026-10-01 | B17: World model | C17: site.arxiv.org/abs "TouchWorld" "Tactile-WAM" | D17: https://arxiv.org/abs/2607.07287; https://arxiv.org/abs/2606.26663 | E17: Query was followed by direct opens of both known primary IDs; checked tactile prediction and manipulation evidence separately.
A18: 2026-10-01 | B18: World model | C18: site.arxiv.org "Mastering Diverse Domains" "manipulation" | D18: https://doi.org/10.1038/s41586-025-08744-2; https://arxiv.org/abs/2301.04104 | E18: Primary Nature search result explicitly identifies robot manipulation among evaluation domains. Direct Nature open returned an internal error; arXiv record opened. Nature and arXiv treated as one report.
A19: 2026-10-01 | B19: World model | C19: site.arxiv.org "Genie: Generative Interactive" "robotics" | D19: https://arxiv.org/html/2402.15391v1; https://openreview.net/pdf?id=bJbSbJskOS | E19: Inspected primary Sec. 3.2 robotics-trained model and Sec. 3.3 game policy transfer; supports robotic predictive-system inclusion without claiming physical robot policy transfer.
A20: 2026-10-01 | B20: World model | C20: site.arxiv.org "PlaNet" "manipulation" "1811.04551" | D20: https://arxiv.org/abs/1811.04551 | E20: Direct primary record was also inspected. Retained as historical general continuous-control background under the proposed manipulation-focused core definition.
... A77: 2026-10-02 | B77: Background / other | C77: Direct primary-source check for contextual citation: https://arxiv.org/abs/2203.09634 | D77: https://arxiv.org/abs/2203.09634 | E77: Identity, title, author list, first-report year and planning/recovery role checked during reviewer revision. Retained as Background R214. No new broad search and no change to the 144 included reports.

Sheet README
A1: Verified-only CSV audit, figures, and source data
A3: Metric | B3: Value
A4: Submitted CSV rows audited | B4: =SUM('Audit Summary'!B2:B4) -> 147
A5: Input rows retained or corrected | B5: =SUM('Audit Summary'!C2:C4) -> 6
A6: Input rows excluded | B6: =SUM('Audit Summary'!D2:D4) -> 141
A7: Verified data-scale output records | B7: =COUNTA('Verified Data Scale'!A2:A8) -> 7
A8: Verified real-robot task records | B8: =COUNTA('World-Gymnast'!A2:A5) -> 4
A9: Submitted columns assessed | B9: =COUNTA('Column Decisions'!A2:A52) -> 51
A11: Decision | B11: Rationale
A12: Exclude corpus_master.csv | B12: All 106 rows are manuscript-derived and lack row-level primary-source URLs, locators, and field-level verification.
A13: Exclude evidence_edges.csv | B13: All 34 edges are manuscript-derived; mixed coding semantics and missing source locators prevent publication-authentic use.
A14: Remove RT-1 hours | B14: The submitted value is an episode-duration assumption, not a source-reported hour measurement.
A15: Correct bound semantics | B15: Cosmos is approximate; V-JEPA 2 and pi_0 are lower bounds; V-JEPA 2-AC is an upper bound.
A16: Correct Dreamer 4 | B16: Use the exact 2,541-hour VPT pool and represent the 100-hour paired-action condition separately.
A17: Retain two figure families | B17: Keep the qualified scale plot and the source-reported World-Gymnast real-robot comparison; omit unsupported ranking and evidence-count plots.
A19: Interpretation warning
A20: The scale values describe different measurement scopes (raw collections, pretraining pools, released robot data, and experimental subsets). They must not be interpreted as a sample-efficiency leaderboard. Only the fields present in the verified sheets are approved for reuse.

Sheet Audit Summary
A1: input_file | B1: input_rows | C1: retained_or_corrected_input_rows | D1: excluded_input_rows | E1: verified_output_rows | F1: audit_conclusion | G1: retention_rate (derived) | H1: reconciliation
A2: corpus_master.csv | B2: 106 | C2: 0 | D2: 106 | E2: 0 | F2: No rows retained because field-level primary-source traceability is absent. | G2: =IF(B2=0,0,C2/B2) -> 0 | H2: =IF(B2=C2+D2,"PASS","CHECK") -> PASS
A3: evidence_edges.csv | B3: 34 | C3: 0 | D3: 34 | E3: 0 | F3: No rows retained because field-level primary-source traceability is absent. | G3: =IF(B3=0,0,C3/B3) -> 0 | H3: =IF(B3=C3+D3,"PASS","CHECK") -> PASS
A4: data_scaling.csv | B4: 7 | C4: 6 | D4: 1 | E4: 7 | F4: Only primary-source-verified scale claims retained; one row split into two claims. | G4: =IF(B4=0,0,C4/B4) -> 0.85714286 | H4: =IF(B4=C4+D4,"PASS","CHECK") -> PASS

Sheet Verified Data Scale
A1: record_id | B1: system | C1: measurement_scope | D1: data_role | E1: reported_hours | F1: bound_type | G1: source_version | H1: source_locator | I1: source_url | J1: verification_date | K1: verification_status | L1: log10_hours (derived)
A2: cosmos_raw | B2: Cosmos WFM | C2: raw candidate video collection | D2: raw_video_collection | E2: 20000000 | F2: approximate | G2: arXiv:2501.03575v3 | H2: Sections 1 and 3.1 | I2: https://arxiv.org/html/2501.03575 | J2: 2026-08-26 | K2: verified_primary_source | L2: =LOG10(E2) -> 7.30103
A3: vjepa2_pretrain | B3: V-JEPA 2 | C3: internet-video pretraining pool | D3: internet_video_pretraining | E3: 1000000 | F3: lower_bound | G3: arXiv:2506.09985v1 | H3: Abstract and Section 2 | I3: https://arxiv.org/html/2506.09985 | J3: 2026-08-26 | K3: verified_primary_source | L3: =LOG10(E3) -> 6
A4: pi0_pretrain | B4: pi_0 | C4: robot-data pretraining mixture | D4: robot_demonstration_pretraining | E4: 10000 | F4: lower_bound | G4: arXiv:2410.24164v4 | H4: Introduction and conclusion | I4: https://arxiv.org/html/2410.24164v4 | J4: 2026-08-26 | K4: verified_primary_source | L4: =LOG10(E4) -> 4
A5: dreamer4_video | B5: Dreamer 4 | C5: VPT gameplay-video pool | D5: gameplay_video_pool | E5: 2541 | F5: exact | G5: arXiv:2509.24527v1 | H5: Section 4.3 and Appendix: Minecraft VPT | I5: https://arxiv.org/pdf/2509.24527 | J5: 2026-08-26 | K5: verified_primary_source | L5: =LOG10(E5) -> 3.4050047
A6: droid_full | B6: DROID | C6: full robot-interaction dataset | D6: robot_interaction_dataset | E6: 350 | F6: exact | G6: arXiv:2403.12945v2 | H6: Abstract | I6: https://arxiv.org/html/2403.12945v2 | J6: 2026-08-26 | K6: verified_primary_source | L6: =LOG10(E6) -> 2.544068
A7: dreamer4_actions | B7: Dreamer 4 | C7: paired-action ablation subset | D7: action_conditioning_ablation | E7: 100 | F7: exact | G7: arXiv:2509.24527v1 | H7: Section 4.3 and Figure 7 | I7: https://arxiv.org/pdf/2509.24527 | J7: 2026-08-26 | K7: verified_primary_source | L7: =LOG10(E7) -> 2
A8: vjepa2_ac | B8: V-JEPA 2-AC | C8: filtered robot-video subset with end-effector states and derived actions | D8: robot_video_with_derived_actions | E8: 62 | F8: upper_bound | G8: arXiv:2506.09985v1 | H8: Abstract and Section 3.1 | I8: https://arxiv.org/html/2506.09985 | J8: 2026-08-26 | K8: verified_primary_source | L8: =LOG10(E8) -> 1.7923917

Sheet World-Gymnast
A1: task | B1: baseline_system | C1: baseline_mean_pct | D1: baseline_se_pct | E1: proposed_system | F1: proposed_mean_pct | G1: proposed_se_pct | H1: trials_per_evaluation | I1: repeated_evaluations | J1: evaluation_protocol | K1: source_version | L1: source_locator | M1: source_url | N1: verification_date | O1: verification_status | P1: delta_pp (derived) | Q1: direction (derived)
A2: Open the drawer | B2: SIMPLER | C2: 34 | D2: 7 | E2: World-Gymnast | F2: 58 | G2: 4 | H2: 10 | I2: 5 | J2: AutoEval real-robot evaluation | K2: arXiv:2602.02454v1 | L2: Section 4.1 and Table 1 | M2: https://arxiv.org/html/2602.02454v1 | N2: 2026-08-26 | O2: verified_primary_source | P2: =F2-C2 -> 24 | Q2: =IF(P2>0,"favors World-Gymnast",IF(P2<0,"favors SIMPLER","tie")) -> favors World-Gymnast
A3: Close the drawer | B3: SIMPLER | C3: 74 | D3: 5 | E3: World-Gymnast | F3: 62 | G3: 6 | H3: 10 | I3: 5 | J3: AutoEval real-robot evaluation | K3: arXiv:2602.02454v1 | L3: Section 4.1 and Table 1 | M3: https://arxiv.org/html/2602.02454v1 | N3: 2026-08-26 | O3: verified_primary_source | P3: =F3-C3 -> -12 | Q3: =IF(P3>0,"favors World-Gymnast",IF(P3<0,"favors SIMPLER","tie")) -> favors SIMPLER
A4: Put the eggplant into the blue sink | B4: SIMPLER | C4: 32 | D4: 10 | E4: World-Gymnast | F4: 72 | G4: 10 | H4: 10 | I4: 5 | J4: AutoEval real-robot evaluation | K4: arXiv:2602.02454v1 | L4: Section 4.1 and Table 1 | M4: https://arxiv.org/html/2602.02454v1 | N4: 2026-08-26 | O4: verified_primary_source | P4: =F4-C4 -> 40 | Q4: =IF(P4>0,"favors World-Gymnast",IF(P4<0,"favors SIMPLER","tie")) -> favors World-Gymnast
A5: Put the eggplant into the yellow basket | B5: SIMPLER | C5: 40 | D5: 10 | E5: World-Gymnast | F5: 78 | G5: 2 | H5: 10 | I5: 5 | J5: AutoEval real-robot evaluation | K5: arXiv:2602.02454v1 | L5: Section 4.1 and Table 1 | M5: https://arxiv.org/html/2602.02454v1 | N5: 2026-08-26 | O5: verified_primary_source | P5: =F5-C5 -> 38 | Q5: =IF(P5>0,"favors World-Gymnast",IF(P5<0,"favors SIMPLER","tie")) -> favors World-Gymnast

Sheet Verified Sources
A1: source_id | B1: system_or_dataset | C1: title | D1: source_version_date | E1: source_version | F1: source_url | G1: verification_date | H1: verification_status
A2: cosmos | B2: Cosmos WFM | C2: Cosmos World Foundation Model Platform for Physical AI | D2: 2025-07-09 | E2: arXiv:2501.03575v3 | F2: https://arxiv.org/html/2501.03575 | G2: 2026-08-26 | H2: verified_primary_source
A3: vjepa2 | B3: V-JEPA 2 / V-JEPA 2-AC | C3: V-JEPA 2: Self-Supervised Video Models Enable Understanding, Prediction and Planning | D3: 2025-06-11 | E3: arXiv:2506.09985v1 | F3: https://arxiv.org/html/2506.09985 | G3: 2026-08-26 | H3: verified_primary_source
A4: pi0 | B4: pi_0 | C4: pi_0: A Vision-Language-Action Flow Model for General Robot Control | D4: 2026-01-08 | E4: arXiv:2410.24164v4 | F4: https://arxiv.org/html/2410.24164v4 | G4: 2026-08-26 | H4: verified_primary_source
A5: dreamer4 | B5: Dreamer 4 | C5: Training Agents Inside of Scalable World Models | D5: 2025-09-29 | E5: arXiv:2509.24527v1 | F5: https://arxiv.org/pdf/2509.24527 | G5: 2026-08-26 | H5: verified_primary_source
A6: droid | B6: DROID | C6: DROID: A Large-Scale In-The-Wild Robot Manipulation Dataset | D6: 2025-04-22 | E6: arXiv:2403.12945v2 | F6: https://arxiv.org/html/2403.12945v2 | G6: 2026-08-26 | H6: verified_primary_source
A7: world_gymnast | B7: World-Gymnast | C7: World-Gymnast: Training Robots with Reinforcement Learning in a World Model | D7: 2026-02-02 | E7: arXiv:2602.02454v1 | F7: https://arxiv.org/html/2602.02454v1 | G7: 2026-08-26 | H7: verified_primary_source

Sheet Source Verification
A1: claim_id | B1: claim_type | C1: submitted_representation | D1: verified_representation | E1: decision | F1: source_locator | G1: source_url | H1: verification_date
A2: cosmos_raw | B2: data scale | C2: 20M presented without a bound | D2: approximately 20M hours | E2: qualifier_corrected | F2: Sections 1 and 3.1 | G2: https://arxiv.org/html/2501.03575 | H2: 2026-08-26
A3: vjepa2_pretrain | B3: data scale | C3: 1M presented as exact | D3: over 1M hours | E3: bound_corrected | F3: Abstract and Section 2 | G3: https://arxiv.org/html/2506.09985 | H3: 2026-08-26
A4: pi0_pretrain | B4: data scale | C4: 10k presented as exact | D4: over 10,000 hours | E4: bound_corrected | F4: Introduction and conclusion | G4: https://arxiv.org/html/2410.24164v4 | H4: 2026-08-26
A5: dreamer4_video | B5: data scale | C5: rounded gameplay-video pool | D5: 2,541 hours | E5: value_corrected | F5: Section 4.3 and Appendix: Minecraft VPT | G5: https://arxiv.org/pdf/2509.24527 | H5: 2026-08-26
A6: dreamer4_actions | B6: data scale | C6: paired-action quantity embedded in a note | D6: 100-hour paired-action condition | E6: claim_split | F6: Section 4.3 and Figure 7 | G6: https://arxiv.org/pdf/2509.24527 | H6: 2026-08-26
A7: droid_full | B7: data scale | C7: 350 hours | D7: 350 hours | E7: retained | F7: Abstract | G7: https://arxiv.org/html/2403.12945v2 | H7: 2026-08-26
A8: vjepa2_ac | B8: data scale | C8: 62 presented as exact | D8: less than 62 hours with end-effector states and derived actions | E8: bound_and_role_corrected | F8: Abstract and Section 3.1 | G8: https://arxiv.org/html/2506.09985 | H8: 2026-08-26
A9: rt1_estimate | B9: data scale | C9: episode-to-hour author estimate | D9: removed | E9: excluded_not_primary_measurement | F9: No reported-hour locator | G9: https://arxiv.org/abs/2212.06817 | H9: 2026-08-26
A10: world_gymnast_open_the_drawer | B10: real-robot success comparison | C10: prior verified extraction | D10: SIMPLER 34±7%; World-Gymnast 58±4% | E10: retained | F10: Section 4.1 and Table 1 | G10: https://arxiv.org/html/2602.02454v1 | H10: 2026-08-26
A11: world_gymnast_close_the_drawer | B11: real-robot success comparison | C11: prior verified extraction | D11: SIMPLER 74±5%; World-Gymnast 62±6% | E11: retained | F11: Section 4.1 and Table 1 | G11: https://arxiv.org/html/2602.02454v1 | H11: 2026-08-26
A12: world_gymnast_put_the_eggplant_into_the_blue_sink | B12: real-robot success comparison | C12: prior verified extraction | D12: SIMPLER 32±10%; World-Gymnast 72±10% | E12: retained | F12: Section 4.1 and Table 1 | G12: https://arxiv.org/html/2602.02454v1 | H12: 2026-08-26
A13: world_gymnast_put_the_eggplant_into_the_yellow_basket | B13: real-robot success comparison | C13: prior verified extraction | D13: SIMPLER 40±10%; World-Gymnast 78±2% | E13: retained | F13: Section 4.1 and Table 1 | G13: https://arxiv.org/html/2602.02454v1 | H13: 2026-08-26

Sheet Record Decisions
A1: input_file | B1: input_row_id | C1: decision | D1: retained_output_id | E1: reason
A2: corpus_master.csv | B2: rt1 | C2: excluded_unverified_record | E2: Record is manuscript-derived and lacks record-level primary-source URL, locator, and field-level verification.
A3: corpus_master.csv | B3: rt2 | C3: excluded_unverified_record | E3: Record is manuscript-derived and lacks record-level primary-source URL, locator, and field-level verification.
A4: corpus_master.csv | B4: oxe | C4: excluded_unverified_record | E4: Record is manuscript-derived and lacks record-level primary-source URL, locator, and field-level verification.
A5: corpus_master.csv | B5: openvla | C5: excluded_unverified_record | E5: Record is manuscript-derived and lacks record-level primary-source URL, locator, and field-level verification.
A6: corpus_master.csv | B6: fast | C6: excluded_unverified_record | E6: Record is manuscript-derived and lacks record-level primary-source URL, locator, and field-level verification.
A7: corpus_master.csv | B7: openvlaoft | C7: excluded_unverified_record | E7: Record is manuscript-derived and lacks record-level primary-source URL, locator, and field-level verification.
A8: corpus_master.csv | B8: octo | C8: excluded_unverified_record | E8: Record is manuscript-derived and lacks record-level primary-source URL, locator, and field-level verification.
A9: corpus_master.csv | B9: pi0 | C9: excluded_unverified_record | E9: Record is manuscript-derived and lacks record-level primary-source URL, locator, and field-level verification.
A10: corpus_master.csv | B10: rdt1b | C10: excluded_unverified_record | E10: Record is manuscript-derived and lacks record-level primary-source URL, locator, and field-level verification.
A11: corpus_master.csv | B11: groot | C11: excluded_unverified_record | E11: Record is manuscript-derived and lacks record-level primary-source URL, locator, and field-level verification.
A12: corpus_master.csv | B12: pi05 | C12: excluded_unverified_record | E12: Record is manuscript-derived and lacks record-level primary-source URL, locator, and field-level verification.
A13: corpus_master.csv | B13: gr2 | C13: excluded_unverified_record | E13: Record is manuscript-derived and lacks record-level primary-source URL, locator, and field-level verification.
... A141: evidence_edges.csv | B141: E034 | C141: excluded_unverified_edge | E141: Edge is manuscript-derived; source locator, independent verification, and normalized evidence semantics are absent.
A142: data_scaling.csv | B142: cosmos::Cosmos WFM | C142: retained_with_qualifier | D142: cosmos_raw | E142: Primary paper reports about 20M hours; encoded as approximate raw collection scale.
A143: data_scaling.csv | B143: vjepa2::V-JEPA 2 | C143: retained_with_qualifier | D143: vjepa2_pretrain | E143: Primary paper reports over 1M hours; encoded as a lower bound.
A144: data_scaling.csv | B144: pi0::pi_0 | C144: retained_with_qualifier | D144: pi0_pretrain | E144: Primary paper reports over 10,000 hours; encoded as a lower bound.
A145: data_scaling.csv | B145: dreamer4::Dreamer 4 | C145: corrected_and_split | D145: dreamer4_video;dreamer4_actions | E145: Video pool corrected to 2,541 hours; 100-hour paired-action condition represented separately.
A146: data_scaling.csv | B146: rt1::RT-1 | C146: excluded_author_estimate | E146: The hour value is an episode-duration conversion, not a primary-source-reported measurement.
A147: data_scaling.csv | B147: droid::DROID | C147: retained | D147: droid_full | E147: Primary paper reports 350 hours of interaction data.
A148: data_scaling.csv | B148: vjepa2::V-JEPA 2-AC | C148: retained_with_qualifier | D148: vjepa2_ac | E148: Primary paper reports less than 62 hours; encoded as an upper bound.

Sheet Column Decisions
A1: input_file | B1: input_column | C1: decision | D1: reason
A2: corpus_master.csv | B2: bib_key | C2: audit_identifier_only | D2: Retained only in the exclusion log, not as a scientific field.
A3: corpus_master.csv | B3: system_name | C3: excluded | D3: No field-level primary-source URL, locator, and independent verification in the submitted CSV.
A4: corpus_master.csv | B4: family | C4: excluded | D4: No field-level primary-source URL, locator, and independent verification in the submitted CSV.
A5: corpus_master.csv | B5: year | C5: excluded | D5: No field-level primary-source URL, locator, and independent verification in the submitted CSV.
A6: corpus_master.csv | B6: primary_group | C6: excluded | D6: No field-level primary-source URL, locator, and independent verification in the submitted CSV.
A7: corpus_master.csv | B7: secondary_labels | C7: excluded | D7: No field-level primary-source URL, locator, and independent verification in the submitted CSV.
A8: corpus_master.csv | B8: wm_role_label | C8: excluded | D8: No field-level primary-source URL, locator, and independent verification in the submitted CSV.
A9: corpus_master.csv | B9: corpus_status | C9: excluded | D9: No field-level primary-source URL, locator, and independent verification in the submitted CSV.
A10: corpus_master.csv | B10: backbone_or_substrate | C10: excluded | D10: No field-level primary-source URL, locator, and independent verification in the submitted CSV.
A11: corpus_master.csv | B11: action_representation | C11: excluded | D11: No field-level primary-source URL, locator, and independent verification in the submitted CSV.
A12: corpus_master.csv | B12: state_space | C12: excluded | D12: No field-level primary-source URL, locator, and independent verification in the submitted CSV.
... A52: data_scaling.csv | B52: note | C52: excluded_or_replaced | D52: Unsupported ratios and estimates were removed; source-backed scope is recorded separately.

Sheet Figures
A1: Publication-ready figures generated from verified-only data
A2: Vector PDFs and 600-dpi PNGs are included separately in the final package.
A4: Scale label | B4: log10(hours) | C4: bound type
A5: ='Verified Data Scale'!B2&" — "&'Verified Data Scale'!C2 -> Cosmos WFM — raw candidate video collection | B5: ='Verified Data Scale'!L2 -> 7.30103 | C5: ='Verified Data Scale'!F2 -> approximate
A6: ='Verified Data Scale'!B3&" — "&'Verified Data Scale'!C3 -> V-JEPA 2 — internet-video pretraining pool | B6: ='Verified Data Scale'!L3 -> 6 | C6: ='Verified Data Scale'!F3 -> lower_bound
A7: ='Verified Data Scale'!B4&" — "&'Verified Data Scale'!C4 -> pi_0 — robot-data pretraining mixture | B7: ='Verified Data Scale'!L4 -> 4 | C7: ='Verified Data Scale'!F4 -> lower_bound
A8: ='Verified Data Scale'!B5&" — "&'Verified Data Scale'!C5 -> Dreamer 4 — VPT gameplay-video pool | B8: ='Verified Data Scale'!L5 -> 3.4050047 | C8: ='Verified Data Scale'!F5 -> exact
A9: ='Verified Data Scale'!B6&" — "&'Verified Data Scale'!C6 -> DROID — full robot-interaction dataset | B9: ='Verified Data Scale'!L6 -> 2.544068 | C9: ='Verified Data Scale'!F6 -> exact
A10: ='Verified Data Scale'!B7&" — "&'Verified Data Scale'!C7 -> Dreamer 4 — paired-action ablation subset | B10: ='Verified Data Scale'!L7 -> 2 | C10: ='Verified Data Scale'!F7 -> exact
A11: ='Verified Data Scale'!B8&" — "&'Verified Data Scale'!C8 -> V-JEPA 2-AC — filtered robot-video subset with end-effector states and derived actions | B11: ='Verified Data Scale'!L8 -> 1.7923917 | C11: ='Verified Data Scale'!F8 -> upper_bound
A23: Task | B23: SIMPLER | C23: World-Gymnast
A24: ='World-Gymnast'!A2 -> Open the drawer | B24: ='World-Gymnast'!C2 -> 34 | C24: ='World-Gymnast'!F2 -> 58
A25: ='World-Gymnast'!A3 -> Close the drawer | B25: ='World-Gymnast'!C3 -> 74 | C25: ='World-Gymnast'!F3 -> 62
A26: ='World-Gymnast'!A4 -> Put the eggplant into the blue sink | B26: ='World-Gymnast'!C4 -> 32 | C26: ='World-Gymnast'!F4 -> 72
A27: ='World-Gymnast'!A5 -> Put the eggplant into the yellow basket | B27: ='World-Gymnast'!C5 -> 40 | C27: ='World-Gymnast'!F5 -> 78

Sheet Plot Index
A1: file | B1: format | C1: resolution | D1: source data | E1: recommended use
A2: verified_data_scale.pdf | B2: Vector PDF | C2: embedded TrueType fonts | D2: Verified Data Scale | E2: Main text L3; preserve scope and bound caveat
A3: verified_data_scale.png | B3: PNG | C3: 600 dpi | D3: Verified Data Scale | E3: Preview or raster-only workflow
A4: verified_world_gymnast_real_robot.pdf | B4: Vector PDF | C4: embedded TrueType fonts | D4: World-Gymnast | E4: Main text or supplement
A5: verified_world_gymnast_real_robot.png | B5: PNG | C5: 600 dpi | D5: World-Gymnast | E5: Preview or raster-only workflow

Sheet Cited Papers
A1: Cited papers and sources
A3: Cited references | C3: =COUNTA(K9:K183) -> 175 | D3: Compiled from the current 29-page draft on 24 September 2026. | F3: Paper citations | G3: =COUNTIFS(G9:G183,"Paper") -> 169
A4: Unresolved decisions | C4: =C3-COUNTIFS(H9:H183,"Include")-COUNTIFS(H9:H183,"Background")-COUNTIFS(H9:H183,"Exclude")-COUNTIFS(H9:H183,"Duplicate") -> 175 | D4: References and years follow the draft. Use the links and metadata notes to check source details. | F4: Other technical sources | G4: =COUNTIFS(G9:G183,"Technical release / software") -> 6
A5: Marked Include | C5: =COUNTIFS(H9:H183,"Include") -> 0 | D5: Choose Include, Background, Exclude or Duplicate in the amber Review decision column.
A6: Figure 3 count | C6: =IF(C4>0,"Not finalized",C5) -> Not finalized | D6: Settle Pending, blank or invalid decisions before using the count for Figure 3. Extend count ranges if adding rows.
A8: Ref. | B8: Year (as cited) | C8: Reference (as cited) | D8: Two-sentence summary | E8: Primary source link | F8: Topic / role | G8: Source type | H8: Review decision | I8: Decision reason | J8: Report ID | K8: Citation key | L8: Metadata notes | M8: Summary basis
A9: 1 | B9: 2023 | C9: B. Zitkovich, T. Yu, S. Xu, P. Xu, T. Xiao, F. Xia, J. Wu, P. Wohlhart, S. Welker, A. Wahid et al., “RT-2: Vision-language-action models transfer web knowledge to robotic control,” in Proc. Conf. Robot Learn. (CoRL), 2023, arXiv:2307.15818. | D9: RT-2 represents robot actions as tokens and co-trains on robotic trajectories and vision-language tasks. It studies how knowledge learned from web data transfers into language-conditioned manipulation. | E9: https://arxiv.org/abs/2307.15818 | F9: VLA/action policy | G9: Paper | H9: Pending | J9: arXiv:2307.15818 | K9: rt2 | M9: Previously primary-source-checked README catalogue and manuscript discussion; no new quantitative claims.
A10: 2 | B10: 2024 | C10: M. J. Kim, K. Pertsch, S. Karamcheti, T. Xiao, A. Balakrishna, S. Nair, R. Rafailov, E. Foster, G. Lam, P. Sanketi et al., “OpenVLA: An open-source vision-language-action model,” in Proc. Conf. Robot Learn. (CoRL), 2024, arXiv:2406.09246. | D10: OpenVLA combines pretrained visual-language representations with autoregressive robot-action prediction in an open model. It provides a generalist manipulation policy that can be adapted to new tasks through fine-tuning. | E10: https://arxiv.org/abs/2406.09246 | F10: VLA/action policy | G10: Paper | H10: Pending | J10: arXiv:2406.09246 | K10: openvla | M10: Previously primary-source-checked README catalogue and manuscript discussion; no new quantitative claims.
A11: 3 | B11: 2024 | C11: Open X-Embodiment Collaboration, “Open X-Embodiment: Robotic learning datasets and RT-X models,” in Proc. IEEE Int. Conf. Robot. Autom. (ICRA), 2024, arXiv:2310.08864. | D11: Open X-Embodiment brings together robot demonstration datasets collected across different embodiments. The accompanying RT-X models examine whether training on this combined data improves transfer between robotic platforms. | E11: https://arxiv.org/abs/2310.08864 | F11: Dataset/benchmark | G11: Paper | H11: Pending | J11: arXiv:2310.08864 | K11: oxe | L11: Hybrid dataset/model report: OXE and RT-X are one cited report; category reflects its dataset role. | M11: Previously primary-source-checked README catalogue and manuscript discussion; no new quantitative claims.
A12: 4 | B12: 2025 | C12: K. Black, N. Brown, D. Driess, A. Esmail, M. Equi, C. Finn, N. Fusai, L. Groom, K. Hausman, B. Ichter et al., “π0: A vision-language-action flow model for general robot control,” in Proc. Robot.: Sci. Syst. (RSS), 2025, arXiv:2410.24164. | D12: The π0 model couples a pretrained vision-language backbone to a flow-matching action expert. It generates continuous action chunks for manipulation across tasks and robot embodiments. | E12: https://arxiv.org/abs/2410.24164 | F12: VLA/action policy | G12: Paper | H12: Pending | J12: arXiv:2410.24164 | K12: pi0 | M12: Previously primary-source-checked README catalogue and manuscript discussion; no new quantitative claims.
A13: 5 | B13: 2025 | C13: J. Bjorck, F. Castañeda, N. Cherniadev, X. Da, R. Ding, L. Fan, Y. Fang, D. Fox, F. Hu, S. Huang et al., “GR00T N1: An open foundation model for generalist humanoid robots,” arXiv preprint, 2025, arXiv:2503.14734. | D13: GR00T N1 combines vision-language interpretation with diffusion-based action generation for humanoid robots. Its dual-system design connects slower semantic processing with continuous control. | E13: https://arxiv.org/abs/2503.14734 | F13: VLA/action policy | G13: Paper | H13: Pending | J13: arXiv:2503.14734 | K13: groot | M13: Previously primary-source-checked README catalogue and manuscript discussion; no new quantitative claims.
A14: 6 | B14: 2025 | C14: Gemini Robotics Team, “Gemini Robotics: Bringing AI into the physical world,” arXiv preprint, 2025, arXiv:2503.20020. | D14: Gemini Robotics extends a Gemini vision-language model to generate robot actions from observations and instructions. The developer-reported study examines manipulation capabilities and transfer across embodiments. | E14: https://arxiv.org/abs/2503.20020 | F14: VLA/action policy | G14: Paper | H14: Pending | J14: arXiv:2503.20020 | K14: geminirobotics | L14: Vendor-authored technical research paper, not reclassified as nonpaper simply because evidence is vendor-reported. | M14: Previously primary-source-checked README catalogue and manuscript discussion; no new quantitative claims.
A15: 7 | B15: 2025 | C15: Figure AI, “Helix: A vision-language-action model for generalist humanoid control,” Figure AI technical blog, , 2025. | D15: Helix combines a slower vision-language component with a faster continuous-action controller for humanoid upper-body manipulation. The cited vendor release describes this dual-system architecture and its demonstrated behaviors. | E15: https://www.figure.ai/news/helix | F15: Vendor technical release | G15: Technical release / software | H15: Pending | J15: https://www.figure.ai/news/helix | K15: helix | M15: Previously primary-source-checked README catalogue and manuscript discussion; no new quantitative claims.
A16: 8 | B16: 2025 | C16: M. J. Kim, C. Finn, and P. Liang, “Fine-tuning vision-languageaction models: Optimizing speed and success,” arXiv preprint, 2025, arXiv:2502.19645. | D16: OpenVLA-OFT studies fine-tuning choices for faster and more successful VLA control. Its recipe uses action chunking and parallel continuous regression instead of sequential action-token decoding. | E16: https://arxiv.org/abs/2502.19645 | F16: Policy training/adaptation method | G16: Paper | H16: Pending | J16: arXiv:2502.19645 | K16: openvlaoft | M16: Previously primary-source-checked README catalogue and manuscript discussion; no new quantitative claims.
A17: 9 | B17: 2025 | C17: S. Fei, S. Wang, J. Shi, Z. Dai, J. Cai, P. Qian, L. Ji, X. He, S. Zhang, Z. Fei et al., “LIBERO-Plus: In-depth robustness analysis of vision-language-action models,” arXiv preprint, 2025, arXiv:2510.13626. | D17: LIBERO-Plus probes manipulation policies with controlled visual, physical-configuration, and instruction perturbations. Its instruction-removal and goal-replacement tests distinguish apparent language robustness from reliable instruction grounding. | E17: https://arxiv.org/abs/2510.13626 | F17: Dataset/benchmark | G17: Paper | H17: Pending | J17: arXiv:2510.13626 | K17: liberoplus | M17: Previously primary-source-checked README catalogue and manuscript discussion; no new quantitative claims.
A18: 10 | B18: 2025 | C18: A. Jain, M. Zhang, K. Arora, W. Chen, M. Torne, M. Z. Irshad, S. Zakharov, Y. Wang, S. Levine, C. Finn et al., “PolaRiS: Scalable real-to-sim evaluations for generalist robot policies,” arXiv preprint, 2025, arXiv:2512.16881. | D18: PolaRiS reconstructs interactive simulation environments from short scans of real scenes for robot-policy evaluation. Paired simulated and physical tests examine how well these evaluations predict real-world performance. | E18: https://arxiv.org/abs/2512.16881 | F18: Dataset/benchmark | G18: Paper | H18: Pending | J18: arXiv:2512.16881 | K18: polaris | L18: Evaluation framework/method paper grouped with benchmark/evaluation sources; not a mere data file. | M18: Primary-source abstract or article and manuscript context; source reviewed 2026-09-24.
A19: 11 | B19: 2026 | C19: H. Li, Y. Zuo, J. Yu, Y. Zhang, Z. Yang, K. Zhang, X. Zhu, Y. Zhang, T. Chen, G. Cui et al., “SimpleVLA-RL: Scaling VLA training via reinforcement learning,” in Proc. Int. Conf. Learn. Representations (ICLR), 2026, arXiv:2509.09674. | D19: SimpleVLA-RL adapts VLA policies through online reinforcement learning with stochastic action-token decoding. It evaluates how interaction changes performance under different demonstration budgets. | E19: https://arxiv.org/abs/2509.09674 | F19: Policy training/adaptation method | G19: Paper | H19: Pending | J19: arXiv:2509.09674 | K19: simplevlarl | M19: Previously primary-source-checked README catalogue and manuscript discussion; no new quantitative claims.
A20: 12 | B20: 2025 | C20: S. Tan, K. Dou, Y. Zhao, and P. Krähenbühl, “Interactive post-training for vision-language-action models,” arXiv preprint, 2025, arXiv:2505.17016. | D20: RIPT-VLA fine-tunes pretrained robot policies through reinforcement learning with sparse task-success rewards. It studies interactive post-training of both lightweight and larger policies under limited supervision. | E20: https://arxiv.org/abs/2505.17016 | F20: Policy training/adaptation method | G20: Paper | H20: Pending | J20: arXiv:2505.17016 | K20: riptvla | M20: Previously primary-source-checked README catalogue and manuscript discussion; no new quantitative claims.
A21: 13 | B21: 2025 | C21: M. Assran, A. Bardes, D. Fan, Q. Garrido, R. Howes, M. Komeili, M. Muckley, A. Rizvi, C. Roberts, K. Sinha et al., “V-JEPA 2: Selfsupervised video models enable understanding, prediction and planning,” arXiv preprint, 2025, arXiv:2506.09985. | D21: V-JEPA 2 learns predictive video representations from action-free video at scale. Its separately adapted V-JEPA 2-AC model predicts action-conditioned latent transitions for planning toward image goals. | E21: https://arxiv.org/abs/2506.09985 | F21: World model/predictive system | G21: Paper | H21: Pending | J21: arXiv:2506.09985 | K21: vjepa2 | M21: Previously primary-source-checked README catalogue and manuscript discussion; no new quantitative claims.
A22: 14 | B22: 2025 | C22: J. Jang, S. Ye, Z. Lin, J. Xiang, J. Bjorck, Y. Fang, F. Hu, S. Huang, K. Kundalia, Y.-C. Lin et al., “DreamGen: Unlocking generalization in robot learning through video world models,” arXiv preprint, 2025, arXiv:2505.12705. | D22: DreamGen generates task-conditioned robot videos and obtains pseudo-action labels through inverse dynamics. The resulting synthetic trajectories augment policy training as an offline data-generation pipeline. | E22: https://arxiv.org/abs/2505.12705 | F22: World model/predictive system | G22: Paper | H22: Pending | J22: arXiv:2505.12705 | K22: dreamgen | M22: Previously primary-source-checked README catalogue and manuscript discussion; no new quantitative claims.
A23: 15 | B23: 2025 | C23: D. Hafner, W. Yan, and T. Lillicrap, “Training agents inside of scalable world models,” arXiv preprint, 2025, arXiv:2509.24527. | D23: Dreamer 4 trains agents inside a scalable video world model learned from offline data. Its main application is Minecraft, while separate ablations examine the amount of action-labeled video required for prediction. | E23: https://arxiv.org/abs/2509.24527 | F23: World model/predictive system | G23: Paper | H23: Pending | J23: arXiv:2509.24527 | K23: dreamer4 | M23: Previously primary-source-checked README catalogue and manuscript discussion; no new quantitative claims.
A24: 16 | B24: 2025 | C24: J. Cen, C. Yu, H. Yuan, Y. Jiang, S. Huang, J. Guo, X. Li, Y. Song, H. Luo, F. Wang et al., “WorldVLA: Towards autoregressive action world model,” arXiv preprint, 2025, arXiv:2506.21539. | D24: WorldVLA uses shared autoregressive modeling for robot actions and future observations. Its predictive-training experiments provide evidence about joint learning without establishing a general advantage for online candidate-action search. | E24: https://arxiv.org/abs/2506.21539 | F24: World model/predictive system | G24: Paper | H24: Pending | J24: arXiv:2506.21539 | K24: worldvla | M24: Previously primary-source-checked README catalogue and manuscript discussion; no new quantitative claims.
A25: 17 | B25: 2026 | C25: M. J. Kim, Y. Gao, T.-Y. Lin, Y.-C. Lin, Y. Ge, G. Lam, P. Liang, S. Song, M.-Y. Liu, C. Finn, and J. Gu, “Cosmos Policy: Fine-tuning video models for visuomotor control and planning,” in Proc. Int. Conf. Learn. Representations (ICLR), 2026, arXiv:2601.16163. | D25: Cosmos Policy adapts a video model to jointly generate actions, future states, and values. It evaluates direct visuomotor execution alongside rollout refinement and candidate selection for planning. | E25: https://arxiv.org/abs/2601.16163 | F25: World model/predictive system | G25: Paper | H25: Pending | J25: arXiv:2601.16163 | K25: cosmospolicy | M25: Previously primary-source-checked README catalogue and manuscript discussion; no new quantitative claims.
A26: 18 | B26: 2026 | C26: Y. Ma, Z. Song, Y. Zhuang, J. Hao, and I. King, “A survey on vision-language-action models for embodied AI,” IEEE Trans. Neural Netw. Learn. Syst, 2026, arXiv:2405.14093. | D26: This survey organizes VLA research into model components, low-level control policies, and high-level task planners. It also reviews datasets, simulators, and benchmarks that support language-conditioned embodied action. | E26: https://arxiv.org/abs/2405.14093 | F26: Survey | G26: Paper | H26: Pending | J26: arXiv:2405.14093 | K26: ma2024survey | M26: Primary-source abstract or article and manuscript context; source reviewed 2026-09-24.
A27: 19 | B27: 2025 | C27: Y. Zhong, F. Bai, S. Cai, X. Huang, Z. Chen, X. Zhang, Y. Wang, S. Guo, T. Guan, K. N. Lui et al., “A survey on vision-language-action models: An action tokenization perspective,” arXiv preprint, 2025, arXiv:2507.01925. | D27: This survey compares VLA systems through the intermediate representations used to express actions. Its tokenization taxonomy spans language, code, affordances, trajectories, goals, latent codes, raw actions, and reasoning. | E27: https://arxiv.org/abs/2507.01925 | F27: Survey | G27: Paper | H27: Pending | J27: arXiv:2507.01925 | K27: zhong2025token | M27: Primary-source abstract or article and manuscript context; source reviewed 2026-09-24.
A28: 20 | B28: 2025 | C28: K. Kawaharazuka, J. Oh, J. Yamada, I. Posner, and Y. Zhu, “Visionlanguage-action models for robotics: A review towards real-world applications,” IEEE Access, vol. 13, pp. 162 467–162 504, 2025. | D28: This review connects VLA architectures and learning methods with the practical requirements of robot deployment. It covers hardware platforms, data collection, augmentation, datasets, and evaluation alongside model design. | E28: https://arxiv.org/abs/2510.07077 | F28: Survey | G28: Paper | H28: Pending | J28: arXiv:2510.07077 | K28: kawaharazuka2025 | M28: Primary-source abstract or article and manuscript context; source reviewed 2026-09-24.
A29: 21 | B29: 2026 | C29: M. U. Din, W. Akram, L. S. Saoud, J. Rosell, and I. Hussain, “Multimodal fusion with vision-language-action models for robotic manipulation: A systematic review,” Information Fusion, vol. 129, p. 104062, 2026. | D29: This systematic review organizes manipulation VLAs by multimodal fusion strategies, architectures, datasets, and evaluation resources. It also develops an agentic outlook in which planners use VLA skills with verification and diagnostic feedback. | E29: https://doi.org/10.1016/j.inffus.2025.104062 | F29: Survey | G29: Paper | H29: Pending | J29: 10.1016/j.inffus.2025.104062 | K29: din2025priorvlasurvey | M29: Published article abstract and agentic-framework discussion, previously checked in the authors institutional repository.
A30: 22 | B30: 2026 | C30: B. Hou, G. Li, J. Jia, T. An, X. Guo, S. Leng, H. Geng, Y. Ze, T. Harada, P. Torr et al., “World model for robot learning: A comprehensive survey,” arXiv preprint, 2026, arXiv:2605.00080. | D30: This survey reviews world models according to their roles in robot-policy learning, planning, simulation, data generation, and evaluation. It relates policy coupling and controllable video prediction to datasets and experimental protocols across embodied domains. | E30: https://arxiv.org/abs/2605.00080 | F30: Survey | G30: Paper | H30: Pending | J30: arXiv:2605.00080 | K30: hou2026wm | M30: Primary-source abstract or article and manuscript context; source reviewed 2026-09-24.
... A41: 33 | B41: 2025 | C41: J. Ding, Y. Zhang, Y. Shang, Y. Zhang, Z. Zong, J. Feng, Y. Yuan, H. Su, N. Li, N. Sukiennik et al., “Understanding world or predicting future? A comprehensive survey of world models,” ACM Computing Surveys, vol. 58, no. 3, pp. 1–38, 2025. | D41: This survey distinguishes world models that construct internal representations from those that simulate future states. It reviews these roles across robotics, autonomous driving, and other domains and identifies open modeling challenges. | E41: https://doi.org/10.1145/3746449 | F41: Survey | G41: Paper | H41: Pending | J41: https://doi.org/10.1145/3746449 | K41: ding2025worldsurvey | M41: Primary-source abstract or article and manuscript context; source reviewed 2026-09-24.
A42: 34 | B42: 2025 | C42: X. Li et al., “A step toward world models: A survey on robotic manipulation,” arXiv preprint, 2025, arXiv:2511.02097. | D42: This survey examines manipulation methods that exhibit world-model capabilities, including approaches not explicitly labeled as world models. It uses their roles in perception, prediction, and control to identify the components needed for broader predictive robotics. | E42: https://arxiv.org/abs/2511.02097 | F42: Survey | G42: Paper | H42: Pending | J42: arXiv:2511.02097 | K42: li2025step | L42: The as-cited reference lists X. Li et al.; the primary source instead identifies Peng-Fei Zhang and colleagues. Citation number, key and as-cited wording are retained for traceability; the author attribution requires correction in the manuscript bibliography. | M42: Primary-source abstract or article and manuscript context; source reviewed 2026-09-24.
A43: 35 | B43: 2025 | C43: Jiang et al., “A survey on vision-language-action models for autonomous driving,” in Proc. IEEE/CVF Int. Conf. Comput. Vis. Workshops (ICCVW), WDFM-AD, 2025. | D43: This survey reviews vision-language-action architectures for autonomous driving, including their progression toward reasoning-centered control. It compares vehicle-domain datasets and evaluation concerns such as safety, instruction following, and explanation quality. | E43: https://openaccess.thecvf.com/content/ICCV2025W/WDFM-AD/html/Jiang_A_Survey_on_Vision-Language-Action_Models_for_Autonomous_Driving_ICCVW_2025_paper.html | F43: Survey | G43: Paper | H43: Pending | J43: https://openaccess.thecvf.com/content/ICCV2025W/WDFM-AD/html/Jiang_A_Survey_on_Vision-Language-Action_Models_for_Autonomous_Driving_ICCVW_2025_paper.html | K43: jiang2025driving | M43: Primary-source abstract or article and manuscript context; source reviewed 2026-09-24.
A44: 36 | B44: 2025 | C44: D. Zhang, J. Sun, C. Hu, X. Wu, Z. Yuan, R. Zhou, F. Shen, and Q. Zhou, “Pure vision language action (VLA) models: A comprehensive survey,” arXiv preprint, 2025, arXiv:2509.19012. | D44: This survey classifies VLA methods into autoregressive, diffusion, reinforcement-learning, hybrid, and specialized approaches. It connects these design choices to application scenarios, datasets, benchmarks, and simulators. | E44: https://arxiv.org/abs/2509.19012 | F44: Survey | G44: Paper | H44: Pending | J44: arXiv:2509.19012 | K44: zhang2025pure | M44: Primary-source abstract or article and manuscript context; source reviewed 2026-09-24.
A45: 37 | B45: 2021 | C45: M. J. Page, J. E. McKenzie, P. M. Bossuyt, I. Boutron, T. C. Hoffmann, C. D. Mulrow, L. Shamseer, J. M. Tetzlaff, E. A. Akl, S. E. Brennan et al., “The PRISMA 2020 statement: An updated guideline for reporting systematic reviews,” BMJ, vol. 372, p. n71, 2021. | D45: The PRISMA 2020 statement provides reporting guidance for systematic reviews through checklists and flow-diagram templates. It supports transparent reporting of searches, selection, synthesis, and limitations rather than certifying that a review was conducted correctly. | E45: https://doi.org/10.1136/bmj.n71 | F45: Methodology | G45: Paper | H45: Pending | J45: https://doi.org/10.1136/bmj.n71 | K45: prisma2020 | M45: Original statement and official PRISMA statement/checklist descriptions; reviewed 2026-09-24.
A46: 38 | B46: 2023 | C46: A. Brohan, N. Brown, J. Carbajal, Y. Chebotar, J. Dabis, C. Finn, K. Gopalakrishnan, K. Hausman, A. Herzog, J. Hsu et al., “RT-1: Robotics transformer for real-world control at scale,” arXiv preprint, 2023, arXiv:2212.06817. | D46: RT-1 maps camera observations and language instructions to discretized robot commands using a transformer policy. It is an early language-conditioned control precursor to later VLA foundation models. | E46: https://arxiv.org/abs/2212.06817 | F46: VLA/action policy | G46: Paper | H46: Pending | J46: arXiv:2212.06817 | K46: rt1 | M46: Previously primary-source-checked README catalogue and manuscript discussion; no new quantitative claims.
A47: 39 | B47: 2023 | C47: Y. Jiang, A. Gupta, Z. Zhang, G. Wang, Y. Dou, Y. Chen, L. Fei-Fei, A. Anandkumar, Y. Zhu, and L. Fan, “VIMA: General robot manipulation with multimodal prompts,” in International Conference on Machine Learning (ICML), 2023, arXiv:2210.03094. | D47: VIMA specifies manipulation tasks using prompts that interleave text and images. A transformer policy converts these multimodal task descriptions and observations into robot actions. | E47: https://arxiv.org/abs/2210.03094 | F47: VLA/action policy | G47: Paper | H47: Pending | J47: arXiv:2210.03094 | K47: vima | M47: Previously primary-source-checked README catalogue and manuscript discussion; no new quantitative claims.
A48: 40 | B48: 2024 | C48: X. Li, M. Liu, H. Zhang, C. Yu, J. Xu, H. Wu, C. Cheang, Y. Jing, W. Zhang, H. Liu et al., “Vision-language foundation models as effective robot imitators,” in Proc. Int. Conf. Learn. Representations (ICLR), 2024, arXiv:2311.01378. | D48: RoboFlamingo adapts a pretrained OpenFlamingo vision-language model for robot imitation learning. An action-prediction interface connects multimodal understanding to language-conditioned manipulation. | E48: https://arxiv.org/abs/2311.01378 | F48: VLA/action policy | G48: Paper | H48: Pending | J48: arXiv:2311.01378 | K48: roboflamingo | M48: Previously primary-source-checked README catalogue and manuscript discussion; no new quantitative claims.
A49: 41 | B49: 2024 | C49: D. Niu, Y. Sharma, G. Biamby, J. Quenum, Y. Bai, B. Shi, T. Darrell, and R. Herzig, “LLARV A: Vision-action instruction tuning enhances robot learning,” in Proc. Conf. Robot Learn. (CoRL), 2024, arXiv:2406.11815. | D49: LLARVA uses vision-action instruction tuning with intermediate two-dimensional visual traces. These traces help align multimodal representations with the robot behaviors learned during adaptation. | E49: https://arxiv.org/abs/2406.11815 | F49: VLA/action policy | G49: Paper | H49: Pending | J49: arXiv:2406.11815 | K49: llarva | M49: Previously primary-source-checked README catalogue and manuscript discussion; no new quantitative claims.
A50: 42 | B50: 2025 | C50: S. Ye, J. Jang, B. Jeon, S. Joo, J. Yang, B. Peng, A. Mandlekar, R. Tan et al., “Latent action pretraining from videos,” in International Conference on Learning Representations (ICLR), 2025, arXiv:2410.11758. | D50: LAPA learns latent action representations from video without ground-truth action labels during pretraining. Robot data subsequently maps the pretrained policy into executable robot actions. | E50: https://arxiv.org/abs/2410.11758 | F50: VLA/action policy | G50: Paper | H50: Pending | J50: arXiv:2410.11758 | K50: lapa | M50: Previously primary-source-checked README catalogue and manuscript discussion; no new quantitative claims.
A51: 43 | B51: 2025 | C51: K. Pertsch, K. Stachowicz, B. Ichter, D. Driess, S. Nair, Q. Vuong, O. Mees, C. Finn, and S. Levine, “FAST: Efficient action tokenization for vision-language-action models,” in Proc. Robot.: Sci. Syst. (RSS), 2025, arXiv:2501.09747. | D51: FAST compresses continuous action chunks into frequency-domain tokens for autoregressive prediction. The π0-FAST policy demonstrates how this representation can support action generation for dexterous control. | E51: https://arxiv.org/abs/2501.09747 | F51: VLA/action policy | G51: Paper | H51: Pending | J51: arXiv:2501.09747 | K51: fast | M51: Previously primary-source-checked README catalogue and manuscript discussion; no new quantitative claims.
A52: 44 | B52: 2025 | C52: Liang et al., “Discrete diffusion VLA: Bringing discrete diffusion to action decoding in vision-language-action policies,” arXiv preprint, 2025, arXiv:2508.20072. | D52: Discrete Diffusion VLA generates discretized action chunks through iterative diffusion-style refinement within a shared transformer. It explores parallel action decoding as an alternative to sequential autoregressive generation. | E52: https://arxiv.org/abs/2508.20072 | F52: VLA/action policy | G52: Paper | H52: Pending | J52: arXiv:2508.20072 | K52: ddvla | M52: Previously primary-source-checked README catalogue and manuscript discussion; no new quantitative claims.
A53: 45 | B53: 2024 | C53: Octo Model Team, D. Ghosh, H. Walke, K. Pertsch, K. Black, O. Mees, S. Dasari, J. Hejna, T. Kreiman, C. Xu et al., “Octo: An open-source generalist robot policy,” in Proc. Robot.: Sci. Syst. (RSS), 2024, arXiv:2405.12213. | D53: Octo is an open generalist robot policy with a diffusion action head and language- or image-goal conditioning. Its adaptation interface accommodates new observation inputs and robot action spaces. | E53: https://arxiv.org/abs/2405.12213 | F53: VLA/action policy | G53: Paper | H53: Pending | J53: arXiv:2405.12213 | K53: octo | M53: Previously primary-source-checked README catalogue and manuscript discussion; no new quantitative claims.
A54: 46 | B54: 2025 | C54: S. Liu, L. Wu, B. Li, H. Tan, H. Chen, Z. Wang, K. Xu, H. Su, and J. Zhu, “RDT-1B: A diffusion foundation model for bimanual manipulation,” arXiv preprint, 2025, arXiv:2410.07864. | D54: RDT-1B uses a diffusion transformer to generate bimanual robot actions conditioned on multimodal inputs. A unified action representation supports learning from robots with different configurations. | E54: https://arxiv.org/abs/2410.07864 | F54: VLA/action policy | G54: Paper | H54: Pending | J54: arXiv:2410.07864 | K54: rdt1b | M54: Previously primary-source-checked README catalogue and manuscript discussion; no new quantitative claims.
... A72: 64 | B72: 2025 | C72: Q. Zhao et al., “CoT-VLA: Visual chain-of-thought reasoning for vision-language-action models,” in Proc. IEEE/CVF Conf. Comput. Vis. Pattern Recognit. (CVPR), 2025, arXiv:2503.22020. | D72: CoT-VLA predicts future images as intermediate visual goals before generating action sequences. This visual chain of thought links prediction to policy execution without itself establishing candidate-action search. | E72: https://arxiv.org/abs/2503.22020 | F72: World model/predictive system | G72: Paper | H72: Pending | J72: arXiv:2503.22020 | K72: cotvla | M72: Previously primary-source-checked README catalogue and manuscript discussion; no new quantitative claims.
A73: 65 | B73: 2025 | C73: M. U. Din, J. Rosell, W. Akram, I. Zaplana, M. A. Roa, L. Seneviratne, and I. Hussain, “Ontology-driven prompt tuning for LLM-based task and motion planning,” Robot. Auton. Syst, 2025. | D73: This framework enriches language-model prompts with ontology-based task knowledge and descriptions of the environment. It uses this knowledge to improve semantic consistency and temporal ordering in task-and-motion plans. | E73: https://arxiv.org/abs/2412.07493v1 | F73: Planning/control context | G73: Paper | H73: Pending | J73: arXiv:2412.07493 | K73: ontollmtamp | L73: The linked arXiv v1 (10 December 2024) matches the supplied title and seven-author list. The as-cited 2025 Robotics and Autonomous Systems entry mixes version metadata: the journal article is ‘Onto-LLM-TAMP: Knowledge-oriented Task and Motion Planning using Large Language Models,’ vol. 200, article 105404 (2026), DOI 10.1016/j.robot.2026.105404, with six authors. The original reference and year are retained as cited; reconcile the intended version before submission. | M73: Primary-source abstract or article and manuscript context; source reviewed 2026-09-24.
A74: 66 | B74: 2022 | C74: M. Shridhar, L. Manuelli, and D. Fox, “Perceiver-Actor: A multi-task transformer for robotic manipulation,” in Proc. Conf. Robot Learn. (CoRL), 2022, arXiv:2209.05451. | D74: PerAct encodes language goals and voxelized RGB-D observations with a Perceiver architecture. It learns discretized six-degree-of-freedom manipulation actions through behavior cloning. | E74: https://arxiv.org/abs/2209.05451 | F74: VLA/action policy | G74: Paper | H74: Pending | J74: arXiv:2209.05451 | K74: peract | M74: Previously primary-source-checked README catalogue and manuscript discussion; no new quantitative claims.
A75: 67 | B75: 2023 | C75: A. Goyal, J. Xu, Y. Guo, V. Blukis, Y.-W. Chao, and D. Fox, “RVT: Robotic view transformer for 3D object manipulation,” in Proc. Conf. Robot Learn. (CoRL), 2023, arXiv:2306.14896. | D75: RVT combines rendered views of a three-dimensional scene with language-goal embeddings in a transformer. The resulting representation supports spatially grounded manipulation from limited demonstrations. | E75: https://arxiv.org/abs/2306.14896 | F75: VLA/action policy | G75: Paper | H75: Pending | J75: arXiv:2306.14896 | K75: rvt | M75: Previously primary-source-checked README catalogue and manuscript discussion; no new quantitative claims.
A76: 68 | B76: 2024 | C76: A. Goyal, V. Blukis, J. Xu, Y. Guo, Y.-W. Chao, and D. Fox, “RVT-2: Learning precise manipulation from few demonstrations,” in Robotics: Science and Systems (RSS), 2024, arXiv:2406.08545. | D76: RVT-2 improves the architecture and execution of language-conditioned multi-view manipulation policies. It emphasizes precise control and efficient learning from few demonstrations. | E76: https://arxiv.org/abs/2406.08545 | F76: VLA/action policy | G76: Paper | H76: Pending | J76: arXiv:2406.08545 | K76: rvt2 | M76: Previously primary-source-checked README catalogue and manuscript discussion; no new quantitative claims.
A77: 69 | B77: 2023 | C77: T. Gervet, Z. Xian, N. Gkanatsios, and K. Fragkiadaki, “Act3D: 3D feature field transformers for multi-task robotic manipulation,” in Conference on Robot Learning (CoRL), 2023, arXiv:2306.17817. | D77: Act3D uses a hierarchical three-dimensional feature field with task-instruction conditioning to predict manipulation actions. Coarse-to-fine spatial sampling concentrates computation where precise action prediction is needed. | E77: https://arxiv.org/abs/2306.17817 | F77: VLA/action policy | G77: Paper | H77: Pending | J77: arXiv:2306.17817 | K77: act3d | M77: Previously primary-source-checked README catalogue and manuscript discussion; no new quantitative claims.
A78: 70 | B78: 2024 | C78: H. Zhen, X. Qiu, P. Chen, J. Yang, X. Yan, Y. Du, Y. Hong, and C. Gan, “3D-VLA: A 3D vision-language-action generative world model,” in Proc. Int. Conf. Mach. Learn. (ICML), 2024, arXiv:2403.09631. | D78: 3D-VLA combines three-dimensional vision-language representations with generation of future observations and robot actions. It connects spatial grounding with predictive policy learning for manipulation. | E78: https://arxiv.org/abs/2403.09631 | F78: World model/predictive system | G78: Paper | H78: Pending | J78: arXiv:2403.09631 | K78: threedvla | M78: Previously primary-source-checked README catalogue and manuscript discussion; no new quantitative claims.
A79: 71 | B79: 2025 | C79: D. Qu, H. Song, Q. Chen, Y. Yao, X. Ye, Y. Ding, Z. Wang, J. Gu, B. Zhao, D. Wang et al., “SpatialVLA: Exploring spatial representations for visual-language-action models,” in Proc. Robot.: Sci. Syst. (RSS), 2025, arXiv:2501.15830. | D79: SpatialVLA uses geometric visual representations and spatially structured action tokens. These representations connect scene geometry with language-conditioned manipulation commands. | E79: https://arxiv.org/abs/2501.15830 | F79: VLA/action policy | G79: Paper | H79: Pending | J79: arXiv:2501.15830 | K79: spatialvla | M79: Previously primary-source-checked README catalogue and manuscript discussion; no new quantitative claims.
A80: 72 | B80: 2025 | C80: Li et al., “PointVLA: Injecting the 3D world into vision-language-action models,” arXiv preprint, 2025, arXiv:2503.07511. | D80: PointVLA injects point-cloud information into pretrained VLA action modules through lightweight adaptation. It gives an existing policy access to three-dimensional geometry for manipulation. | E80: https://arxiv.org/abs/2503.07511 | F80: VLA/action policy | G80: Paper | H80: Pending | J80: arXiv:2503.07511 | K80: pointvla | M80: Previously primary-source-checked README catalogue and manuscript discussion; no new quantitative claims.
A81: 73 | B81: 2024 | C81: Jia et al., “Lift3D foundation policy: Lifting 2D large-scale pretrained models for robust 3D robotic manipulation,” arXiv preprint, 2024, arXiv:2411.18623. | D81: Lift3D adapts pretrained two-dimensional visual features into implicit and explicit three-dimensional manipulation representations. Its reported policy uses point clouds and robot state without language conditioning. | E81: https://arxiv.org/abs/2411.18623 | F81: Planning/control context | G81: Paper | H81: Pending | J81: arXiv:2411.18623 | K81: lift3d | M81: Previously primary-source-checked README catalogue and manuscript discussion; no new quantitative claims.
A82: 74 | B82: 2025 | C82: Yang et al., “FP3: A 3D foundation policy for robotic manipulation,” arXiv preprint, 2025, arXiv:2503.08950. | D82: FP3 pretrains a diffusion-transformer manipulation policy using point clouds, proprioception, and CLIP-encoded instructions. It adapts this language-conditioned three-dimensional policy to downstream tasks. | E82: https://arxiv.org/abs/2503.08950 | F82: VLA/action policy | G82: Paper | H82: Pending | J82: arXiv:2503.08950 | K82: fp3 | M82: Previously primary-source-checked README catalogue and manuscript discussion; no new quantitative claims.
A83: 75 | B83: 2025 | C83: Li et al., “BridgeVLA: Input-output alignment for efficient 3D manipulation learning,” arXiv preprint, 2025, arXiv:2506.07961. [Online]. Available: | D83: BridgeVLA projects three-dimensional observations into multiple image views and predicts spatial action heatmaps. This design aligns visual inputs with the spatial representation of control outputs. | E83: https://arxiv.org/abs/2506.07961 | F83: VLA/action policy | G83: Paper | H83: Pending | J83: arXiv:2506.07961 | K83: bridgevla | M83: Previously primary-source-checked README catalogue and manuscript discussion; no new quantitative claims.
A84: 76 | B84: 2025 | C84: Deng et al., “GraspVLA: A grasping foundation model pre-trained on billion-scale synthetic action data,” arXiv preprint, 2025, arXiv:2505.03233. | D84: GraspVLA combines autoregressive perception with flow-matching action generation for grasping. Its training integrates synthetic robot data with semantic pretraining to support generalizable grasp behavior. | E84: https://arxiv.org/abs/2505.03233 | F84: VLA/action policy | G84: Paper | H84: Pending | J84: arXiv:2505.03233 | K84: graspvla | M84: Previously primary-source-checked README catalogue and manuscript discussion; no new quantitative claims.
A85: 77 | B85: 2025 | C85: Sun et al., “GeoVLA: Empowering 3D representations in vision-language-action models,” arXiv preprint, 2025, arXiv:2508.09071. | D85: GeoVLA fuses image-language representations with point-cloud geometry in an action expert. This spatial interface supplies three-dimensional context for language-conditioned manipulation. | E85: https://arxiv.org/abs/2508.09071 | F85: VLA/action policy | G85: Paper | H85: Pending | J85: arXiv:2508.09071 | K85: geovla | M85: Previously primary-source-checked README catalogue and manuscript discussion; no new quantitative claims.
... A108: 100 | B108: 2025 | C108: NVIDIA GEAR Lab, “GR00T N1.5: An improved open foundation model for generalist humanoid robots,” NVIDIA Research, , 2025. | D108: GR00T N1.5 extends the GR00T humanoid policy family with changes to its architecture and training data. The official release describes future-latent representation alignment as a component of policy learning. | E108: https://research.nvidia.com/labs/gear/gr00t-n1_5/ | F108: Vendor technical release | G108: Technical release / software | H108: Pending | J108: https://research.nvidia.com/labs/gear/gr00t-n1_5/ | K108: grootn15 | M108: Source-checked VLA/action-policy README catalogue (2026-09-23) and surgical manuscript context; no new quantitative claim.
A109: 101 | B109: 2024 | C109: C.-L. Cheang, G. Chen, Y. Jing, T. Kong, H. Li, Y. Li, Y. Liu, H. Wu, J. Xu, Y. Yang et al., “GR-2: A generative video-language-action model with web-scale knowledge for robot manipulation,” arXiv preprint, 2024, arXiv:2410.06158. | D109: GR-2 combines large-scale video pretraining with joint video and action learning for robotic manipulation. Its predictive-policy formulation connects visual knowledge from web video to robot trajectories. | E109: https://arxiv.org/abs/2410.06158 | F109: VLA/action policy | G109: Paper | H109: Pending | J109: arXiv:2410.06158 | K109: gr2 | L109: Vendor-authored technical research paper, not reclassified as nonpaper simply because evidence is vendor-reported. | M109: Source-checked VLA/action-policy README catalogue (2026-09-23) and surgical manuscript context; no new quantitative claim.
A110: 102 | B110: 2025 | C110: Gemini Robotics Team, “Gemini Robotics 1.5: Pushing the frontier of generalist robots with advanced embodied reasoning, thinking, and motion transfer,” arXiv preprint, 2025, arXiv:2510.03342. | D110: Gemini Robotics 1.5 integrates embodied reasoning with action generation in a multi-embodiment policy. The developer report also describes transferring motion knowledge across robot configurations. | E110: https://arxiv.org/abs/2510.03342 | F110: VLA/action policy | G110: Paper | H110: Pending | J110: arXiv:2510.03342 | K110: gemini15 | L110: Vendor-authored technical research paper, not reclassified as nonpaper simply because evidence is vendor-reported. | M110: Source-checked VLA/action-policy README catalogue (2026-09-23) and surgical manuscript context; no new quantitative claim.
A111: 103 | B111: 2024 | C111: Chiang et al., “Mobility VLA: Multimodal instruction navigation with long-context VLMs and topological graphs,” arXiv preprint, 2024, arXiv:2407.07775. | D111: Mobility VLA combines long-context vision-language understanding with topological navigation. Its reported setting concerns multimodal instruction following for navigation, providing context for broader mobile-robot systems. | E111: https://arxiv.org/abs/2407.07775 | F111: Planning/control context | G111: Paper | H111: Pending | J111: arXiv:2407.07775 | K111: mobilityvla | M111: Source-checked VLA/action-policy README catalogue (2026-09-23) and surgical manuscript context; no new quantitative claim.
A112: 104 | B112: 2011 | C112: S. Ross, G. J. Gordon, and J. A. Bagnell, “A reduction of imitation learning and structured prediction to no-regret online learning,” in Proc. Int. Conf. Artif. Intell. Statist. (AISTATS), 2011. | D112: DAgger addresses imitation-learning distribution shift by iteratively collecting expert labels on states encountered by the learner. The paper connects this data-aggregation procedure to no-regret online learning and sequential prediction. | E112: https://proceedings.mlr.press/v15/ross11a/ross11a.pdf | F112: Methodology | G112: Paper | H112: Pending | J112: https://proceedings.mlr.press/v15/ross11a/ross11a.pdf | K112: dagger | M112: Primary-source abstract or official release checked online on 2026-09-24; manuscript context used to identify the cited role.
A113: 105 | B113: 2024 | C113: A. Khazatsky, K. Pertsch, S. Nair, A. Balakrishna, S. Dasari, S. Karamcheti, S. Nasiriany, M. K. Srirama, L. Y. Chen, K. Ellis et al., “DROID: A large-scale in-the-wild robot manipulation dataset,” arXiv preprint, 2024, arXiv:2403.12945. | D113: DROID provides diverse real-world robot manipulation demonstrations collected across environments. It supports research on policy learning and generalization from robot observations and actions. | E113: https://arxiv.org/abs/2403.12945 | F113: Dataset/benchmark | G113: Paper | H113: Pending | J113: arXiv:2403.12945 | K113: droid | M113: Supported by the surgical manuscript discussion and earlier primary-source review notes; qualitative scope retained without new performance claims.
A114: 106 | B114: 2025 | C114: NVIDIA, “Cosmos world foundation model platform for physical AI,” arXiv preprint, 2025, arXiv:2501.03575. | D114: Cosmos provides video tokenization and generative world foundation models for physical-AI development. Action conditioning and robot-control use depend on the particular model and its adaptation. | E114: https://arxiv.org/abs/2501.03575 | F114: World model/predictive system | G114: Paper | H114: Pending | J114: arXiv:2501.03575 | K114: cosmos | M114: Source-checked world-model README catalogue (2026-09-23) and surgical manuscript context; no new quantitative claim.
A115: 107 | B115: 2025 | C115: S. Motamed, L. Culp, K. Swersky, P. Jaini, and R. Geirhos, “Do generative video models understand physical laws?” in Proc. IEEE/CVF Int. Conf. Comput. Vis. (ICCV), 2025, arXiv:2501.09038. | D115: Physics-IQ evaluates physical prediction using paired real videos rather than visual plausibility alone. It supplies evidence about physical consistency in generative video models without directly measuring robot-control success. | E115: https://arxiv.org/abs/2501.09038 | F115: Dataset/benchmark | G115: Paper | H115: Pending | J115: arXiv:2501.09038 | K115: physicsiq | M115: Supported by the surgical manuscript discussion and earlier primary-source review notes; qualitative scope retained without new performance claims.
A116: 108 | B116: 2025 | C116: Li et al., “WorldModelBench: Judging video generation models as world models,” arXiv preprint, 2025, arXiv:2502.20694. | D116: WorldModelBench evaluates instruction-conditioned video generation against physical principles. It assesses properties of generated worlds rather than serving as a direct manipulation-policy success benchmark. | E116: https://arxiv.org/abs/2502.20694 | F116: Dataset/benchmark | G116: Paper | H116: Pending | J116: arXiv:2502.20694 | K116: wmbench | M116: Supported by the surgical manuscript discussion and earlier primary-source review notes; qualitative scope retained without new performance claims.
A117: 109 | B117: 2025 | C117: Z. Huang et al., “VBench-2.0: Advancing video generation benchmark suite for intrinsic faithfulness,” arXiv preprint, 2025, arXiv:2503.21755. | D117: VBench-2.0 evaluates generated video for human fidelity, controllability, creativity, physics, and commonsense. Its metrics target intrinsic faithfulness beyond surface visual plausibility. | E117: https://arxiv.org/abs/2503.21755 | F117: Dataset/benchmark | G117: Paper | H117: Pending | J117: arXiv:2503.21755 | K117: vbench2 | M117: Primary-source abstract or official release checked online on 2026-09-24; manuscript context used to identify the cited role.
A118: 110 | B118: 2024 | C118: X. Li, K. Hsu, J. Gu, K. Pertsch, O. Mees, H. R. Walke, C. Fu, I. Lunawat, I. Sieh, S. Kirmani et al., “Evaluating real-world robot manipulation policies in simulation,” arXiv preprint, 2024, arXiv:2405.05941. | D118: SimplerEnv constructs simulated evaluations intended to correspond to physical robot manipulation settings. It studies how closely policy performance in these simulations tracks real-world evaluation. | E118: https://arxiv.org/abs/2405.05941 | F118: Dataset/benchmark | G118: Paper | H118: Pending | J118: arXiv:2405.05941 | K118: simplerenv | M118: Supported by the surgical manuscript discussion and earlier primary-source review notes; qualitative scope retained without new performance claims.
A119: 111 | B119: 2026 | C119: R. Cui, Z. Zhang, J. Pang, H. Chi, J. Guo, S. Zhang, S. Xie, X. Jin, Y. Mu, J. Yang, G. Yao, X. Zhan, Y.-Q. Zhang, and H. Zhao, “LIBERO-Safety: A comprehensive benchmark for physical and semantic safety in vision-language-action models,” arXiv preprint, 2026, arXiv:2606.23686. | D119: LIBERO-Safety procedurally generates safety-critical manipulation scenarios and accompanying collision-free demonstrations. It evaluates physical and semantic safety properties of embodied policies under task constraints. | E119: https://arxiv.org/abs/2606.23686 | F119: Dataset/benchmark | G119: Paper | H119: Pending | J119: arXiv:2606.23686 | K119: safelibero | M119: Primary-source abstract or official release checked online on 2026-09-24; manuscript context used to identify the cited role.
A120: 112 | B120: 2023 | C120: A. Z. Ren, A. Dixit, A. Bodrova, S. Singh, S. Tu, N. Brown, P. Xu, L. Takayama, F. Xia, J. Varley et al., “Robots that ask for help: Uncertainty alignment for large language model planners,” in Proc. Conf. Robot Learn. (CoRL), 2023, arXiv:2307.01928. | D120: KnowNo uses conformal prediction to calibrate uncertainty in language-model planning. The framework uses this uncertainty to determine when a robot should request human assistance. | E120: https://arxiv.org/abs/2307.01928 | F120: Planning/control context | G120: Paper | H120: Pending | J120: arXiv:2307.01928 | K120: knowno | M120: Source-checked VLA/action-policy README catalogue (2026-09-23) and surgical manuscript context; no new quantitative claim.
A121: 113 | B121: 2019 | C121: A. D. Ames, S. Coogan, M. Egerstedt, G. Notomista, K. Sreenath, and P. Tabuada, “Control barrier functions: Theory and applications,” in Proc. Eur. Control Conf. (ECC), 2019. | D121: This overview explains how control barrier functions can verify and enforce safety properties of dynamical systems. It connects the theory to optimization-based safety-critical controllers and robotic applications. | E121: https://arxiv.org/abs/1903.11199 | F121: Planning/control context | G121: Paper | H121: Pending | J121: arXiv:1903.11199 | K121: cbf | L121: Foundational control survey/tutorial, not a review-methodology reporting guideline. | M121: Primary-source abstract or official release checked online on 2026-09-24; manuscript context used to identify the cited role.
A122: 114 | B122: 2017 | C122: S. Bansal, M. Chen, S. Herbert, and C. J. Tomlin, “Hamilton–Jacobi reachability: A brief overview and recent advances,” in Proc. IEEE Conf. Decis. Control (CDC), 2017. | D122: This tutorial reviews Hamilton-Jacobi reachability for analyzing safety and performance of nonlinear dynamical systems with bounded disturbances. It also discusses numerical tools and approaches to the computational difficulty of high-dimensional systems. | E122: https://arxiv.org/abs/1709.07523 | F122: Planning/control context | G122: Paper | H122: Pending | J122: arXiv:1709.07523 | K122: hjreach | L122: Foundational control survey/tutorial, not a review-methodology reporting guideline. | M122: Primary-source abstract or official release checked online on 2026-09-24; manuscript context used to identify the cited role.
A123: 115 | B123: 2018 | C123: D. Ha and J. Schmidhuber, “World models,” arXiv preprint, 2018, arXiv:1803.10122. | D123: World Models combines a variational image encoder, recurrent latent dynamics, and a compact controller. It demonstrates learning behavior within a learned environment in simulated control tasks. | E123: https://arxiv.org/abs/1803.10122 | F123: World model/predictive system | G123: Paper | H123: Pending | J123: arXiv:1803.10122 | K123: worldmodels2018 | M123: Source-checked world-model README catalogue (2026-09-23) and surgical manuscript context; no new quantitative claim.
A124: 116 | B124: 2019 | C124: D. Hafner, T. Lillicrap, I. Fischer, R. Villegas, D. Ha, H. Lee, and J. Davidson, “Learning latent dynamics for planning from pixels,” in Proc. Int. Conf. Mach. Learn. (ICML), 2019, arXiv:1811.04551. [Online]. Available: | D124: PlaNet learns action-conditioned recurrent latent dynamics from images. It uses model-predictive control to select action sequences by evaluating imagined futures. | E124: https://arxiv.org/abs/1811.04551 | F124: World model/predictive system | G124: Paper | H124: Pending | J124: arXiv:1811.04551 | K124: planet | M124: Source-checked world-model README catalogue (2026-09-23) and surgical manuscript context; no new quantitative claim.
A125: 117 | B125: 2025 | C125: D. Hafner, J. Pasukonis, J. Ba, and T. Lillicrap, “Mastering diverse control tasks through world models,” Nature, vol. 640, pp. 647–653, 2025. | D125: DreamerV3 learns policies and value functions through trajectories imagined in a latent dynamics model. Its training design aims to support varied control domains with a common configuration. | E125: https://arxiv.org/abs/2301.04104 | F125: World model/predictive system | G125: Paper | H125: Pending | J125: arXiv:2301.04104 | K125: dreamerv3 | M125: Source-checked world-model README catalogue (2026-09-23) and surgical manuscript context; no new quantitative claim.
A126: 118 | B126: 2020 | C126: J. Schrittwieser, I. Antonoglou, T. Hubert, K. Simonyan, L. Sifre, S. Schmitt, A. Guez, E. Lockhart, D. Hassabis, T. Graepel et al., “Mastering Atari, Go, chess and shogi by planning with a learned model,” Nature, vol. 588, pp. 604–609, 2020. | D126: MuZero learns latent transitions that predict rewards, values, and action priors for tree search. Its cited demonstrations concern games, with planning-relevant prediction that does not require observation reconstruction. | E126: https://arxiv.org/abs/1911.08265 | F126: World model/predictive system | G126: Paper | H126: Pending | J126: arXiv:1911.08265 | K126: muzero | M126: Source-checked world-model README catalogue (2026-09-23) and surgical manuscript context; no new quantitative claim.
A127: 119 | B127: 2024 | C127: N. Hansen, H. Su, and X. Wang, “TD-MPC2: Scalable, robust world models for continuous control,” in Proc. Int. Conf. Learn. Representations (ICLR), 2024, arXiv:2310.16828. | D127: TD-MPC2 learns task-conditioned latent dynamics and value functions for continuous control. These predictions support model-predictive control across multiple tasks. | E127: https://arxiv.org/abs/2310.16828 | F127: World model/predictive system | G127: Paper | H127: Pending | J127: arXiv:2310.16828 | K127: tdmpc2 | M127: Source-checked world-model README catalogue (2026-09-23) and surgical manuscript context; no new quantitative claim.
A128: 120 | B128: 2023 | C128: Y. Du, S. Yang, B. Dai, H. Dai, O. Nachum, J. B. Tenenbaum, D. Schuurmans, and P. Abbeel, “Learning universal policies via text-guided video generation,” in Adv. Neural Inf. Process. Syst. (NeurIPS), 2023. | D128: UniPi generates a language-conditioned video plan and recovers executable actions through inverse dynamics. The generated plan is a visual action proposal rather than a forward prediction conditioned on supplied candidate robot actions. | E128: https://arxiv.org/abs/2302.00111 | F128: World model/predictive system | G128: Paper | H128: Pending | J128: arXiv:2302.00111 | K128: unipi | M128: Source-checked world-model README catalogue (2026-09-23) and surgical manuscript context; no new quantitative claim.
A129: 121 | B129: 2024 | C129: S. Yang, Y. Du, K. Ghasemipour, J. Tompson, L. Kaelbling, D. Schuurmans, and P. Abbeel, “Learning interactive real-world simulators,” in Proc. Int. Conf. Learn. Representations (ICLR), 2024. | D129: UniSim learns an interactive video simulator that responds to high-level instructions or low-level controls. It supports policy learning and evaluation through generated environment interactions. | E129: https://arxiv.org/abs/2310.06114 | F129: World model/predictive system | G129: Paper | H129: Pending | J129: arXiv:2310.06114 | K129: unisim | M129: Source-checked world-model README catalogue (2026-09-23) and surgical manuscript context; no new quantitative claim.
A130: 122 | B130: 2024 | C130: P.-C. Ko, J. Mao, Y. Du, S.-H. Sun, and J. B. Tenenbaum, “Learning to act from actionless videos through dense correspondences,” in International Conference on Learning Representations (ICLR), 2024, arXiv:2310.08576. | D130: AVDC generates task-directed videos and uses dense correspondences between frames to infer control actions. This connects action-free video demonstrations to robot execution. | E130: https://arxiv.org/abs/2310.08576 | F130: World model/predictive system | G130: Paper | H130: Pending | J130: arXiv:2310.08576 | K130: avdc | M130: Source-checked world-model README catalogue (2026-09-23) and surgical manuscript context; no new quantitative claim.
A131: 123 | B131: 2024 | C131: K. Black, M. Nakamoto, P. Atreya, H. Walke, C. Finn, A. Kumar, and S. Levine, “Zero-shot robotic manipulation with pretrained image-editing diffusion models,” in International Conference on Learning Representations (ICLR), 2024, arXiv:2310.10639. | D131: SuSIE adapts an image-editing diffusion model to propose visual subgoals from an observation and language instruction. A goal-conditioned controller executes the proposed subgoals. | E131: https://arxiv.org/abs/2310.10639 | F131: World model/predictive system | G131: Paper | H131: Pending | J131: arXiv:2310.10639 | K131: susie | M131: Source-checked world-model README catalogue (2026-09-23) and surgical manuscript context; no new quantitative claim.
A132: 124 | B132: 2024 | C132: Y. Du, S. Yang, P. Florence, F. Xia, A. Wahid, B. Ichter, P. Sermanet, T. Yu, P. Abbeel, J. B. Tenenbaum, L. Kaelbling, A. Zeng, and J. Tompson, “Video language planning,” in International Conference on Learning Representations (ICLR), 2024, arXiv:2310.10625. | D132: Video Language Planning searches over language proposals and generated video continuations using vision-language policies and value functions. A goal-conditioned policy executes the resulting visual plan. | E132: https://arxiv.org/abs/2310.10625 | F132: World model/predictive system | G132: Paper | H132: Pending | J132: arXiv:2310.10625 | K132: vlp | M132: Source-checked world-model README catalogue (2026-09-23) and surgical manuscript context; no new quantitative claim.
A133: 125 | B133: 2024 | C133: J. Wu, S. Yin, N. Feng, X. He, D. Li, J. Hao, and M. Long, “iVideoGPT: Interactive VideoGPTs are scalable world models,” in Advances in Neural Information Processing Systems (NeurIPS), 2024, arXiv:2405.15223. [Online]. Available: | D133: iVideoGPT autoregressively models tokenized observations, actions, and rewards. Its learned dynamics support interactive video prediction, visual planning, and model-based reinforcement learning. | E133: https://arxiv.org/abs/2405.15223 | F133: World model/predictive system | G133: Paper | H133: Pending | J133: arXiv:2405.15223 | K133: ivideogpt | M133: Source-checked world-model README catalogue (2026-09-23) and surgical manuscript context; no new quantitative claim.
A134: 126 | B134: 2024 | C134: H. Wu, Y. Jing, C. Cheang, G. Chen, J. Xu, X. Li, M. Liu, H. Li, and T. Kong, “Unleashing large-scale video generative pre-training for visual robot manipulation,” in Proc. Int. Conf. Learn. Representations (ICLR), 2024, arXiv:2312.13139. | D134: GR-1 predicts future images and robot actions from language, visual history, and robot state after video pretraining. This shared predictive-policy training is distinct from searching over supplied candidate actions during deployment. | E134: https://arxiv.org/abs/2312.13139 | F134: VLA/action policy | G134: Paper | H134: Pending | J134: arXiv:2312.13139 | K134: gr1 | M134: Source-checked world-model README catalogue (2026-09-23) and surgical manuscript context; no new quantitative claim.
... A141: 133 | B141: 2026 | C141: J. Chen, K. Wang, K. Chen, S. Chen, F. Gao, W. Tang, Z. Li, W. Liu, Z. Yao, B. Li, Y. Xu, and C. Yu, “LaWAM: Latent world action models for efficient dynamics-aware robot policies,” arXiv preprint, 2026, arXiv:2606.15768. | D141: LaWAM predicts latent visual subgoals and conditions robot-action generation on them. It incorporates predictive information into a policy without requiring dense future-image generation. | E141: https://arxiv.org/abs/2606.15768 | F141: World model/predictive system | G141: Paper | H141: Pending | J141: arXiv:2606.15768 | K141: lawam | M141: Source-checked world-model README catalogue (2026-09-23) and surgical manuscript context; no new quantitative claim.
A142: 134 | B142: 2026 | C142: J. Sun, W. Zhang, Z. Qi, S. Ren, Z. Liu, H. Zhu, G. Sun, X. Jin, and Z. Chen, “VLA-JEPA: Enhancing vision-language-action model with latent world model,” arXiv preprint, 2026, arXiv:2602.10098. | D142: VLA-JEPA pretrains a policy backbone to predict future latent states from current observations. It subsequently adapts an action head, with future frames serving as training targets rather than inputs to the prediction pathway. | E142: https://arxiv.org/abs/2602.10098 | F142: World model/predictive system | G142: Paper | H142: Pending | J142: arXiv:2602.10098 | K142: jepavla | L142: Citation key aliases VLA-JEPA, not a separate JEPA-VLA report. | M142: Source-checked world-model README catalogue (2026-09-23) and surgical manuscript context; no new quantitative claim.
A143: 135 | B143: 2025 | C143: H. Zhen, Q. Sun, H. Zhang, J. Li, S. Zhou, Y. Du, and C. Gan, “TesserAct: Learning 4D embodied world models,” arXiv preprint, 2025, arXiv:2504.20995. | D143: TesserAct predicts RGB, depth, and surface-normal video to represent how three-dimensional scenes evolve. Its multimodal predictions also support learning inverse dynamics for embodied tasks. | E143: https://arxiv.org/abs/2504.20995 | F143: World model/predictive system | G143: Paper | H143: Pending | J143: arXiv:2504.20995 | K143: tesseract | M143: Source-checked world-model README catalogue (2026-09-23) and surgical manuscript context; no new quantitative claim.
A144: 136 | B144: 2025 | C144: G. Lu, B. Jia, P. Li, Y. Chen, Z. Wang, Y. Tang, and S. Huang, “GWM: Towards scalable gaussian world models for robotic manipulation,” in IEEE/CVF International Conference on Computer Vision (ICCV), pp. 9263–9274, 2025. | D144: GWM models action-conditioned manipulation dynamics using Gaussian scene representations. The paper studies this representation for predictive pretraining and learned simulation. | E144: https://arxiv.org/abs/2508.17600 | F144: World model/predictive system | G144: Paper | H144: Pending | J144: arXiv:2508.17600 | K144: gaussianworld | M144: Source-checked world-model README catalogue (2026-09-23) and surgical manuscript context; no new quantitative claim.
A145: 137 | B145: 2024 | C145: G. Lu, S. Zhang, Z. Wang, C. Liu, J. Lu, and Y. Tang, “ManiGaussian: Dynamic gaussian splatting for multi-task robotic manipulation,” in European Conference on Computer Vision (ECCV), 2024, arXiv:2403.08321. [Online]. Available: | D145: ManiGaussian uses dynamic Gaussian representations and future-scene reconstruction as predictive supervision for manipulation. Its language-conditioned policy evaluation is conducted in RLBench simulation. | E145: https://arxiv.org/abs/2403.08321 | F145: World model/predictive system | G145: Paper | H145: Pending | J145: arXiv:2403.08321 | K145: manigaussian | M145: Source-checked world-model README catalogue (2026-09-23) and surgical manuscript context; no new quantitative claim.
A146: 138 | B146: 2024 | C146: T. Zhang, H.-X. Yu, R. Wu, B. Y. Feng, C. Zheng, N. Snavely, J. Wu, and W. T. Freeman, “PhysDreamer: Physics-based interaction with 3D objects via video generation,” in European Conference on Computer Vision (ECCV), 2024, arXiv:2404.13026. | D146: PhysDreamer distills motion information from video generation into physical material estimates and interactive three-dimensional dynamics. Its object-response demonstrations provide context for physical prediction rather than direct evidence of robot task success. | E146: https://arxiv.org/abs/2404.13026 | F146: World model/predictive system | G146: Paper | H146: Pending | J146: arXiv:2404.13026 | K146: physdreamer | M146: Source-checked world-model README catalogue (2026-09-23) and surgical manuscript context; no new quantitative claim.
A147: 139 | B147: 2026 | C147: S. Wu et al., “Tactile-W AM: Touch-aware world action model with tactile asymmetric attention,” arXiv preprint, 2026, arXiv:2606.26663. | D147: Tactile-WAM jointly models visual, tactile, and action information with tactile asymmetric attention. It directs contact information toward action prediction while limiting interference with video generation. | E147: https://arxiv.org/abs/2606.26663 | F147: World model/predictive system | G147: Paper | H147: Pending | J147: arXiv:2606.26663 | K147: dreamtac | L147: Citation key is an alias for Tactile-WAM; not an additional DreamTac report. Recovered title has a spacing error. | M147: Source-checked world-model README catalogue (2026-09-23) and surgical manuscript context; no new quantitative claim. The legacy bib_key dreamtac resolves to Tactile-WAM, not a separate DreamTac model.
A148: 140 | B148: 2026 | C148: J. Zhou, F. Hong, Y. Li, Y. Zhao, Y. Cen, Z. Liu, J. Huang, Z. Chen, R. Zhang, W. Zhu et al., “TouchWorld: A predictive and reactive tactile foundation model for dexterous manipulation,” arXiv preprint, 2026, arXiv:2607.07287. | D148: TouchWorld combines predicted tactile subgoals and visuomotor action chunks with a faster tactile and proprioceptive correction policy. This joins predictive and reactive control for contact-rich dexterous manipulation. | E148: https://arxiv.org/abs/2607.07287 | F148: World model/predictive system | G148: Paper | H148: Pending | J148: arXiv:2607.07287 | K148: touchworld | M148: Source-checked world-model README catalogue (2026-09-23) and surgical manuscript context; no new quantitative claim.
