Workbook

Sheet README
A1: Verified-only CSV audit, figures, and source data
A3: Metric | B3: Value
A4: Submitted CSV rows audited | B4: =SUM('Audit Summary'!B2:B4) -> 147
A5: Input rows retained or corrected | B5: =SUM('Audit Summary'!C2:C4) -> 6
A6: Input rows excluded | B6: =SUM('Audit Summary'!D2:D4) -> 141
A7: Verified data-scale output records | B7: =COUNTA('Verified Data Scale'!A2:A8) -> 7
A8: Verified real-robot task records | B8: =COUNTA('World-Gymnast'!A2:A5) -> 4
A9: Submitted columns assessed | B9: =COUNTA('Column Decisions'!A2:A52) -> 51
A11: Decision | B11: Rationale
A12: Exclude corpus_master.csv | B12: All 106 rows are manuscript-derived and lack row-level primary-source URLs, locators, and field-level verification.
A13: Exclude evidence_edges.csv | B13: All 34 edges are manuscript-derived; mixed coding semantics and missing source locators prevent publication-authentic use.
A14: Remove RT-1 hours | B14: The submitted value is an episode-duration assumption, not a source-reported hour measurement.
A15: Correct bound semantics | B15: Cosmos is approximate; V-JEPA 2 and pi_0 are lower bounds; V-JEPA 2-AC is an upper bound.
A16: Correct Dreamer 4 | B16: Use the exact 2,541-hour VPT pool and represent the 100-hour paired-action condition separately.
A17: Retain two figure families | B17: Keep the qualified scale plot and the source-reported World-Gymnast real-robot comparison; omit unsupported ranking and evidence-count plots.
A19: Interpretation warning
A20: The scale values describe different measurement scopes (raw collections, pretraining pools, released robot data, and experimental subsets). They must not be interpreted as a sample-efficiency leaderboard. Only the fields present in the verified sheets are approved for reuse.

Sheet Audit Summary
A1: input_file | B1: input_rows | C1: retained_or_corrected_input_rows | D1: excluded_input_rows | E1: verified_output_rows | F1: audit_conclusion | G1: retention_rate (derived) | H1: reconciliation
A2: corpus_master.csv | B2: 106 | C2: 0 | D2: 106 | E2: 0 | F2: No rows retained because field-level primary-source traceability is absent. | G2: =IF(B2=0,0,C2/B2) -> 0 | H2: =IF(B2=C2+D2,"PASS","CHECK") -> PASS
A3: evidence_edges.csv | B3: 34 | C3: 0 | D3: 34 | E3: 0 | F3: No rows retained because field-level primary-source traceability is absent. | G3: =IF(B3=0,0,C3/B3) -> 0 | H3: =IF(B3=C3+D3,"PASS","CHECK") -> PASS
A4: data_scaling.csv | B4: 7 | C4: 6 | D4: 1 | E4: 7 | F4: Only primary-source-verified scale claims retained; one row split into two claims. | G4: =IF(B4=0,0,C4/B4) -> 0.85714286 | H4: =IF(B4=C4+D4,"PASS","CHECK") -> PASS

Sheet Verified Data Scale
A1: record_id | B1: system | C1: measurement_scope | D1: data_role | E1: reported_hours | F1: bound_type | G1: source_version | H1: source_locator | I1: source_url | J1: verification_date | K1: verification_status | L1: log10_hours (derived)
A2: cosmos_raw | B2: Cosmos WFM | C2: raw candidate video collection | D2: raw_video_collection | E2: 20000000 | F2: approximate | G2: arXiv:2501.03575v3 | H2: Sections 1 and 3.1 | I2: https://arxiv.org/html/2501.03575 | J2: 2026-08-26 | K2: verified_primary_source | L2: =LOG10(E2) -> 7.30103
A3: vjepa2_pretrain | B3: V-JEPA 2 | C3: internet-video pretraining pool | D3: internet_video_pretraining | E3: 1000000 | F3: lower_bound | G3: arXiv:2506.09985v1 | H3: Abstract and Section 2 | I3: https://arxiv.org/html/2506.09985 | J3: 2026-08-26 | K3: verified_primary_source | L3: =LOG10(E3) -> 6
A4: pi0_pretrain | B4: pi_0 | C4: robot-data pretraining mixture | D4: robot_demonstration_pretraining | E4: 10000 | F4: lower_bound | G4: arXiv:2410.24164v4 | H4: Introduction and conclusion | I4: https://arxiv.org/html/2410.24164v4 | J4: 2026-08-26 | K4: verified_primary_source | L4: =LOG10(E4) -> 4
A5: dreamer4_video | B5: Dreamer 4 | C5: VPT gameplay-video pool | D5: gameplay_video_pool | E5: 2541 | F5: exact | G5: arXiv:2509.24527v1 | H5: Section 4.3 and Appendix: Minecraft VPT | I5: https://arxiv.org/pdf/2509.24527 | J5: 2026-08-26 | K5: verified_primary_source | L5: =LOG10(E5) -> 3.4050047
A6: droid_full | B6: DROID | C6: full robot-interaction dataset | D6: robot_interaction_dataset | E6: 350 | F6: exact | G6: arXiv:2403.12945v2 | H6: Abstract | I6: https://arxiv.org/html/2403.12945v2 | J6: 2026-08-26 | K6: verified_primary_source | L6: =LOG10(E6) -> 2.544068
A7: dreamer4_actions | B7: Dreamer 4 | C7: paired-action ablation subset | D7: action_conditioning_ablation | E7: 100 | F7: exact | G7: arXiv:2509.24527v1 | H7: Section 4.3 and Figure 7 | I7: https://arxiv.org/pdf/2509.24527 | J7: 2026-08-26 | K7: verified_primary_source | L7: =LOG10(E7) -> 2
A8: vjepa2_ac | B8: V-JEPA 2-AC | C8: filtered robot-video subset with end-effector states and derived actions | D8: robot_video_with_derived_actions | E8: 62 | F8: upper_bound | G8: arXiv:2506.09985v1 | H8: Abstract and Section 3.1 | I8: https://arxiv.org/html/2506.09985 | J8: 2026-08-26 | K8: verified_primary_source | L8: =LOG10(E8) -> 1.7923917

Sheet World-Gymnast
A1: task | B1: baseline_system | C1: baseline_mean_pct | D1: baseline_se_pct | E1: proposed_system | F1: proposed_mean_pct | G1: proposed_se_pct | H1: trials_per_evaluation | I1: repeated_evaluations | J1: evaluation_protocol | K1: source_version | L1: source_locator | M1: source_url | N1: verification_date | O1: verification_status | P1: delta_pp (derived) | Q1: direction (derived)
A2: Open the drawer | B2: SIMPLER | C2: 34 | D2: 7 | E2: World-Gymnast | F2: 58 | G2: 4 | H2: 10 | I2: 5 | J2: AutoEval real-robot evaluation | K2: arXiv:2602.02454v1 | L2: Section 4.1 and Table 1 | M2: https://arxiv.org/html/2602.02454v1 | N2: 2026-08-26 | O2: verified_primary_source | P2: =F2-C2 -> 24 | Q2: =IF(P2>0,"favors World-Gymnast",IF(P2<0,"favors SIMPLER","tie")) -> favors World-Gymnast
A3: Close the drawer | B3: SIMPLER | C3: 74 | D3: 5 | E3: World-Gymnast | F3: 62 | G3: 6 | H3: 10 | I3: 5 | J3: AutoEval real-robot evaluation | K3: arXiv:2602.02454v1 | L3: Section 4.1 and Table 1 | M3: https://arxiv.org/html/2602.02454v1 | N3: 2026-08-26 | O3: verified_primary_source | P3: =F3-C3 -> -12 | Q3: =IF(P3>0,"favors World-Gymnast",IF(P3<0,"favors SIMPLER","tie")) -> favors SIMPLER
A4: Put the eggplant into the blue sink | B4: SIMPLER | C4: 32 | D4: 10 | E4: World-Gymnast | F4: 72 | G4: 10 | H4: 10 | I4: 5 | J4: AutoEval real-robot evaluation | K4: arXiv:2602.02454v1 | L4: Section 4.1 and Table 1 | M4: https://arxiv.org/html/2602.02454v1 | N4: 2026-08-26 | O4: verified_primary_source | P4: =F4-C4 -> 40 | Q4: =IF(P4>0,"favors World-Gymnast",IF(P4<0,"favors SIMPLER","tie")) -> favors World-Gymnast
A5: Put the eggplant into the yellow basket | B5: SIMPLER | C5: 40 | D5: 10 | E5: World-Gymnast | F5: 78 | G5: 2 | H5: 10 | I5: 5 | J5: AutoEval real-robot evaluation | K5: arXiv:2602.02454v1 | L5: Section 4.1 and Table 1 | M5: https://arxiv.org/html/2602.02454v1 | N5: 2026-08-26 | O5: verified_primary_source | P5: =F5-C5 -> 38 | Q5: =IF(P5>0,"favors World-Gymnast",IF(P5<0,"favors SIMPLER","tie")) -> favors World-Gymnast

Sheet Verified Sources
A1: source_id | B1: system_or_dataset | C1: title | D1: source_version_date | E1: source_version | F1: source_url | G1: verification_date | H1: verification_status
A2: cosmos | B2: Cosmos WFM | C2: Cosmos World Foundation Model Platform for Physical AI | D2: 2025-07-09 | E2: arXiv:2501.03575v3 | F2: https://arxiv.org/html/2501.03575 | G2: 2026-08-26 | H2: verified_primary_source
A3: vjepa2 | B3: V-JEPA 2 / V-JEPA 2-AC | C3: V-JEPA 2: Self-Supervised Video Models Enable Understanding, Prediction and Planning | D3: 2025-06-11 | E3: arXiv:2506.09985v1 | F3: https://arxiv.org/html/2506.09985 | G3: 2026-08-26 | H3: verified_primary_source
A4: pi0 | B4: pi_0 | C4: pi_0: A Vision-Language-Action Flow Model for General Robot Control | D4: 2026-01-08 | E4: arXiv:2410.24164v4 | F4: https://arxiv.org/html/2410.24164v4 | G4: 2026-08-26 | H4: verified_primary_source
A5: dreamer4 | B5: Dreamer 4 | C5: Training Agents Inside of Scalable World Models | D5: 2025-09-29 | E5: arXiv:2509.24527v1 | F5: https://arxiv.org/pdf/2509.24527 | G5: 2026-08-26 | H5: verified_primary_source
A6: droid | B6: DROID | C6: DROID: A Large-Scale In-The-Wild Robot Manipulation Dataset | D6: 2025-04-22 | E6: arXiv:2403.12945v2 | F6: https://arxiv.org/html/2403.12945v2 | G6: 2026-08-26 | H6: verified_primary_source
A7: world_gymnast | B7: World-Gymnast | C7: World-Gymnast: Training Robots with Reinforcement Learning in a World Model | D7: 2026-02-02 | E7: arXiv:2602.02454v1 | F7: https://arxiv.org/html/2602.02454v1 | G7: 2026-08-26 | H7: verified_primary_source

Sheet Source Verification
A1: claim_id | B1: claim_type | C1: submitted_representation | D1: verified_representation | E1: decision | F1: source_locator | G1: source_url | H1: verification_date
A2: cosmos_raw | B2: data scale | C2: 20M presented without a bound | D2: approximately 20M hours | E2: qualifier_corrected | F2: Sections 1 and 3.1 | G2: https://arxiv.org/html/2501.03575 | H2: 2026-08-26
A3: vjepa2_pretrain | B3: data scale | C3: 1M presented as exact | D3: over 1M hours | E3: bound_corrected | F3: Abstract and Section 2 | G3: https://arxiv.org/html/2506.09985 | H3: 2026-08-26
A4: pi0_pretrain | B4: data scale | C4: 10k presented as exact | D4: over 10,000 hours | E4: bound_corrected | F4: Introduction and conclusion | G4: https://arxiv.org/html/2410.24164v4 | H4: 2026-08-26
A5: dreamer4_video | B5: data scale | C5: rounded gameplay-video pool | D5: 2,541 hours | E5: value_corrected | F5: Section 4.3 and Appendix: Minecraft VPT | G5: https://arxiv.org/pdf/2509.24527 | H5: 2026-08-26
A6: dreamer4_actions | B6: data scale | C6: paired-action quantity embedded in a note | D6: 100-hour paired-action condition | E6: claim_split | F6: Section 4.3 and Figure 7 | G6: https://arxiv.org/pdf/2509.24527 | H6: 2026-08-26
A7: droid_full | B7: data scale | C7: 350 hours | D7: 350 hours | E7: retained | F7: Abstract | G7: https://arxiv.org/html/2403.12945v2 | H7: 2026-08-26
A8: vjepa2_ac | B8: data scale | C8: 62 presented as exact | D8: less than 62 hours with end-effector states and derived actions | E8: bound_and_role_corrected | F8: Abstract and Section 3.1 | G8: https://arxiv.org/html/2506.09985 | H8: 2026-08-26
A9: rt1_estimate | B9: data scale | C9: episode-to-hour author estimate | D9: removed | E9: excluded_not_primary_measurement | F9: No reported-hour locator | G9: https://arxiv.org/abs/2212.06817 | H9: 2026-08-26
A10: world_gymnast_open_the_drawer | B10: real-robot success comparison | C10: prior verified extraction | D10: SIMPLER 34±7%; World-Gymnast 58±4% | E10: retained | F10: Section 4.1 and Table 1 | G10: https://arxiv.org/html/2602.02454v1 | H10: 2026-08-26
A11: world_gymnast_close_the_drawer | B11: real-robot success comparison | C11: prior verified extraction | D11: SIMPLER 74±5%; World-Gymnast 62±6% | E11: retained | F11: Section 4.1 and Table 1 | G11: https://arxiv.org/html/2602.02454v1 | H11: 2026-08-26
A12: world_gymnast_put_the_eggplant_into_the_blue_sink | B12: real-robot success comparison | C12: prior verified extraction | D12: SIMPLER 32±10%; World-Gymnast 72±10% | E12: retained | F12: Section 4.1 and Table 1 | G12: https://arxiv.org/html/2602.02454v1 | H12: 2026-08-26
A13: world_gymnast_put_the_eggplant_into_the_yellow_basket | B13: real-robot success comparison | C13: prior verified extraction | D13: SIMPLER 40±10%; World-Gymnast 78±2% | E13: retained | F13: Section 4.1 and Table 1 | G13: https://arxiv.org/html/2602.02454v1 | H13: 2026-08-26

Sheet Record Decisions
A1: input_file | B1: input_row_id | C1: decision | D1: retained_output_id | E1: reason
A2: corpus_master.csv | B2: rt1 | C2: excluded_unverified_record | E2: Record is manuscript-derived and lacks record-level primary-source URL, locator, and field-level verification.
A3: corpus_master.csv | B3: rt2 | C3: excluded_unverified_record | E3: Record is manuscript-derived and lacks record-level primary-source URL, locator, and field-level verification.
A4: corpus_master.csv | B4: oxe | C4: excluded_unverified_record | E4: Record is manuscript-derived and lacks record-level primary-source URL, locator, and field-level verification.
A5: corpus_master.csv | B5: openvla | C5: excluded_unverified_record | E5: Record is manuscript-derived and lacks record-level primary-source URL, locator, and field-level verification.
A6: corpus_master.csv | B6: fast | C6: excluded_unverified_record | E6: Record is manuscript-derived and lacks record-level primary-source URL, locator, and field-level verification.
A7: corpus_master.csv | B7: openvlaoft | C7: excluded_unverified_record | E7: Record is manuscript-derived and lacks record-level primary-source URL, locator, and field-level verification.
A8: corpus_master.csv | B8: octo | C8: excluded_unverified_record | E8: Record is manuscript-derived and lacks record-level primary-source URL, locator, and field-level verification.
A9: corpus_master.csv | B9: pi0 | C9: excluded_unverified_record | E9: Record is manuscript-derived and lacks record-level primary-source URL, locator, and field-level verification.
A10: corpus_master.csv | B10: rdt1b | C10: excluded_unverified_record | E10: Record is manuscript-derived and lacks record-level primary-source URL, locator, and field-level verification.
A11: corpus_master.csv | B11: groot | C11: excluded_unverified_record | E11: Record is manuscript-derived and lacks record-level primary-source URL, locator, and field-level verification.
A12: corpus_master.csv | B12: pi05 | C12: excluded_unverified_record | E12: Record is manuscript-derived and lacks record-level primary-source URL, locator, and field-level verification.
A13: corpus_master.csv | B13: gr2 | C13: excluded_unverified_record | E13: Record is manuscript-derived and lacks record-level primary-source URL, locator, and field-level verification.
... A141: evidence_edges.csv | B141: E034 | C141: excluded_unverified_edge | E141: Edge is manuscript-derived; source locator, independent verification, and normalized evidence semantics are absent.
A142: data_scaling.csv | B142: cosmos::Cosmos WFM | C142: retained_with_qualifier | D142: cosmos_raw | E142: Primary paper reports about 20M hours; encoded as approximate raw collection scale.
A143: data_scaling.csv | B143: vjepa2::V-JEPA 2 | C143: retained_with_qualifier | D143: vjepa2_pretrain | E143: Primary paper reports over 1M hours; encoded as a lower bound.
A144: data_scaling.csv | B144: pi0::pi_0 | C144: retained_with_qualifier | D144: pi0_pretrain | E144: Primary paper reports over 10,000 hours; encoded as a lower bound.
A145: data_scaling.csv | B145: dreamer4::Dreamer 4 | C145: corrected_and_split | D145: dreamer4_video;dreamer4_actions | E145: Video pool corrected to 2,541 hours; 100-hour paired-action condition represented separately.
A146: data_scaling.csv | B146: rt1::RT-1 | C146: excluded_author_estimate | E146: The hour value is an episode-duration conversion, not a primary-source-reported measurement.
A147: data_scaling.csv | B147: droid::DROID | C147: retained | D147: droid_full | E147: Primary paper reports 350 hours of interaction data.
A148: data_scaling.csv | B148: vjepa2::V-JEPA 2-AC | C148: retained_with_qualifier | D148: vjepa2_ac | E148: Primary paper reports less than 62 hours; encoded as an upper bound.

Sheet Column Decisions
A1: input_file | B1: input_column | C1: decision | D1: reason
A2: corpus_master.csv | B2: bib_key | C2: audit_identifier_only | D2: Retained only in the exclusion log, not as a scientific field.
A3: corpus_master.csv | B3: system_name | C3: excluded | D3: No field-level primary-source URL, locator, and independent verification in the submitted CSV.
A4: corpus_master.csv | B4: family | C4: excluded | D4: No field-level primary-source URL, locator, and independent verification in the submitted CSV.
A5: corpus_master.csv | B5: year | C5: excluded | D5: No field-level primary-source URL, locator, and independent verification in the submitted CSV.
A6: corpus_master.csv | B6: primary_group | C6: excluded | D6: No field-level primary-source URL, locator, and independent verification in the submitted CSV.
A7: corpus_master.csv | B7: secondary_labels | C7: excluded | D7: No field-level primary-source URL, locator, and independent verification in the submitted CSV.
A8: corpus_master.csv | B8: wm_role_label | C8: excluded | D8: No field-level primary-source URL, locator, and independent verification in the submitted CSV.
A9: corpus_master.csv | B9: corpus_status | C9: excluded | D9: No field-level primary-source URL, locator, and independent verification in the submitted CSV.
A10: corpus_master.csv | B10: backbone_or_substrate | C10: excluded | D10: No field-level primary-source URL, locator, and independent verification in the submitted CSV.
A11: corpus_master.csv | B11: action_representation | C11: excluded | D11: No field-level primary-source URL, locator, and independent verification in the submitted CSV.
A12: corpus_master.csv | B12: state_space | C12: excluded | D12: No field-level primary-source URL, locator, and independent verification in the submitted CSV.
... A52: data_scaling.csv | B52: note | C52: excluded_or_replaced | D52: Unsupported ratios and estimates were removed; source-backed scope is recorded separately.

Sheet Figures
A1: Publication-ready figures generated from verified-only data
A2: Vector PDFs and 600-dpi PNGs are included separately in the final package.
A4: Scale label | B4: log10(hours) | C4: bound type
A5: ='Verified Data Scale'!B2&" — "&'Verified Data Scale'!C2 -> Cosmos WFM — raw candidate video collection | B5: ='Verified Data Scale'!L2 -> 7.30103 | C5: ='Verified Data Scale'!F2 -> approximate
A6: ='Verified Data Scale'!B3&" — "&'Verified Data Scale'!C3 -> V-JEPA 2 — internet-video pretraining pool | B6: ='Verified Data Scale'!L3 -> 6 | C6: ='Verified Data Scale'!F3 -> lower_bound
A7: ='Verified Data Scale'!B4&" — "&'Verified Data Scale'!C4 -> pi_0 — robot-data pretraining mixture | B7: ='Verified Data Scale'!L4 -> 4 | C7: ='Verified Data Scale'!F4 -> lower_bound
A8: ='Verified Data Scale'!B5&" — "&'Verified Data Scale'!C5 -> Dreamer 4 — VPT gameplay-video pool | B8: ='Verified Data Scale'!L5 -> 3.4050047 | C8: ='Verified Data Scale'!F5 -> exact
A9: ='Verified Data Scale'!B6&" — "&'Verified Data Scale'!C6 -> DROID — full robot-interaction dataset | B9: ='Verified Data Scale'!L6 -> 2.544068 | C9: ='Verified Data Scale'!F6 -> exact
A10: ='Verified Data Scale'!B7&" — "&'Verified Data Scale'!C7 -> Dreamer 4 — paired-action ablation subset | B10: ='Verified Data Scale'!L7 -> 2 | C10: ='Verified Data Scale'!F7 -> exact
A11: ='Verified Data Scale'!B8&" — "&'Verified Data Scale'!C8 -> V-JEPA 2-AC — filtered robot-video subset with end-effector states and derived actions | B11: ='Verified Data Scale'!L8 -> 1.7923917 | C11: ='Verified Data Scale'!F8 -> upper_bound
A23: Task | B23: SIMPLER | C23: World-Gymnast
A24: ='World-Gymnast'!A2 -> Open the drawer | B24: ='World-Gymnast'!C2 -> 34 | C24: ='World-Gymnast'!F2 -> 58
A25: ='World-Gymnast'!A3 -> Close the drawer | B25: ='World-Gymnast'!C3 -> 74 | C25: ='World-Gymnast'!F3 -> 62
A26: ='World-Gymnast'!A4 -> Put the eggplant into the blue sink | B26: ='World-Gymnast'!C4 -> 32 | C26: ='World-Gymnast'!F4 -> 72
A27: ='World-Gymnast'!A5 -> Put the eggplant into the yellow basket | B27: ='World-Gymnast'!C5 -> 40 | C27: ='World-Gymnast'!F5 -> 78

Sheet Plot Index
A1: file | B1: format | C1: resolution | D1: source data | E1: recommended use
A2: verified_data_scale.pdf | B2: Vector PDF | C2: embedded TrueType fonts | D2: Verified Data Scale | E2: Main text L3; preserve scope and bound caveat
A3: verified_data_scale.png | B3: PNG | C3: 600 dpi | D3: Verified Data Scale | E3: Preview or raster-only workflow
A4: verified_world_gymnast_real_robot.pdf | B4: Vector PDF | C4: embedded TrueType fonts | D4: World-Gymnast | E4: Main text or supplement
A5: verified_world_gymnast_real_robot.png | B5: PNG | C5: 600 dpi | D5: World-Gymnast | E5: Preview or raster-only workflow

Sheet Cited Papers
A1: Cited papers and sources
A3: Cited references | C3: =COUNTA(K9:K183) -> 175 | D3: Compiled from the current 29-page draft on 24 September 2026. | F3: Paper citations | G3: =COUNTIFS(G9:G183,"Paper") -> 169
A4: Unresolved decisions | C4: =C3-COUNTIFS(H9:H183,"Include")-COUNTIFS(H9:H183,"Background")-COUNTIFS(H9:H183,"Exclude")-COUNTIFS(H9:H183,"Duplicate") -> 175 | D4: References and years follow the draft. Use the links and metadata notes to check source details. | F4: Other technical sources | G4: =COUNTIFS(G9:G183,"Technical release / software") -> 6
A5: Marked Include | C5: =COUNTIFS(H9:H183,"Include") -> 0 | D5: Choose Include, Background, Exclude or Duplicate in the amber Review decision column.
A6: Figure 3 count | C6: =IF(C4>0,"Not finalized",C5) -> Not finalized | D6: Settle Pending, blank or invalid decisions before using the count for Figure 3. Extend count ranges if adding rows.
A8: Ref. | B8: Year (as cited) | C8: Reference (as cited) | D8: Two-sentence summary | E8: Primary source link | F8: Topic / role | G8: Source type | H8: Review decision | I8: Decision reason | J8: Report ID | K8: Citation key | L8: Metadata notes | M8: Summary basis
A9: 1 | B9: 2023 | C9: B. Zitkovich, T. Yu, S. Xu, P. Xu, T. Xiao, F. Xia, J. Wu, P. Wohlhart, S. Welker, A. Wahid et al., “RT-2: Vision-language-action models transfer web knowledge to robotic control,” in Proc. Conf. Robot Learn. (CoRL), 2023, arXiv:2307.15818. | D9: RT-2 represents robot actions as tokens and co-trains on robotic trajectories and vision-language tasks. It studies how knowledge learned from web data transfers into language-conditioned manipulation. | E9: https://arxiv.org/abs/2307.15818 | F9: VLA/action policy | G9: Paper | H9: Pending | J9: arXiv:2307.15818 | K9: rt2 | M9: Previously primary-source-checked README catalogue and manuscript discussion; no new quantitative claims.
A10: 2 | B10: 2024 | C10: M. J. Kim, K. Pertsch, S. Karamcheti, T. Xiao, A. Balakrishna, S. Nair, R. Rafailov, E. Foster, G. Lam, P. Sanketi et al., “OpenVLA: An open-source vision-language-action model,” in Proc. Conf. Robot Learn. (CoRL), 2024, arXiv:2406.09246. | D10: OpenVLA combines pretrained visual-language representations with autoregressive robot-action prediction in an open model. It provides a generalist manipulation policy that can be adapted to new tasks through fine-tuning. | E10: https://arxiv.org/abs/2406.09246 | F10: VLA/action policy | G10: Paper | H10: Pending | J10: arXiv:2406.09246 | K10: openvla | M10: Previously primary-source-checked README catalogue and manuscript discussion; no new quantitative claims.
A11: 3 | B11: 2024 | C11: Open X-Embodiment Collaboration, “Open X-Embodiment: Robotic learning datasets and RT-X models,” in Proc. IEEE Int. Conf. Robot. Autom. (ICRA), 2024, arXiv:2310.08864. | D11: Open X-Embodiment brings together robot demonstration datasets collected across different embodiments. The accompanying RT-X models examine whether training on this combined data improves transfer between robotic platforms. | E11: https://arxiv.org/abs/2310.08864 | F11: Dataset/benchmark | G11: Paper | H11: Pending | J11: arXiv:2310.08864 | K11: oxe | L11: Hybrid dataset/model report: OXE and RT-X are one cited report; category reflects its dataset role. | M11: Previously primary-source-checked README catalogue and manuscript discussion; no new quantitative claims.
A12: 4 | B12: 2025 | C12: K. Black, N. Brown, D. Driess, A. Esmail, M. Equi, C. Finn, N. Fusai, L. Groom, K. Hausman, B. Ichter et al., “π0: A vision-language-action flow model for general robot control,” in Proc. Robot.: Sci. Syst. (RSS), 2025, arXiv:2410.24164. | D12: The π0 model couples a pretrained vision-language backbone to a flow-matching action expert. It generates continuous action chunks for manipulation across tasks and robot embodiments. | E12: https://arxiv.org/abs/2410.24164 | F12: VLA/action policy | G12: Paper | H12: Pending | J12: arXiv:2410.24164 | K12: pi0 | M12: Previously primary-source-checked README catalogue and manuscript discussion; no new quantitative claims.
A13: 5 | B13: 2025 | C13: J. Bjorck, F. Castañeda, N. Cherniadev, X. Da, R. Ding, L. Fan, Y. Fang, D. Fox, F. Hu, S. Huang et al., “GR00T N1: An open foundation model for generalist humanoid robots,” arXiv preprint, 2025, arXiv:2503.14734. | D13: GR00T N1 combines vision-language interpretation with diffusion-based action generation for humanoid robots. Its dual-system design connects slower semantic processing with continuous control. | E13: https://arxiv.org/abs/2503.14734 | F13: VLA/action policy | G13: Paper | H13: Pending | J13: arXiv:2503.14734 | K13: groot | M13: Previously primary-source-checked README catalogue and manuscript discussion; no new quantitative claims.
A14: 6 | B14: 2025 | C14: Gemini Robotics Team, “Gemini Robotics: Bringing AI into the physical world,” arXiv preprint, 2025, arXiv:2503.20020. | D14: Gemini Robotics extends a Gemini vision-language model to generate robot actions from observations and instructions. The developer-reported study examines manipulation capabilities and transfer across embodiments. | E14: https://arxiv.org/abs/2503.20020 | F14: VLA/action policy | G14: Paper | H14: Pending | J14: arXiv:2503.20020 | K14: geminirobotics | L14: Vendor-authored technical research paper, not reclassified as nonpaper simply because evidence is vendor-reported. | M14: Previously primary-source-checked README catalogue and manuscript discussion; no new quantitative claims.
A15: 7 | B15: 2025 | C15: Figure AI, “Helix: A vision-language-action model for generalist humanoid control,” Figure AI technical blog, , 2025. | D15: Helix combines a slower vision-language component with a faster continuous-action controller for humanoid upper-body manipulation. The cited vendor release describes this dual-system architecture and its demonstrated behaviors. | E15: https://www.figure.ai/news/helix | F15: Vendor technical release | G15: Technical release / software | H15: Pending | J15: https://www.figure.ai/news/helix | K15: helix | M15: Previously primary-source-checked README catalogue and manuscript discussion; no new quantitative claims.
A16: 8 | B16: 2025 | C16: M. J. Kim, C. Finn, and P. Liang, “Fine-tuning vision-languageaction models: Optimizing speed and success,” arXiv preprint, 2025, arXiv:2502.19645. | D16: OpenVLA-OFT studies fine-tuning choices for faster and more successful VLA control. Its recipe uses action chunking and parallel continuous regression instead of sequential action-token decoding. | E16: https://arxiv.org/abs/2502.19645 | F16: Policy training/adaptation method | G16: Paper | H16: Pending | J16: arXiv:2502.19645 | K16: openvlaoft | M16: Previously primary-source-checked README catalogue and manuscript discussion; no new quantitative claims.
A17: 9 | B17: 2025 | C17: S. Fei, S. Wang, J. Shi, Z. Dai, J. Cai, P. Qian, L. Ji, X. He, S. Zhang, Z. Fei et al., “LIBERO-Plus: In-depth robustness analysis of vision-language-action models,” arXiv preprint, 2025, arXiv:2510.13626. | D17: LIBERO-Plus probes manipulation policies with controlled visual, physical-configuration, and instruction perturbations. Its instruction-removal and goal-replacement tests distinguish apparent language robustness from reliable instruction grounding. | E17: https://arxiv.org/abs/2510.13626 | F17: Dataset/benchmark | G17: Paper | H17: Pending | J17: arXiv:2510.13626 | K17: liberoplus | M17: Previously primary-source-checked README catalogue and manuscript discussion; no new quantitative claims.
A18: 10 | B18: 2025 | C18: A. Jain, M. Zhang, K. Arora, W. Chen, M. Torne, M. Z. Irshad, S. Zakharov, Y. Wang, S. Levine, C. Finn et al., “PolaRiS: Scalable real-to-sim evaluations for generalist robot policies,” arXiv preprint, 2025, arXiv:2512.16881. | D18: PolaRiS reconstructs interactive simulation environments from short scans of real scenes for robot-policy evaluation. Paired simulated and physical tests examine how well these evaluations predict real-world performance. | E18: https://arxiv.org/abs/2512.16881 | F18: Dataset/benchmark | G18: Paper | H18: Pending | J18: arXiv:2512.16881 | K18: polaris | L18: Evaluation framework/method paper grouped with benchmark/evaluation sources; not a mere data file. | M18: Primary-source abstract or article and manuscript context; source reviewed 2026-09-24.
A19: 11 | B19: 2026 | C19: H. Li, Y. Zuo, J. Yu, Y. Zhang, Z. Yang, K. Zhang, X. Zhu, Y. Zhang, T. Chen, G. Cui et al., “SimpleVLA-RL: Scaling VLA training via reinforcement learning,” in Proc. Int. Conf. Learn. Representations (ICLR), 2026, arXiv:2509.09674. | D19: SimpleVLA-RL adapts VLA policies through online reinforcement learning with stochastic action-token decoding. It evaluates how interaction changes performance under different demonstration budgets. | E19: https://arxiv.org/abs/2509.09674 | F19: Policy training/adaptation method | G19: Paper | H19: Pending | J19: arXiv:2509.09674 | K19: simplevlarl | M19: Previously primary-source-checked README catalogue and manuscript discussion; no new quantitative claims.
A20: 12 | B20: 2025 | C20: S. Tan, K. Dou, Y. Zhao, and P. Krähenbühl, “Interactive post-training for vision-language-action models,” arXiv preprint, 2025, arXiv:2505.17016. | D20: RIPT-VLA fine-tunes pretrained robot policies through reinforcement learning with sparse task-success rewards. It studies interactive post-training of both lightweight and larger policies under limited supervision. | E20: https://arxiv.org/abs/2505.17016 | F20: Policy training/adaptation method | G20: Paper | H20: Pending | J20: arXiv:2505.17016 | K20: riptvla | M20: Previously primary-source-checked README catalogue and manuscript discussion; no new quantitative claims.
A21: 13 | B21: 2025 | C21: M. Assran, A. Bardes, D. Fan, Q. Garrido, R. Howes, M. Komeili, M. Muckley, A. Rizvi, C. Roberts, K. Sinha et al., “V-JEPA 2: Selfsupervised video models enable understanding, prediction and planning,” arXiv preprint, 2025, arXiv:2506.09985. | D21: V-JEPA 2 learns predictive video representations from action-free video at scale. Its separately adapted V-JEPA 2-AC model predicts action-conditioned latent transitions for planning toward image goals. | E21: https://arxiv.org/abs/2506.09985 | F21: World model/predictive system | G21: Paper | H21: Pending | J21: arXiv:2506.09985 | K21: vjepa2 | M21: Previously primary-source-checked README catalogue and manuscript discussion; no new quantitative claims.
A22: 14 | B22: 2025 | C22: J. Jang, S. Ye, Z. Lin, J. Xiang, J. Bjorck, Y. Fang, F. Hu, S. Huang, K. Kundalia, Y.-C. Lin et al., “DreamGen: Unlocking generalization in robot learning through video world models,” arXiv preprint, 2025, arXiv:2505.12705. | D22: DreamGen generates task-conditioned robot videos and obtains pseudo-action labels through inverse dynamics. The resulting synthetic trajectories augment policy training as an offline data-generation pipeline. | E22: https://arxiv.org/abs/2505.12705 | F22: World model/predictive system | G22: Paper | H22: Pending | J22: arXiv:2505.12705 | K22: dreamgen | M22: Previously primary-source-checked README catalogue and manuscript discussion; no new quantitative claims.
A23: 15 | B23: 2025 | C23: D. Hafner, W. Yan, and T. Lillicrap, “Training agents inside of scalable world models,” arXiv preprint, 2025, arXiv:2509.24527. | D23: Dreamer 4 trains agents inside a scalable video world model learned from offline data. Its main application is Minecraft, while separate ablations examine the amount of action-labeled video required for prediction. | E23: https://arxiv.org/abs/2509.24527 | F23: World model/predictive system | G23: Paper | H23: Pending | J23: arXiv:2509.24527 | K23: dreamer4 | M23: Previously primary-source-checked README catalogue and manuscript discussion; no new quantitative claims.
A24: 16 | B24: 2025 | C24: J. Cen, C. Yu, H. Yuan, Y. Jiang, S. Huang, J. Guo, X. Li, Y. Song, H. Luo, F. Wang et al., “WorldVLA: Towards autoregressive action world model,” arXiv preprint, 2025, arXiv:2506.21539. | D24: WorldVLA uses shared autoregressive modeling for robot actions and future observations. Its predictive-training experiments provide evidence about joint learning without establishing a general advantage for online candidate-action search. | E24: https://arxiv.org/abs/2506.21539 | F24: World model/predictive system | G24: Paper | H24: Pending | J24: arXiv:2506.21539 | K24: worldvla | M24: Previously primary-source-checked README catalogue and manuscript discussion; no new quantitative claims.
A25: 17 | B25: 2026 | C25: M. J. Kim, Y. Gao, T.-Y. Lin, Y.-C. Lin, Y. Ge, G. Lam, P. Liang, S. Song, M.-Y. Liu, C. Finn, and J. Gu, “Cosmos Policy: Fine-tuning video models for visuomotor control and planning,” in Proc. Int. Conf. Learn. Representations (ICLR), 2026, arXiv:2601.16163. | D25: Cosmos Policy adapts a video model to jointly generate actions, future states, and values. It evaluates direct visuomotor execution alongside rollout refinement and candidate selection for planning. | E25: https://arxiv.org/abs/2601.16163 | F25: World model/predictive system | G25: Paper | H25: Pending | J25: arXiv:2601.16163 | K25: cosmospolicy | M25: Previously primary-source-checked README catalogue and manuscript discussion; no new quantitative claims.
A26: 18 | B26: 2026 | C26: Y. Ma, Z. Song, Y. Zhuang, J. Hao, and I. King, “A survey on vision-language-action models for embodied AI,” IEEE Trans. Neural Netw. Learn. Syst, 2026, arXiv:2405.14093. | D26: This survey organizes VLA research into model components, low-level control policies, and high-level task planners. It also reviews datasets, simulators, and benchmarks that support language-conditioned embodied action. | E26: https://arxiv.org/abs/2405.14093 | F26: Survey | G26: Paper | H26: Pending | J26: arXiv:2405.14093 | K26: ma2024survey | M26: Primary-source abstract or article and manuscript context; source reviewed 2026-09-24.
A27: 19 | B27: 2025 | C27: Y. Zhong, F. Bai, S. Cai, X. Huang, Z. Chen, X. Zhang, Y. Wang, S. Guo, T. Guan, K. N. Lui et al., “A survey on vision-language-action models: An action tokenization perspective,” arXiv preprint, 2025, arXiv:2507.01925. | D27: This survey compares VLA systems through the intermediate representations used to express actions. Its tokenization taxonomy spans language, code, affordances, trajectories, goals, latent codes, raw actions, and reasoning. | E27: https://arxiv.org/abs/2507.01925 | F27: Survey | G27: Paper | H27: Pending | J27: arXiv:2507.01925 | K27: zhong2025token | M27: Primary-source abstract or article and manuscript context; source reviewed 2026-09-24.
A28: 20 | B28: 2025 | C28: K. Kawaharazuka, J. Oh, J. Yamada, I. Posner, and Y. Zhu, “Visionlanguage-action models for robotics: A review towards real-world applications,” IEEE Access, vol. 13, pp. 162 467–162 504, 2025. | D28: This review connects VLA architectures and learning methods with the practical requirements of robot deployment. It covers hardware platforms, data collection, augmentation, datasets, and evaluation alongside model design. | E28: https://arxiv.org/abs/2510.07077 | F28: Survey | G28: Paper | H28: Pending | J28: arXiv:2510.07077 | K28: kawaharazuka2025 | M28: Primary-source abstract or article and manuscript context; source reviewed 2026-09-24.
A29: 21 | B29: 2026 | C29: M. U. Din, W. Akram, L. S. Saoud, J. Rosell, and I. Hussain, “Multimodal fusion with vision-language-action models for robotic manipulation: A systematic review,” Information Fusion, vol. 129, p. 104062, 2026. | D29: This systematic review organizes manipulation VLAs by multimodal fusion strategies, architectures, datasets, and evaluation resources. It also develops an agentic outlook in which planners use VLA skills with verification and diagnostic feedback. | E29: https://doi.org/10.1016/j.inffus.2025.104062 | F29: Survey | G29: Paper | H29: Pending | J29: 10.1016/j.inffus.2025.104062 | K29: din2025priorvlasurvey | M29: Published article abstract and agentic-framework discussion, previously checked in the authors institutional repository.
A30: 22 | B30: 2026 | C30: B. Hou, G. Li, J. Jia, T. An, X. Guo, S. Leng, H. Geng, Y. Ze, T. Harada, P. Torr et al., “World model for robot learning: A comprehensive survey,” arXiv preprint, 2026, arXiv:2605.00080. | D30: This survey reviews world models according to their roles in robot-policy learning, planning, simulation, data generation, and evaluation. It relates policy coupling and controllable video prediction to datasets and experimental protocols across embodied domains. | E30: https://arxiv.org/abs/2605.00080 | F30: Survey | G30: Paper | H30: Pending | J30: arXiv:2605.00080 | K30: hou2026wm | M30: Primary-source abstract or article and manuscript context; source reviewed 2026-09-24.
... A41: 33 | B41: 2025 | C41: J. Ding, Y. Zhang, Y. Shang, Y. Zhang, Z. Zong, J. Feng, Y. Yuan, H. Su, N. Li, N. Sukiennik et al., “Understanding world or predicting future? A comprehensive survey of world models,” ACM Computing Surveys, vol. 58, no. 3, pp. 1–38, 2025. | D41: This survey distinguishes world models that construct internal representations from those that simulate future states. It reviews these roles across robotics, autonomous driving, and other domains and identifies open modeling challenges. | E41: https://doi.org/10.1145/3746449 | F41: Survey | G41: Paper | H41: Pending | J41: https://doi.org/10.1145/3746449 | K41: ding2025worldsurvey | M41: Primary-source abstract or article and manuscript context; source reviewed 2026-09-24.
A42: 34 | B42: 2025 | C42: X. Li et al., “A step toward world models: A survey on robotic manipulation,” arXiv preprint, 2025, arXiv:2511.02097. | D42: This survey examines manipulation methods that exhibit world-model capabilities, including approaches not explicitly labeled as world models. It uses their roles in perception, prediction, and control to identify the components needed for broader predictive robotics. | E42: https://arxiv.org/abs/2511.02097 | F42: Survey | G42: Paper | H42: Pending | J42: arXiv:2511.02097 | K42: li2025step | L42: The as-cited reference lists X. Li et al.; the primary source instead identifies Peng-Fei Zhang and colleagues. Citation number, key and as-cited wording are retained for traceability; the author attribution requires correction in the manuscript bibliography. | M42: Primary-source abstract or article and manuscript context; source reviewed 2026-09-24.
A43: 35 | B43: 2025 | C43: Jiang et al., “A survey on vision-language-action models for autonomous driving,” in Proc. IEEE/CVF Int. Conf. Comput. Vis. Workshops (ICCVW), WDFM-AD, 2025. | D43: This survey reviews vision-language-action architectures for autonomous driving, including their progression toward reasoning-centered control. It compares vehicle-domain datasets and evaluation concerns such as safety, instruction following, and explanation quality. | E43: https://openaccess.thecvf.com/content/ICCV2025W/WDFM-AD/html/Jiang_A_Survey_on_Vision-Language-Action_Models_for_Autonomous_Driving_ICCVW_2025_paper.html | F43: Survey | G43: Paper | H43: Pending | J43: https://openaccess.thecvf.com/content/ICCV2025W/WDFM-AD/html/Jiang_A_Survey_on_Vision-Language-Action_Models_for_Autonomous_Driving_ICCVW_2025_paper.html | K43: jiang2025driving | M43: Primary-source abstract or article and manuscript context; source reviewed 2026-09-24.
A44: 36 | B44: 2025 | C44: D. Zhang, J. Sun, C. Hu, X. Wu, Z. Yuan, R. Zhou, F. Shen, and Q. Zhou, “Pure vision language action (VLA) models: A comprehensive survey,” arXiv preprint, 2025, arXiv:2509.19012. | D44: This survey classifies VLA methods into autoregressive, diffusion, reinforcement-learning, hybrid, and specialized approaches. It connects these design choices to application scenarios, datasets, benchmarks, and simulators. | E44: https://arxiv.org/abs/2509.19012 | F44: Survey | G44: Paper | H44: Pending | J44: arXiv:2509.19012 | K44: zhang2025pure | M44: Primary-source abstract or article and manuscript context; source reviewed 2026-09-24.
A45: 37 | B45: 2021 | C45: M. J. Page, J. E. McKenzie, P. M. Bossuyt, I. Boutron, T. C. Hoffmann, C. D. Mulrow, L. Shamseer, J. M. Tetzlaff, E. A. Akl, S. E. Brennan et al., “The PRISMA 2020 statement: An updated guideline for reporting systematic reviews,” BMJ, vol. 372, p. n71, 2021. | D45: The PRISMA 2020 statement provides reporting guidance for systematic reviews through checklists and flow-diagram templates. It supports transparent reporting of searches, selection, synthesis, and limitations rather than certifying that a review was conducted correctly. | E45: https://doi.org/10.1136/bmj.n71 | F45: Methodology | G45: Paper | H45: Pending | J45: https://doi.org/10.1136/bmj.n71 | K45: prisma2020 | M45: Original statement and official PRISMA statement/checklist descriptions; reviewed 2026-09-24.
A46: 38 | B46: 2023 | C46: A. Brohan, N. Brown, J. Carbajal, Y. Chebotar, J. Dabis, C. Finn, K. Gopalakrishnan, K. Hausman, A. Herzog, J. Hsu et al., “RT-1: Robotics transformer for real-world control at scale,” arXiv preprint, 2023, arXiv:2212.06817. | D46: RT-1 maps camera observations and language instructions to discretized robot commands using a transformer policy. It is an early language-conditioned control precursor to later VLA foundation models. | E46: https://arxiv.org/abs/2212.06817 | F46: VLA/action policy | G46: Paper | H46: Pending | J46: arXiv:2212.06817 | K46: rt1 | M46: Previously primary-source-checked README catalogue and manuscript discussion; no new quantitative claims.
A47: 39 | B47: 2023 | C47: Y. Jiang, A. Gupta, Z. Zhang, G. Wang, Y. Dou, Y. Chen, L. Fei-Fei, A. Anandkumar, Y. Zhu, and L. Fan, “VIMA: General robot manipulation with multimodal prompts,” in International Conference on Machine Learning (ICML), 2023, arXiv:2210.03094. | D47: VIMA specifies manipulation tasks using prompts that interleave text and images. A transformer policy converts these multimodal task descriptions and observations into robot actions. | E47: https://arxiv.org/abs/2210.03094 | F47: VLA/action policy | G47: Paper | H47: Pending | J47: arXiv:2210.03094 | K47: vima | M47: Previously primary-source-checked README catalogue and manuscript discussion; no new quantitative claims.
A48: 40 | B48: 2024 | C48: X. Li, M. Liu, H. Zhang, C. Yu, J. Xu, H. Wu, C. Cheang, Y. Jing, W. Zhang, H. Liu et al., “Vision-language foundation models as effective robot imitators,” in Proc. Int. Conf. Learn. Representations (ICLR), 2024, arXiv:2311.01378. | D48: RoboFlamingo adapts a pretrained OpenFlamingo vision-language model for robot imitation learning. An action-prediction interface connects multimodal understanding to language-conditioned manipulation. | E48: https://arxiv.org/abs/2311.01378 | F48: VLA/action policy | G48: Paper | H48: Pending | J48: arXiv:2311.01378 | K48: roboflamingo | M48: Previously primary-source-checked README catalogue and manuscript discussion; no new quantitative claims.
A49: 41 | B49: 2024 | C49: D. Niu, Y. Sharma, G. Biamby, J. Quenum, Y. Bai, B. Shi, T. Darrell, and R. Herzig, “LLARV A: Vision-action instruction tuning enhances robot learning,” in Proc. Conf. Robot Learn. (CoRL), 2024, arXiv:2406.11815. | D49: LLARVA uses vision-action instruction tuning with intermediate two-dimensional visual traces. These traces help align multimodal representations with the robot behaviors learned during adaptation. | E49: https://arxiv.org/abs/2406.11815 | F49: VLA/action policy | G49: Paper | H49: Pending | J49: arXiv:2406.11815 | K49: llarva | M49: Previously primary-source-checked README catalogue and manuscript discussion; no new quantitative claims.
A50: 42 | B50: 2025 | C50: S. Ye, J. Jang, B. Jeon, S. Joo, J. Yang, B. Peng, A. Mandlekar, R. Tan et al., “Latent action pretraining from videos,” in International Conference on Learning Representations (ICLR), 2025, arXiv:2410.11758. | D50: LAPA learns latent action representations from video without ground-truth action labels during pretraining. Robot data subsequently maps the pretrained policy into executable robot actions. | E50: https://arxiv.org/abs/2410.11758 | F50: VLA/action policy | G50: Paper | H50: Pending | J50: arXiv:2410.11758 | K50: lapa | M50: Previously primary-source-checked README catalogue and manuscript discussion; no new quantitative claims.
A51: 43 | B51: 2025 | C51: K. Pertsch, K. Stachowicz, B. Ichter, D. Driess, S. Nair, Q. Vuong, O. Mees, C. Finn, and S. Levine, “FAST: Efficient action tokenization for vision-language-action models,” in Proc. Robot.: Sci. Syst. (RSS), 2025, arXiv:2501.09747. | D51: FAST compresses continuous action chunks into frequency-domain tokens for autoregressive prediction. The π0-FAST policy demonstrates how this representation can support action generation for dexterous control. | E51: https://arxiv.org/abs/2501.09747 | F51: VLA/action policy | G51: Paper | H51: Pending | J51: arXiv:2501.09747 | K51: fast | M51: Previously primary-source-checked README catalogue and manuscript discussion; no new quantitative claims.
A52: 44 | B52: 2025 | C52: Liang et al., “Discrete diffusion VLA: Bringing discrete diffusion to action decoding in vision-language-action policies,” arXiv preprint, 2025, arXiv:2508.20072. | D52: Discrete Diffusion VLA generates discretized action chunks through iterative diffusion-style refinement within a shared transformer. It explores parallel action decoding as an alternative to sequential autoregressive generation. | E52: https://arxiv.org/abs/2508.20072 | F52: VLA/action policy | G52: Paper | H52: Pending | J52: arXiv:2508.20072 | K52: ddvla | M52: Previously primary-source-checked README catalogue and manuscript discussion; no new quantitative claims.
A53: 45 | B53: 2024 | C53: Octo Model Team, D. Ghosh, H. Walke, K. Pertsch, K. Black, O. Mees, S. Dasari, J. Hejna, T. Kreiman, C. Xu et al., “Octo: An open-source generalist robot policy,” in Proc. Robot.: Sci. Syst. (RSS), 2024, arXiv:2405.12213. | D53: Octo is an open generalist robot policy with a diffusion action head and language- or image-goal conditioning. Its adaptation interface accommodates new observation inputs and robot action spaces. | E53: https://arxiv.org/abs/2405.12213 | F53: VLA/action policy | G53: Paper | H53: Pending | J53: arXiv:2405.12213 | K53: octo | M53: Previously primary-source-checked README catalogue and manuscript discussion; no new quantitative claims.
A54: 46 | B54: 2025 | C54: S. Liu, L. Wu, B. Li, H. Tan, H. Chen, Z. Wang, K. Xu, H. Su, and J. Zhu, “RDT-1B: A diffusion foundation model for bimanual manipulation,” arXiv preprint, 2025, arXiv:2410.07864. | D54: RDT-1B uses a diffusion transformer to generate bimanual robot actions conditioned on multimodal inputs. A unified action representation supports learning from robots with different configurations. | E54: https://arxiv.org/abs/2410.07864 | F54: VLA/action policy | G54: Paper | H54: Pending | J54: arXiv:2410.07864 | K54: rdt1b | M54: Previously primary-source-checked README catalogue and manuscript discussion; no new quantitative claims.
... A72: 64 | B72: 2025 | C72: Q. Zhao et al., “CoT-VLA: Visual chain-of-thought reasoning for vision-language-action models,” in Proc. IEEE/CVF Conf. Comput. Vis. Pattern Recognit. (CVPR), 2025, arXiv:2503.22020. | D72: CoT-VLA predicts future images as intermediate visual goals before generating action sequences. This visual chain of thought links prediction to policy execution without itself establishing candidate-action search. | E72: https://arxiv.org/abs/2503.22020 | F72: World model/predictive system | G72: Paper | H72: Pending | J72: arXiv:2503.22020 | K72: cotvla | M72: Previously primary-source-checked README catalogue and manuscript discussion; no new quantitative claims.
A73: 65 | B73: 2025 | C73: M. U. Din, J. Rosell, W. Akram, I. Zaplana, M. A. Roa, L. Seneviratne, and I. Hussain, “Ontology-driven prompt tuning for LLM-based task and motion planning,” Robot. Auton. Syst, 2025. | D73: This framework enriches language-model prompts with ontology-based task knowledge and descriptions of the environment. It uses this knowledge to improve semantic consistency and temporal ordering in task-and-motion plans. | E73: https://arxiv.org/abs/2412.07493v1 | F73: Planning/control context | G73: Paper | H73: Pending | J73: arXiv:2412.07493 | K73: ontollmtamp | L73: The linked arXiv v1 (10 December 2024) matches the supplied title and seven-author list. The as-cited 2025 Robotics and Autonomous Systems entry mixes version metadata: the journal article is ‘Onto-LLM-TAMP: Knowledge-oriented Task and Motion Planning using Large Language Models,’ vol. 200, article 105404 (2026), DOI 10.1016/j.robot.2026.105404, with six authors. The original reference and year are retained as cited; reconcile the intended version before submission. | M73: Primary-source abstract or article and manuscript context; source reviewed 2026-09-24.
A74: 66 | B74: 2022 | C74: M. Shridhar, L. Manuelli, and D. Fox, “Perceiver-Actor: A multi-task transformer for robotic manipulation,” in Proc. Conf. Robot Learn. (CoRL), 2022, arXiv:2209.05451. | D74: PerAct encodes language goals and voxelized RGB-D observations with a Perceiver architecture. It learns discretized six-degree-of-freedom manipulation actions through behavior cloning. | E74: https://arxiv.org/abs/2209.05451 | F74: VLA/action policy | G74: Paper | H74: Pending | J74: arXiv:2209.05451 | K74: peract | M74: Previously primary-source-checked README catalogue and manuscript discussion; no new quantitative claims.
A75: 67 | B75: 2023 | C75: A. Goyal, J. Xu, Y. Guo, V. Blukis, Y.-W. Chao, and D. Fox, “RVT: Robotic view transformer for 3D object manipulation,” in Proc. Conf. Robot Learn. (CoRL), 2023, arXiv:2306.14896. | D75: RVT combines rendered views of a three-dimensional scene with language-goal embeddings in a transformer. The resulting representation supports spatially grounded manipulation from limited demonstrations. | E75: https://arxiv.org/abs/2306.14896 | F75: VLA/action policy | G75: Paper | H75: Pending | J75: arXiv:2306.14896 | K75: rvt | M75: Previously primary-source-checked README catalogue and manuscript discussion; no new quantitative claims.
A76: 68 | B76: 2024 | C76: A. Goyal, V. Blukis, J. Xu, Y. Guo, Y.-W. Chao, and D. Fox, “RVT-2: Learning precise manipulation from few demonstrations,” in Robotics: Science and Systems (RSS), 2024, arXiv:2406.08545. | D76: RVT-2 improves the architecture and execution of language-conditioned multi-view manipulation policies. It emphasizes precise control and efficient learning from few demonstrations. | E76: https://arxiv.org/abs/2406.08545 | F76: VLA/action policy | G76: Paper | H76: Pending | J76: arXiv:2406.08545 | K76: rvt2 | M76: Previously primary-source-checked README catalogue and manuscript discussion; no new quantitative claims.
A77: 69 | B77: 2023 | C77: T. Gervet, Z. Xian, N. Gkanatsios, and K. Fragkiadaki, “Act3D: 3D feature field transformers for multi-task robotic manipulation,” in Conference on Robot Learning (CoRL), 2023, arXiv:2306.17817. | D77: Act3D uses a hierarchical three-dimensional feature field with task-instruction conditioning to predict manipulation actions. Coarse-to-fine spatial sampling concentrates computation where precise action prediction is needed. | E77: https://arxiv.org/abs/2306.17817 | F77: VLA/action policy | G77: Paper | H77: Pending | J77: arXiv:2306.17817 | K77: act3d | M77: Previously primary-source-checked README catalogue and manuscript discussion; no new quantitative claims.
A78: 70 | B78: 2024 | C78: H. Zhen, X. Qiu, P. Chen, J. Yang, X. Yan, Y. Du, Y. Hong, and C. Gan, “3D-VLA: A 3D vision-language-action generative world model,” in Proc. Int. Conf. Mach. Learn. (ICML), 2024, arXiv:2403.09631. | D78: 3D-VLA combines three-dimensional vision-language representations with generation of future observations and robot actions. It connects spatial grounding with predictive policy learning for manipulation. | E78: https://arxiv.org/abs/2403.09631 | F78: World model/predictive system | G78: Paper | H78: Pending | J78: arXiv:2403.09631 | K78: threedvla | M78: Previously primary-source-checked README catalogue and manuscript discussion; no new quantitative claims.
A79: 71 | B79: 2025 | C79: D. Qu, H. Song, Q. Chen, Y. Yao, X. Ye, Y. Ding, Z. Wang, J. Gu, B. Zhao, D. Wang et al., “SpatialVLA: Exploring spatial representations for visual-language-action models,” in Proc. Robot.: Sci. Syst. (RSS), 2025, arXiv:2501.15830. | D79: SpatialVLA uses geometric visual representations and spatially structured action tokens. These representations connect scene geometry with language-conditioned manipulation commands. | E79: https://arxiv.org/abs/2501.15830 | F79: VLA/action policy | G79: Paper | H79: Pending | J79: arXiv:2501.15830 | K79: spatialvla | M79: Previously primary-source-checked README catalogue and manuscript discussion; no new quantitative claims.
A80: 72 | B80: 2025 | C80: Li et al., “PointVLA: Injecting the 3D world into vision-language-action models,” arXiv preprint, 2025, arXiv:2503.07511. | D80: PointVLA injects point-cloud information into pretrained VLA action modules through lightweight adaptation. It gives an existing policy access to three-dimensional geometry for manipulation. | E80: https://arxiv.org/abs/2503.07511 | F80: VLA/action policy | G80: Paper | H80: Pending | J80: arXiv:2503.07511 | K80: pointvla | M80: Previously primary-source-checked README catalogue and manuscript discussion; no new quantitative claims.
A81: 73 | B81: 2024 | C81: Jia et al., “Lift3D foundation policy: Lifting 2D large-scale pretrained models for robust 3D robotic manipulation,” arXiv preprint, 2024, arXiv:2411.18623. | D81: Lift3D adapts pretrained two-dimensional visual features into implicit and explicit three-dimensional manipulation representations. Its reported policy uses point clouds and robot state without language conditioning. | E81: https://arxiv.org/abs/2411.18623 | F81: Planning/control context | G81: Paper | H81: Pending | J81: arXiv:2411.18623 | K81: lift3d | M81: Previously primary-source-checked README catalogue and manuscript discussion; no new quantitative claims.
A82: 74 | B82: 2025 | C82: Yang et al., “FP3: A 3D foundation policy for robotic manipulation,” arXiv preprint, 2025, arXiv:2503.08950. | D82: FP3 pretrains a diffusion-transformer manipulation policy using point clouds, proprioception, and CLIP-encoded instructions. It adapts this language-conditioned three-dimensional policy to downstream tasks. | E82: https://arxiv.org/abs/2503.08950 | F82: VLA/action policy | G82: Paper | H82: Pending | J82: arXiv:2503.08950 | K82: fp3 | M82: Previously primary-source-checked README catalogue and manuscript discussion; no new quantitative claims.
A83: 75 | B83: 2025 | C83: Li et al., “BridgeVLA: Input-output alignment for efficient 3D manipulation learning,” arXiv preprint, 2025, arXiv:2506.07961. [Online]. Available: | D83: BridgeVLA projects three-dimensional observations into multiple image views and predicts spatial action heatmaps. This design aligns visual inputs with the spatial representation of control outputs. | E83: https://arxiv.org/abs/2506.07961 | F83: VLA/action policy | G83: Paper | H83: Pending | J83: arXiv:2506.07961 | K83: bridgevla | M83: Previously primary-source-checked README catalogue and manuscript discussion; no new quantitative claims.
A84: 76 | B84: 2025 | C84: Deng et al., “GraspVLA: A grasping foundation model pre-trained on billion-scale synthetic action data,” arXiv preprint, 2025, arXiv:2505.03233. | D84: GraspVLA combines autoregressive perception with flow-matching action generation for grasping. Its training integrates synthetic robot data with semantic pretraining to support generalizable grasp behavior. | E84: https://arxiv.org/abs/2505.03233 | F84: VLA/action policy | G84: Paper | H84: Pending | J84: arXiv:2505.03233 | K84: graspvla | M84: Previously primary-source-checked README catalogue and manuscript discussion; no new quantitative claims.
A85: 77 | B85: 2025 | C85: Sun et al., “GeoVLA: Empowering 3D representations in vision-language-action models,” arXiv preprint, 2025, arXiv:2508.09071. | D85: GeoVLA fuses image-language representations with point-cloud geometry in an action expert. This spatial interface supplies three-dimensional context for language-conditioned manipulation. | E85: https://arxiv.org/abs/2508.09071 | F85: VLA/action policy | G85: Paper | H85: Pending | J85: arXiv:2508.09071 | K85: geovla | M85: Previously primary-source-checked README catalogue and manuscript discussion; no new quantitative claims.
... A108: 100 | B108: 2025 | C108: NVIDIA GEAR Lab, “GR00T N1.5: An improved open foundation model for generalist humanoid robots,” NVIDIA Research, , 2025. | D108: GR00T N1.5 extends the GR00T humanoid policy family with changes to its architecture and training data. The official release describes future-latent representation alignment as a component of policy learning. | E108: https://research.nvidia.com/labs/gear/gr00t-n1_5/ | F108: Vendor technical release | G108: Technical release / software | H108: Pending | J108: https://research.nvidia.com/labs/gear/gr00t-n1_5/ | K108: grootn15 | M108: Source-checked VLA/action-policy README catalogue (2026-09-23) and surgical manuscript context; no new quantitative claim.
A109: 101 | B109: 2024 | C109: C.-L. Cheang, G. Chen, Y. Jing, T. Kong, H. Li, Y. Li, Y. Liu, H. Wu, J. Xu, Y. Yang et al., “GR-2: A generative video-language-action model with web-scale knowledge for robot manipulation,” arXiv preprint, 2024, arXiv:2410.06158. | D109: GR-2 combines large-scale video pretraining with joint video and action learning for robotic manipulation. Its predictive-policy formulation connects visual knowledge from web video to robot trajectories. | E109: https://arxiv.org/abs/2410.06158 | F109: VLA/action policy | G109: Paper | H109: Pending | J109: arXiv:2410.06158 | K109: gr2 | L109: Vendor-authored technical research paper, not reclassified as nonpaper simply because evidence is vendor-reported. | M109: Source-checked VLA/action-policy README catalogue (2026-09-23) and surgical manuscript context; no new quantitative claim.
A110: 102 | B110: 2025 | C110: Gemini Robotics Team, “Gemini Robotics 1.5: Pushing the frontier of generalist robots with advanced embodied reasoning, thinking, and motion transfer,” arXiv preprint, 2025, arXiv:2510.03342. | D110: Gemini Robotics 1.5 integrates embodied reasoning with action generation in a multi-embodiment policy. The developer report also describes transferring motion knowledge across robot configurations. | E110: https://arxiv.org/abs/2510.03342 | F110: VLA/action policy | G110: Paper | H110: Pending | J110: arXiv:2510.03342 | K110: gemini15 | L110: Vendor-authored technical research paper, not reclassified as nonpaper simply because evidence is vendor-reported. | M110: Source-checked VLA/action-policy README catalogue (2026-09-23) and surgical manuscript context; no new quantitative claim.
A111: 103 | B111: 2024 | C111: Chiang et al., “Mobility VLA: Multimodal instruction navigation with long-context VLMs and topological graphs,” arXiv preprint, 2024, arXiv:2407.07775. | D111: Mobility VLA combines long-context vision-language understanding with topological navigation. Its reported setting concerns multimodal instruction following for navigation, providing context for broader mobile-robot systems. | E111: https://arxiv.org/abs/2407.07775 | F111: Planning/control context | G111: Paper | H111: Pending | J111: arXiv:2407.07775 | K111: mobilityvla | M111: Source-checked VLA/action-policy README catalogue (2026-09-23) and surgical manuscript context; no new quantitative claim.
A112: 104 | B112: 2011 | C112: S. Ross, G. J. Gordon, and J. A. Bagnell, “A reduction of imitation learning and structured prediction to no-regret online learning,” in Proc. Int. Conf. Artif. Intell. Statist. (AISTATS), 2011. | D112: DAgger addresses imitation-learning distribution shift by iteratively collecting expert labels on states encountered by the learner. The paper connects this data-aggregation procedure to no-regret online learning and sequential prediction. | E112: https://proceedings.mlr.press/v15/ross11a/ross11a.pdf | F112: Methodology | G112: Paper | H112: Pending | J112: https://proceedings.mlr.press/v15/ross11a/ross11a.pdf | K112: dagger | M112: Primary-source abstract or official release checked online on 2026-09-24; manuscript context used to identify the cited role.
A113: 105 | B113: 2024 | C113: A. Khazatsky, K. Pertsch, S. Nair, A. Balakrishna, S. Dasari, S. Karamcheti, S. Nasiriany, M. K. Srirama, L. Y. Chen, K. Ellis et al., “DROID: A large-scale in-the-wild robot manipulation dataset,” arXiv preprint, 2024, arXiv:2403.12945. | D113: DROID provides diverse real-world robot manipulation demonstrations collected across environments. It supports research on policy learning and generalization from robot observations and actions. | E113: https://arxiv.org/abs/2403.12945 | F113: Dataset/benchmark | G113: Paper | H113: Pending | J113: arXiv:2403.12945 | K113: droid | M113: Supported by the surgical manuscript discussion and earlier primary-source review notes; qualitative scope retained without new performance claims.
A114: 106 | B114: 2025 | C114: NVIDIA, “Cosmos world foundation model platform for physical AI,” arXiv preprint, 2025, arXiv:2501.03575. | D114: Cosmos provides video tokenization and generative world foundation models for physical-AI development. Action conditioning and robot-control use depend on the particular model and its adaptation. | E114: https://arxiv.org/abs/2501.03575 | F114: World model/predictive system | G114: Paper | H114: Pending | J114: arXiv:2501.03575 | K114: cosmos | M114: Source-checked world-model README catalogue (2026-09-23) and surgical manuscript context; no new quantitative claim.
A115: 107 | B115: 2025 | C115: S. Motamed, L. Culp, K. Swersky, P. Jaini, and R. Geirhos, “Do generative video models understand physical laws?” in Proc. IEEE/CVF Int. Conf. Comput. Vis. (ICCV), 2025, arXiv:2501.09038. | D115: Physics-IQ evaluates physical prediction using paired real videos rather than visual plausibility alone. It supplies evidence about physical consistency in generative video models without directly measuring robot-control success. | E115: https://arxiv.org/abs/2501.09038 | F115: Dataset/benchmark | G115: Paper | H115: Pending | J115: arXiv:2501.09038 | K115: physicsiq | M115: Supported by the surgical manuscript discussion and earlier primary-source review notes; qualitative scope retained without new performance claims.
A116: 108 | B116: 2025 | C116: Li et al., “WorldModelBench: Judging video generation models as world models,” arXiv preprint, 2025, arXiv:2502.20694. | D116: WorldModelBench evaluates instruction-conditioned video generation against physical principles. It assesses properties of generated worlds rather than serving as a direct manipulation-policy success benchmark. | E116: https://arxiv.org/abs/2502.20694 | F116: Dataset/benchmark | G116: Paper | H116: Pending | J116: arXiv:2502.20694 | K116: wmbench | M116: Supported by the surgical manuscript discussion and earlier primary-source review notes; qualitative scope retained without new performance claims.
A117: 109 | B117: 2025 | C117: Z. Huang et al., “VBench-2.0: Advancing video generation benchmark suite for intrinsic faithfulness,” arXiv preprint, 2025, arXiv:2503.21755. | D117: VBench-2.0 evaluates generated video for human fidelity, controllability, creativity, physics, and commonsense. Its metrics target intrinsic faithfulness beyond surface visual plausibility. | E117: https://arxiv.org/abs/2503.21755 | F117: Dataset/benchmark | G117: Paper | H117: Pending | J117: arXiv:2503.21755 | K117: vbench2 | M117: Primary-source abstract or official release checked online on 2026-09-24; manuscript context used to identify the cited role.
A118: 110 | B118: 2024 | C118: X. Li, K. Hsu, J. Gu, K. Pertsch, O. Mees, H. R. Walke, C. Fu, I. Lunawat, I. Sieh, S. Kirmani et al., “Evaluating real-world robot manipulation policies in simulation,” arXiv preprint, 2024, arXiv:2405.05941. | D118: SimplerEnv constructs simulated evaluations intended to correspond to physical robot manipulation settings. It studies how closely policy performance in these simulations tracks real-world evaluation. | E118: https://arxiv.org/abs/2405.05941 | F118: Dataset/benchmark | G118: Paper | H118: Pending | J118: arXiv:2405.05941 | K118: simplerenv | M118: Supported by the surgical manuscript discussion and earlier primary-source review notes; qualitative scope retained without new performance claims.
A119: 111 | B119: 2026 | C119: R. Cui, Z. Zhang, J. Pang, H. Chi, J. Guo, S. Zhang, S. Xie, X. Jin, Y. Mu, J. Yang, G. Yao, X. Zhan, Y.-Q. Zhang, and H. Zhao, “LIBERO-Safety: A comprehensive benchmark for physical and semantic safety in vision-language-action models,” arXiv preprint, 2026, arXiv:2606.23686. | D119: LIBERO-Safety procedurally generates safety-critical manipulation scenarios and accompanying collision-free demonstrations. It evaluates physical and semantic safety properties of embodied policies under task constraints. | E119: https://arxiv.org/abs/2606.23686 | F119: Dataset/benchmark | G119: Paper | H119: Pending | J119: arXiv:2606.23686 | K119: safelibero | M119: Primary-source abstract or official release checked online on 2026-09-24; manuscript context used to identify the cited role.
A120: 112 | B120: 2023 | C120: A. Z. Ren, A. Dixit, A. Bodrova, S. Singh, S. Tu, N. Brown, P. Xu, L. Takayama, F. Xia, J. Varley et al., “Robots that ask for help: Uncertainty alignment for large language model planners,” in Proc. Conf. Robot Learn. (CoRL), 2023, arXiv:2307.01928. | D120: KnowNo uses conformal prediction to calibrate uncertainty in language-model planning. The framework uses this uncertainty to determine when a robot should request human assistance. | E120: https://arxiv.org/abs/2307.01928 | F120: Planning/control context | G120: Paper | H120: Pending | J120: arXiv:2307.01928 | K120: knowno | M120: Source-checked VLA/action-policy README catalogue (2026-09-23) and surgical manuscript context; no new quantitative claim.
A121: 113 | B121: 2019 | C121: A. D. Ames, S. Coogan, M. Egerstedt, G. Notomista, K. Sreenath, and P. Tabuada, “Control barrier functions: Theory and applications,” in Proc. Eur. Control Conf. (ECC), 2019. | D121: This overview explains how control barrier functions can verify and enforce safety properties of dynamical systems. It connects the theory to optimization-based safety-critical controllers and robotic applications. | E121: https://arxiv.org/abs/1903.11199 | F121: Planning/control context | G121: Paper | H121: Pending | J121: arXiv:1903.11199 | K121: cbf | L121: Foundational control survey/tutorial, not a review-methodology reporting guideline. | M121: Primary-source abstract or official release checked online on 2026-09-24; manuscript context used to identify the cited role.
A122: 114 | B122: 2017 | C122: S. Bansal, M. Chen, S. Herbert, and C. J. Tomlin, “Hamilton–Jacobi reachability: A brief overview and recent advances,” in Proc. IEEE Conf. Decis. Control (CDC), 2017. | D122: This tutorial reviews Hamilton-Jacobi reachability for analyzing safety and performance of nonlinear dynamical systems with bounded disturbances. It also discusses numerical tools and approaches to the computational difficulty of high-dimensional systems. | E122: https://arxiv.org/abs/1709.07523 | F122: Planning/control context | G122: Paper | H122: Pending | J122: arXiv:1709.07523 | K122: hjreach | L122: Foundational control survey/tutorial, not a review-methodology reporting guideline. | M122: Primary-source abstract or official release checked online on 2026-09-24; manuscript context used to identify the cited role.
A123: 115 | B123: 2018 | C123: D. Ha and J. Schmidhuber, “World models,” arXiv preprint, 2018, arXiv:1803.10122. | D123: World Models combines a variational image encoder, recurrent latent dynamics, and a compact controller. It demonstrates learning behavior within a learned environment in simulated control tasks. | E123: https://arxiv.org/abs/1803.10122 | F123: World model/predictive system | G123: Paper | H123: Pending | J123: arXiv:1803.10122 | K123: worldmodels2018 | M123: Source-checked world-model README catalogue (2026-09-23) and surgical manuscript context; no new quantitative claim.
A124: 116 | B124: 2019 | C124: D. Hafner, T. Lillicrap, I. Fischer, R. Villegas, D. Ha, H. Lee, and J. Davidson, “Learning latent dynamics for planning from pixels,” in Proc. Int. Conf. Mach. Learn. (ICML), 2019, arXiv:1811.04551. [Online]. Available: | D124: PlaNet learns action-conditioned recurrent latent dynamics from images. It uses model-predictive control to select action sequences by evaluating imagined futures. | E124: https://arxiv.org/abs/1811.04551 | F124: World model/predictive system | G124: Paper | H124: Pending | J124: arXiv:1811.04551 | K124: planet | M124: Source-checked world-model README catalogue (2026-09-23) and surgical manuscript context; no new quantitative claim.
A125: 117 | B125: 2025 | C125: D. Hafner, J. Pasukonis, J. Ba, and T. Lillicrap, “Mastering diverse control tasks through world models,” Nature, vol. 640, pp. 647–653, 2025. | D125: DreamerV3 learns policies and value functions through trajectories imagined in a latent dynamics model. Its training design aims to support varied control domains with a common configuration. | E125: https://arxiv.org/abs/2301.04104 | F125: World model/predictive system | G125: Paper | H125: Pending | J125: arXiv:2301.04104 | K125: dreamerv3 | M125: Source-checked world-model README catalogue (2026-09-23) and surgical manuscript context; no new quantitative claim.
A126: 118 | B126: 2020 | C126: J. Schrittwieser, I. Antonoglou, T. Hubert, K. Simonyan, L. Sifre, S. Schmitt, A. Guez, E. Lockhart, D. Hassabis, T. Graepel et al., “Mastering Atari, Go, chess and shogi by planning with a learned model,” Nature, vol. 588, pp. 604–609, 2020. | D126: MuZero learns latent transitions that predict rewards, values, and action priors for tree search. Its cited demonstrations concern games, with planning-relevant prediction that does not require observation reconstruction. | E126: https://arxiv.org/abs/1911.08265 | F126: World model/predictive system | G126: Paper | H126: Pending | J126: arXiv:1911.08265 | K126: muzero | M126: Source-checked world-model README catalogue (2026-09-23) and surgical manuscript context; no new quantitative claim.
A127: 119 | B127: 2024 | C127: N. Hansen, H. Su, and X. Wang, “TD-MPC2: Scalable, robust world models for continuous control,” in Proc. Int. Conf. Learn. Representations (ICLR), 2024, arXiv:2310.16828. | D127: TD-MPC2 learns task-conditioned latent dynamics and value functions for continuous control. These predictions support model-predictive control across multiple tasks. | E127: https://arxiv.org/abs/2310.16828 | F127: World model/predictive system | G127: Paper | H127: Pending | J127: arXiv:2310.16828 | K127: tdmpc2 | M127: Source-checked world-model README catalogue (2026-09-23) and surgical manuscript context; no new quantitative claim.
A128: 120 | B128: 2023 | C128: Y. Du, S. Yang, B. Dai, H. Dai, O. Nachum, J. B. Tenenbaum, D. Schuurmans, and P. Abbeel, “Learning universal policies via text-guided video generation,” in Adv. Neural Inf. Process. Syst. (NeurIPS), 2023. | D128: UniPi generates a language-conditioned video plan and recovers executable actions through inverse dynamics. The generated plan is a visual action proposal rather than a forward prediction conditioned on supplied candidate robot actions. | E128: https://arxiv.org/abs/2302.00111 | F128: World model/predictive system | G128: Paper | H128: Pending | J128: arXiv:2302.00111 | K128: unipi | M128: Source-checked world-model README catalogue (2026-09-23) and surgical manuscript context; no new quantitative claim.
A129: 121 | B129: 2024 | C129: S. Yang, Y. Du, K. Ghasemipour, J. Tompson, L. Kaelbling, D. Schuurmans, and P. Abbeel, “Learning interactive real-world simulators,” in Proc. Int. Conf. Learn. Representations (ICLR), 2024. | D129: UniSim learns an interactive video simulator that responds to high-level instructions or low-level controls. It supports policy learning and evaluation through generated environment interactions. | E129: https://arxiv.org/abs/2310.06114 | F129: World model/predictive system | G129: Paper | H129: Pending | J129: arXiv:2310.06114 | K129: unisim | M129: Source-checked world-model README catalogue (2026-09-23) and surgical manuscript context; no new quantitative claim.
A130: 122 | B130: 2024 | C130: P.-C. Ko, J. Mao, Y. Du, S.-H. Sun, and J. B. Tenenbaum, “Learning to act from actionless videos through dense correspondences,” in International Conference on Learning Representations (ICLR), 2024, arXiv:2310.08576. | D130: AVDC generates task-directed videos and uses dense correspondences between frames to infer control actions. This connects action-free video demonstrations to robot execution. | E130: https://arxiv.org/abs/2310.08576 | F130: World model/predictive system | G130: Paper | H130: Pending | J130: arXiv:2310.08576 | K130: avdc | M130: Source-checked world-model README catalogue (2026-09-23) and surgical manuscript context; no new quantitative claim.
A131: 123 | B131: 2024 | C131: K. Black, M. Nakamoto, P. Atreya, H. Walke, C. Finn, A. Kumar, and S. Levine, “Zero-shot robotic manipulation with pretrained image-editing diffusion models,” in International Conference on Learning Representations (ICLR), 2024, arXiv:2310.10639. | D131: SuSIE adapts an image-editing diffusion model to propose visual subgoals from an observation and language instruction. A goal-conditioned controller executes the proposed subgoals. | E131: https://arxiv.org/abs/2310.10639 | F131: World model/predictive system | G131: Paper | H131: Pending | J131: arXiv:2310.10639 | K131: susie | M131: Source-checked world-model README catalogue (2026-09-23) and surgical manuscript context; no new quantitative claim.
A132: 124 | B132: 2024 | C132: Y. Du, S. Yang, P. Florence, F. Xia, A. Wahid, B. Ichter, P. Sermanet, T. Yu, P. Abbeel, J. B. Tenenbaum, L. Kaelbling, A. Zeng, and J. Tompson, “Video language planning,” in International Conference on Learning Representations (ICLR), 2024, arXiv:2310.10625. | D132: Video Language Planning searches over language proposals and generated video continuations using vision-language policies and value functions. A goal-conditioned policy executes the resulting visual plan. | E132: https://arxiv.org/abs/2310.10625 | F132: World model/predictive system | G132: Paper | H132: Pending | J132: arXiv:2310.10625 | K132: vlp | M132: Source-checked world-model README catalogue (2026-09-23) and surgical manuscript context; no new quantitative claim.
A133: 125 | B133: 2024 | C133: J. Wu, S. Yin, N. Feng, X. He, D. Li, J. Hao, and M. Long, “iVideoGPT: Interactive VideoGPTs are scalable world models,” in Advances in Neural Information Processing Systems (NeurIPS), 2024, arXiv:2405.15223. [Online]. Available: | D133: iVideoGPT autoregressively models tokenized observations, actions, and rewards. Its learned dynamics support interactive video prediction, visual planning, and model-based reinforcement learning. | E133: https://arxiv.org/abs/2405.15223 | F133: World model/predictive system | G133: Paper | H133: Pending | J133: arXiv:2405.15223 | K133: ivideogpt | M133: Source-checked world-model README catalogue (2026-09-23) and surgical manuscript context; no new quantitative claim.
A134: 126 | B134: 2024 | C134: H. Wu, Y. Jing, C. Cheang, G. Chen, J. Xu, X. Li, M. Liu, H. Li, and T. Kong, “Unleashing large-scale video generative pre-training for visual robot manipulation,” in Proc. Int. Conf. Learn. Representations (ICLR), 2024, arXiv:2312.13139. | D134: GR-1 predicts future images and robot actions from language, visual history, and robot state after video pretraining. This shared predictive-policy training is distinct from searching over supplied candidate actions during deployment. | E134: https://arxiv.org/abs/2312.13139 | F134: VLA/action policy | G134: Paper | H134: Pending | J134: arXiv:2312.13139 | K134: gr1 | M134: Source-checked world-model README catalogue (2026-09-23) and surgical manuscript context; no new quantitative claim.
... A141: 133 | B141: 2026 | C141: J. Chen, K. Wang, K. Chen, S. Chen, F. Gao, W. Tang, Z. Li, W. Liu, Z. Yao, B. Li, Y. Xu, and C. Yu, “LaWAM: Latent world action models for efficient dynamics-aware robot policies,” arXiv preprint, 2026, arXiv:2606.15768. | D141: LaWAM predicts latent visual subgoals and conditions robot-action generation on them. It incorporates predictive information into a policy without requiring dense future-image generation. | E141: https://arxiv.org/abs/2606.15768 | F141: World model/predictive system | G141: Paper | H141: Pending | J141: arXiv:2606.15768 | K141: lawam | M141: Source-checked world-model README catalogue (2026-09-23) and surgical manuscript context; no new quantitative claim.
A142: 134 | B142: 2026 | C142: J. Sun, W. Zhang, Z. Qi, S. Ren, Z. Liu, H. Zhu, G. Sun, X. Jin, and Z. Chen, “VLA-JEPA: Enhancing vision-language-action model with latent world model,” arXiv preprint, 2026, arXiv:2602.10098. | D142: VLA-JEPA pretrains a policy backbone to predict future latent states from current observations. It subsequently adapts an action head, with future frames serving as training targets rather than inputs to the prediction pathway. | E142: https://arxiv.org/abs/2602.10098 | F142: World model/predictive system | G142: Paper | H142: Pending | J142: arXiv:2602.10098 | K142: jepavla | L142: Citation key aliases VLA-JEPA, not a separate JEPA-VLA report. | M142: Source-checked world-model README catalogue (2026-09-23) and surgical manuscript context; no new quantitative claim.
A143: 135 | B143: 2025 | C143: H. Zhen, Q. Sun, H. Zhang, J. Li, S. Zhou, Y. Du, and C. Gan, “TesserAct: Learning 4D embodied world models,” arXiv preprint, 2025, arXiv:2504.20995. | D143: TesserAct predicts RGB, depth, and surface-normal video to represent how three-dimensional scenes evolve. Its multimodal predictions also support learning inverse dynamics for embodied tasks. | E143: https://arxiv.org/abs/2504.20995 | F143: World model/predictive system | G143: Paper | H143: Pending | J143: arXiv:2504.20995 | K143: tesseract | M143: Source-checked world-model README catalogue (2026-09-23) and surgical manuscript context; no new quantitative claim.
A144: 136 | B144: 2025 | C144: G. Lu, B. Jia, P. Li, Y. Chen, Z. Wang, Y. Tang, and S. Huang, “GWM: Towards scalable gaussian world models for robotic manipulation,” in IEEE/CVF International Conference on Computer Vision (ICCV), pp. 9263–9274, 2025. | D144: GWM models action-conditioned manipulation dynamics using Gaussian scene representations. The paper studies this representation for predictive pretraining and learned simulation. | E144: https://arxiv.org/abs/2508.17600 | F144: World model/predictive system | G144: Paper | H144: Pending | J144: arXiv:2508.17600 | K144: gaussianworld | M144: Source-checked world-model README catalogue (2026-09-23) and surgical manuscript context; no new quantitative claim.
A145: 137 | B145: 2024 | C145: G. Lu, S. Zhang, Z. Wang, C. Liu, J. Lu, and Y. Tang, “ManiGaussian: Dynamic gaussian splatting for multi-task robotic manipulation,” in European Conference on Computer Vision (ECCV), 2024, arXiv:2403.08321. [Online]. Available: | D145: ManiGaussian uses dynamic Gaussian representations and future-scene reconstruction as predictive supervision for manipulation. Its language-conditioned policy evaluation is conducted in RLBench simulation. | E145: https://arxiv.org/abs/2403.08321 | F145: World model/predictive system | G145: Paper | H145: Pending | J145: arXiv:2403.08321 | K145: manigaussian | M145: Source-checked world-model README catalogue (2026-09-23) and surgical manuscript context; no new quantitative claim.
A146: 138 | B146: 2024 | C146: T. Zhang, H.-X. Yu, R. Wu, B. Y. Feng, C. Zheng, N. Snavely, J. Wu, and W. T. Freeman, “PhysDreamer: Physics-based interaction with 3D objects via video generation,” in European Conference on Computer Vision (ECCV), 2024, arXiv:2404.13026. | D146: PhysDreamer distills motion information from video generation into physical material estimates and interactive three-dimensional dynamics. Its object-response demonstrations provide context for physical prediction rather than direct evidence of robot task success. | E146: https://arxiv.org/abs/2404.13026 | F146: World model/predictive system | G146: Paper | H146: Pending | J146: arXiv:2404.13026 | K146: physdreamer | M146: Source-checked world-model README catalogue (2026-09-23) and surgical manuscript context; no new quantitative claim.
A147: 139 | B147: 2026 | C147: S. Wu et al., “Tactile-W AM: Touch-aware world action model with tactile asymmetric attention,” arXiv preprint, 2026, arXiv:2606.26663. | D147: Tactile-WAM jointly models visual, tactile, and action information with tactile asymmetric attention. It directs contact information toward action prediction while limiting interference with video generation. | E147: https://arxiv.org/abs/2606.26663 | F147: World model/predictive system | G147: Paper | H147: Pending | J147: arXiv:2606.26663 | K147: dreamtac | L147: Citation key is an alias for Tactile-WAM; not an additional DreamTac report. Recovered title has a spacing error. | M147: Source-checked world-model README catalogue (2026-09-23) and surgical manuscript context; no new quantitative claim. The legacy bib_key dreamtac resolves to Tactile-WAM, not a separate DreamTac model.
A148: 140 | B148: 2026 | C148: J. Zhou, F. Hong, Y. Li, Y. Zhao, Y. Cen, Z. Liu, J. Huang, Z. Chen, R. Zhang, W. Zhu et al., “TouchWorld: A predictive and reactive tactile foundation model for dexterous manipulation,” arXiv preprint, 2026, arXiv:2607.07287. | D148: TouchWorld combines predicted tactile subgoals and visuomotor action chunks with a faster tactile and proprioceptive correction policy. This joins predictive and reactive control for contact-rich dexterous manipulation. | E148: https://arxiv.org/abs/2607.07287 | F148: World model/predictive system | G148: Paper | H148: Pending | J148: arXiv:2607.07287 | K148: touchworld | M148: Source-checked world-model README catalogue (2026-09-23) and surgical manuscript context; no new quantitative claim.
A149: 141 | B149: 2023 | C149: A. Mandlekar, S. Nasiriany, B. Wen, I. Akinola, Y. Narang, L. Fan, Y. Zhu, and D. Fox, “MimicGen: A data generation system for scalable robot learning using human demonstrations,” in Conference on Robot Learning (CoRL), 2023, arXiv:2310.17596. | D149: MimicGen transforms and recombines human demonstrations to generate additional robot trajectories in conventional simulation. It is a demonstration-expansion pipeline rather than a learned environment dynamics model. | E149: https://arxiv.org/abs/2310.17596 | F149: Data-generation method | G149: Paper | H149: Pending | J149: arXiv:2310.17596 | K149: mimicgen | M149: Source-checked world-model README catalogue (2026-09-23) and surgical manuscript context; no new quantitative claim.
A150: 142 | B150: 2025 | C150: Z. Jiang, Y. Xie, K. Lin, Z. Xu, W. Wan, A. Mandlekar, L. Fan, and Y. Zhu, “DexMimicGen: Automated data generation for bimanual dexterous manipulation via imitation learning,” in IEEE International Conference on Robotics and Automation (ICRA), 2025, arXiv:2410.24185. | D150: DexMimicGen extends demonstration-based data generation to bimanual dexterous manipulation in simulation. It handles coordination between manipulators when synthesizing trajectories for imitation learning. | E150: https://arxiv.org/abs/2410.24185 | F150: Data-generation method | G150: Paper | H150: Pending | J150: arXiv:2410.24185 | K150: dexmimicgen | M150: Source-checked world-model README catalogue (2026-09-23) and surgical manuscript context; no new quantitative claim.
A151: 143 | B151: 2025 | C151: Y. Li, Y. Zhu, J. Wen, C. Shen, and Y. Xu, “WorldEval: World model as real-world robot policies evaluator,” arXiv preprint, 2025, arXiv:2505.19017. | D151: WorldEval adapts video generation to action-following simulation using Policy2Vec. It evaluates robot policies through generated rollouts instead of requiring each evaluation to run on hardware. | E151: https://arxiv.org/abs/2505.19017 | F151: World model/predictive system | G151: Paper | H151: Pending | J151: arXiv:2505.19017 | K151: policyeval | M151: Source-checked world-model README catalogue (2026-09-23) and surgical manuscript context; no new quantitative claim.
A152: 144 | B152: 2026 | C152: A. K. Sharma, Y. Sun, N. Lu, Y. Zhang, J. Liu, and S. Yang, “WorldGymnast: Training robots with reinforcement learning in a world model,” arXiv preprint, 2026, arXiv:2602.02454. | D152: World-Gymnast trains robot policies with reinforcement learning inside a learned environment and tests transfer to hardware. Its physical-task comparisons provide evidence about the complete training-and-simulation package rather than isolating every component. | E152: https://arxiv.org/abs/2602.02454 | F152: World model/predictive system | G152: Paper | H152: Pending | J152: arXiv:2602.02454 | K152: sharma2026worldgymnast | M152: Source-checked world-model README catalogue (2026-09-23) and surgical manuscript context; no new quantitative claim.
A153: 145 | B153: 2025 | C153: R. Zheng, J. Wang, S. Reed, J. Bjorck, Y. Fang, F. Hu, J. Jang, K. Kundalia, Z. Lin, L. Magne et al., “FLARE: Robot learning with implicit world modeling,” in Proc. Conf. Robot Learn. (CoRL), 2025, arXiv:2505.15659. | D153: FLARE aligns policy features with embeddings of future observations to incorporate latent prediction into diffusion-based action learning. It also supports co-training with action-free video and is distinct from the reinforcement-learning method FLaRe. | E153: https://arxiv.org/abs/2505.15659 | F153: World model/predictive system | G153: Paper | H153: Pending | J153: arXiv:2505.15659 | K153: flarewm | L153: FLARE predictive alignment paper is distinct from FLaRe RL fine-tuning (flarerl). | M153: Source-checked world-model README catalogue (2026-09-23) and surgical manuscript context; no new quantitative claim.
A154: 146 | B154: 2025 | C154: Zhang et al., “DreamVLA: A vision-language-action model dreamed with comprehensive world knowledge,” arXiv preprint, 2025, arXiv:2507.04447. | D154: DreamVLA forecasts compact dynamic, spatial, and semantic representations. A diffusion-based action generator conditions its manipulation commands on this predicted world information. | E154: https://arxiv.org/abs/2507.04447 | F154: World model/predictive system | G154: Paper | H154: Pending | J154: arXiv:2507.04447 | K154: dreamvla | M154: Source-checked world-model README catalogue (2026-09-23) and surgical manuscript context; no new quantitative claim.
A155: 147 | B155: 2026 | C155: M. Han et al., “Beyond dense futures: World models as structured planners for robotic manipulation,” arXiv preprint, 2026, arXiv:2603.12553. | D155: StructVLA first trains a generative model to predict sparse visual milestones from instructions and observation history. A second training stage adapts that model to action-token prediction conditioned on instructions and interleaved observation–action history. | E155: https://arxiv.org/abs/2603.12553 | F155: World model/predictive system | G155: Paper | H155: Pending | J155: arXiv:2603.12553 | K155: structvla | M155: Source-checked world-model README catalogue (2026-09-23) and surgical manuscript context; no new quantitative claim.
A156: 148 | B156: 2025 | C156: U. Robotics, “UnifoLM-WMA-0: An open-source world-modelaction architecture for humanoid robots,” Unitree open-source release, 2025. | D156: UnifoLM-WMA-0 is Unitree's released framework connecting predictive video dynamics with policy enhancement and learned simulation. The cited source is an official technical release rather than a separately identified peer-reviewed paper. | E156: https://github.com/unitreerobotics/unifolm-world-model-action | F156: Vendor technical release | G156: Technical release / software | H156: Pending | J156: https://github.com/unitreerobotics/unifolm-world-model-action | K156: unifolm | L156: Cited Unitree software/model release; no formal paper identified in current citation. | M156: Source-checked world-model README catalogue (2026-09-23) and surgical manuscript context; no new quantitative claim.
A157: 149 | B157: 2026 | C157: Q. Feng, J. Yu, J. Liu, Y. Jia, Z. Wu, H. Chen, Z. Qian, S. Gu, P. Jia, S. Ma et al., “HarmoWAM: Harmonizing generalizable and precise manipulation via adaptive world action models,” arXiv preprint, 2026, arXiv:2605.10942. | D157: HarmoWAM combines predictive and reactive action experts through adaptive gating. This architecture aims to balance generalization with precise manipulation control. | E157: https://arxiv.org/abs/2605.10942 | F157: World model/predictive system | G157: Paper | H157: Pending | J157: arXiv:2605.10942 | K157: harmowam | M157: Source-checked world-model README catalogue (2026-09-23) and surgical manuscript context; no new quantitative claim.
...

Sheet Current References
A1: Current manuscript references
A3: Cited sources | C3: =COUNTA(B9:B187) -> 179 | D3: References in the manuscript released on 1 October 2026. | G3: Paper sources | H3: =COUNTIFS(G9:G187,"Paper") -> 171
A4: Pending decisions | C4: =COUNTIFS(H9:H187,"Pending") -> 179 | D4: Review decisions are Pending. Citation counts do not establish the 156-report included corpus. | G4: Other technical sources | H4: =COUNTIFS(G9:G187,"Technical release / software") -> 8
D5: The earlier 175-reference Cited Papers sheet is retained unchanged.
A8: Ref. | B8: Citation key | C8: Year (as cited) | D8: Reference (as cited) | E8: Two-sentence summary | F8: Primary source link | G8: Source type | H8: Review decision
A9: 1 | B9: rt2 | C9: 2023 | D9: B. Zitkovich, T. Yu, S. Xu, P. Xu, T. Xiao, F. Xia, J. Wu, P. Wohlhart, S. Welker, A. Wahid et al., “RT-2: Vision-language-action models transfer web knowledge to robotic control,” in Proc. Conf. Robot Learn. (CoRL), 2023, arXiv:2307.15818. | E9: RT-2 represents robot actions as tokens and co-trains on robotic trajectories and vision-language tasks. It studies how knowledge learned from web data transfers into language-conditioned manipulation. | F9: https://arxiv.org/abs/2307.15818 | G9: Paper | H9: Pending
A10: 2 | B10: openvla | C10: 2024 | D10: M. J. Kim, K. Pertsch, S. Karamcheti, T. Xiao, A. Balakrishna, S. Nair, R. Rafailov, E. Foster, G. Lam, P. Sanketi et al., “OpenVLA: An open-source vision-language-action model,” in Proc. Conf. Robot Learn. (CoRL), 2024, arXiv:2406.09246. | E10: OpenVLA combines pretrained visual-language representations with autoregressive robot-action prediction in an open model. It provides a generalist manipulation policy that can be adapted to new tasks through fine-tuning. | F10: https://arxiv.org/abs/2406.09246 | G10: Paper | H10: Pending
A11: 3 | B11: oxe | C11: 2024 | D11: Open X-Embodiment Collaboration, “Open X-Embodiment: Robotic learning datasets and RT-X models,” in Proc. IEEE Int. Conf. Robot. Autom. (ICRA), 2024, arXiv:2310.08864. | E11: Open X-Embodiment brings together robot demonstration datasets collected across different embodiments. The accompanying RT-X models examine whether training on this combined data improves transfer between robotic platforms. | F11: https://arxiv.org/abs/2310.08864 | G11: Paper | H11: Pending
A12: 4 | B12: pi0 | C12: 2025 | D12: K. Black, N. Brown, D. Driess, A. Esmail, M. Equi, C. Finn, N. Fusai, L. Groom, K. Hausman, B. Ichter et al., “π0: A vision-language-action flow model for general robot control,” in Proc. Robot.: Sci. Syst. (RSS), 2025, arXiv:2410.24164. | E12: The π0 model couples a pretrained vision-language backbone to a flow-matching action expert. It generates continuous action chunks for manipulation across tasks and robot embodiments. | F12: https://arxiv.org/abs/2410.24164 | G12: Paper | H12: Pending
A13: 5 | B13: groot | C13: 2025 | D13: J. Bjorck, F. Castañeda, N. Cherniadev, X. Da, R. Ding, L. Fan, Y. Fang, D. Fox, F. Hu, S. Huang et al., “GR00T N1: An open foundation model for generalist humanoid robots,” arXiv preprint arXiv:2503.14734, 2025. | E13: GR00T N1 combines vision-language interpretation with diffusion-based action generation for humanoid robots. Its dual-system design connects slower semantic processing with continuous control. | F13: https://arxiv.org/abs/2503.14734 | G13: Paper | H13: Pending
A14: 6 | B14: geminirobotics | C14: 2025 | D14: Gemini Robotics Team, “Gemini Robotics: Bringing AI into the physical world,” arXiv preprint arXiv:2503.20020, 2025, google DeepMind technical report. | E14: Gemini Robotics extends a Gemini vision-language model to generate robot actions from observations and instructions. The developer-reported study examines manipulation capabilities and transfer across embodiments. | F14: https://arxiv.org/abs/2503.20020 | G14: Paper | H14: Pending
A15: 7 | B15: gemini15 | C15: 2025 | D15: –––, “Gemini Robotics 1.5: Pushing the frontier of generalist robots with advanced embodied reasoning, thinking, and motion transfer,” arXiv preprint arXiv:2510.03342, 2025, google DeepMind technical report. | E15: Gemini Robotics 1.5 integrates embodied reasoning with action generation in a multi-embodiment policy. The developer report also describes transferring motion knowledge across robot configurations. | F15: https://arxiv.org/abs/2510.03342 | G15: Paper | H15: Pending
A16: 8 | B16: openvlaoft | C16: 2025 | D16: M. J. Kim, C. Finn, and P. Liang, “Fine-tuning vision-language-action models: Optimizing speed and success,” arXiv preprint arXiv:2502.19645, 2025. | E16: OpenVLA-OFT studies fine-tuning choices for faster and more successful VLA control. Its recipe uses action chunking and parallel continuous regression instead of sequential action-token decoding. | F16: https://arxiv.org/abs/2502.19645 | G16: Paper | H16: Pending
A17: 9 | B17: liberoplus | C17: 2025 | D17: S. Fei, S. Wang, J. Shi, Z. Dai, J. Cai, P. Qian, L. Ji, X. He, S. Zhang, Z. Fei et al., “LIBERO-Plus: In-depth robustness analysis of vision-language-action models,” arXiv preprint arXiv:2510.13626, 2025. | E17: LIBERO-Plus probes manipulation policies with controlled visual, physical-configuration, and instruction perturbations. Its instruction-removal and goal-replacement tests distinguish apparent language robustness from reliable instruction grounding. | F17: https://arxiv.org/abs/2510.13626 | G17: Paper | H17: Pending
A18: 10 | B18: polaris | C18: 2025 | D18: A. Jain, M. Zhang, K. Arora, W. Chen, M. Torne, M. Z. Irshad, S. Zakharov, Y. Wang, S. Levine, C. Finn et al., “PolaRiS: Scalable real-to-sim evaluations for generalist robot policies,” arXiv preprint arXiv:2512.16881, 2025. | E18: PolaRiS reconstructs interactive simulation environments from short scans of real scenes for robot-policy evaluation. Paired simulated and physical tests examine how well these evaluations predict real-world performance. | F18: https://arxiv.org/abs/2512.16881 | G18: Paper | H18: Pending
A19: 11 | B19: simplevlarl | C19: 2026 | D19: H. Li, Y. Zuo, J. Yu, Y. Zhang, Z. Yang, K. Zhang, X. Zhu, Y. Zhang, T. Chen, G. Cui et al., “SimpleVLA-RL: Scaling VLA training via reinforcement learning,” in Proc. Int. Conf. Learn. Representations (ICLR), 2026, arXiv:2509.09674. | E19: SimpleVLA-RL adapts VLA policies through online reinforcement learning with stochastic action-token decoding. It evaluates how interaction changes performance under different demonstration budgets. | F19: https://arxiv.org/abs/2509.09674 | G19: Paper | H19: Pending
A20: 12 | B20: riptvla | C20: 2025 | D20: S. Tan, K. Dou, Y. Zhao, and P. Krähenbühl, “Interactive post-training for vision-language-action models,” arXiv preprint arXiv:2505.17016, 2025. | E20: RIPT-VLA fine-tunes pretrained robot policies through reinforcement learning with sparse task-success rewards. It studies interactive post-training of both lightweight and larger policies under limited supervision. | F20: https://arxiv.org/abs/2505.17016 | G20: Paper | H20: Pending
... A187: 179 | B187: ego4d | C187: 2022 | D187: K. Grauman, A. Westbury, E. Byrne, Z. Chavis, A. Furnari, R. Girdhar, J. Hamburger et al., “Ego4D: Around the world in 3,000 hours of egocentric video,” in IEEE/CVF Conference on Computer Vision and Pattern Recognition (CVPR), 2022. | E187: Ego4D collects diverse first-person human video and defines benchmarks for egocentric perception. It provides visual experience relevant to representation learning, distinct from demonstrations labelled with robot-control actions. | F187: https://arxiv.org/abs/2110.07058 | G187: Paper | H187: Pending
